Workbook
Name list4: '[1]list of incentive '!$E$3:$E$20

Sheet ASE Target (Spares), FY 21-22
B2: ='ASE Target vs Ach(Spares)(Inpt)'!C2 -> Month | C2: ='ASE Target vs Ach(Spares)(Inpt)'!D2 -> Jul | D2: ='ASE Target vs Ach(Spares)(Inpt)'!E2 -> <<< No input
A4: Sales | C4: Input if any new ASE appointed | G4: No input▼ | H4: input▼(if Require) | I4: input▼(if Require) | J4: input▼(if Require) | K4: input▼(if Require) | L4: input▼(if Require) | M4: input▼(if Require) | N4: input▼(if Require) | O4: input▼(if Require) | P4: input▼(if Require) | Q4: input▼(if Require) | R4: input▼(if Require) | S4: input▼(if Require)
A5: Sl. | B5: Wing | C5: Name | D5: ID | E5: Cell No | F5: Joinning Date | G5: Total Yearly Budget | H5: Jul | I5: Aug | J5: Sep | K5: Oct | L5: Nov | M5: Dec | N5: Jan | O5: Feb | P5: Mar | Q5: Apr | R5: May | S5: Jun
A6: 1 | B6: DSL-DHK | C6: Md. Shohidul | D6: 1418 | E6: `01730046583 | G6: =SUM(H6:S6) -> 2700000 | H6: 500000 | O6: 600000 | P6: 300000 | Q6: 400000 | R6: 400000 | S6: 500000
A7: 2 | B7: DSL-DHK | C7: Sagar Chakrobarti | D7: 2701 | E7: `01708911660 | G7: =SUM(H7:S7) -> 250000 | O7: 250000
A8: 3 | B8: DSL-DHK | C8: Md. Minhazul Islam | D8: 2330 | E8: `01762686570 | G8: =SUM(H8:S8) -> 2000000 | O8: 1000000 | P8: 1000000
A9: 4 | B9: DSL-DHK | C9: Md. Nazmul Hasan Titu | D9: 2913 | E9: `01730046581 | G9: =SUM(H9:S9) -> 1500000 | H9: 250000 | O9: 250000 | P9: 250000 | Q9: 250000 | R9: 250000 | S9: 250000
A10: 5 | B10: DSL-DHK | C10: Md. Zahirul Islam | D10: 2914 | E10: `01755520323 | G10: =SUM(H10:S10) -> 5600000 | H10: 1000000 | O10: 800000 | P10: 800000 | Q10: 1000000 | R10: 1000000 | S10: 1000000
A11: 6 | B11: DSL-DHK | C11: Md. Rakibul Hasan | D11: 2927 | E11: `01730046571 | G11: =SUM(H11:S11) -> 1900000 | H11: 300000 | O11: 400000 | P11: 300000 | Q11: 300000 | R11: 300000 | S11: 300000
A12: 7 | B12: DSL-DHK | C12: Md Ariful Islam | D12: 2699 | E12: `01708154106 | G12: =SUM(H12:S12) -> 2000000 | H12: 400000 | P12: 400000 | Q12: 400000 | R12: 400000 | S12: 400000
A13: 8 | B13: DSL-DHK | C13: Mohammad Jewel Rana | D13: 3002 | E13: `01762686572 | F13: 43893 | G13: =SUM(H13:S13) -> 3600000 | H13: 600000 | O13: 600000 | P13: 600000 | Q13: 600000 | R13: 600000 | S13: 600000
A14: 9 | B14: DSL-DHK | C14: Faysal Ahmed | D14: 3004 | E14: `01730046576 | F14: 43893 | G14: =SUM(H14:S14) -> 3600000 | H14: 600000 | O14: 600000 | P14: 600000 | Q14: 600000 | R14: 600000 | S14: 600000
A15: 10 | B15: DSL-DHK | C15: Rakibul Islam Razib | D15: 3006 | E15: `01730046580 | F15: 43893 | G15: =SUM(H15:S15) -> 1210000 | H15: 250000 | P15: 230000 | Q15: 230000 | R15: 250000 | S15: 250000
A16: 11 | B16: DSL-DHK | C16: Ashraful Islam | D16: 3003 | E16: `01764660814 | F16: 43898 | G16: =SUM(H16:S16) -> 3600000 | H16: 500000 | O16: 800000 | P16: 800000 | Q16: 500000 | R16: 500000 | S16: 500000
A17: 12 | B17: DSL-DHK | C17: Md. Rakibul Islam | D17: 5690 | E17: `01730046571 | F17: 44287 | G17: =SUM(H17:S17) -> 3600000 | H17: 600000 | O17: 600000 | P17: 600000 | Q17: 600000 | R17: 600000 | S17: 600000
A18: 13 | B18: DSL-DHK | C18: Ohid Hasan Saikat | D18: 5691 | E18: `01755520384 | F18: 44287 | G18: =SUM(H18:S18) -> 1900000 | H18: 300000 | O18: 300000 | P18: 400000 | Q18: 300000 | R18: 300000 | S18: 300000
A19: 14 | B19: DSL-DHK | C19: Abdullah Al Mahmud | D19: 5692 | E19: `01740053252 | F19: 44287 | G19: =SUM(H19:S19) -> 2700000 | H19: 400000 | O19: 700000 | P19: 400000 | Q19: 400000 | R19: 400000 | S19: 400000
A20: 15 | B20: DSL-DHK | C20: Apurba Kumar Gain | D20: 5927 | E20: `01730046577 | F20: 44565 | G20: =SUM(H20:S20) -> 1150000 | H20: 230000 | P20: 230000 | Q20: 230000 | R20: 230000 | S20: 230000
A21: 16 | B21: DSL-DHK | C21: Amirul Islam | D21: 5928 | F21: 44565 | G21: =SUM(H21:S21) -> 1250000 | H21: 250000 | O21: 0 | P21: 250000 | Q21: 250000 | R21: 250000 | S21: 250000
A22: 17 | B22: DSL-DHK | C22: Md. Jafor Ikbal | D22: 5929 | F22: 44565 | G22: =SUM(H22:S22) -> 0
A23: 14 | B23: DSL-DHK | C23: Md. Habibur Rahman | D23: 6079 | E23: `01740053252 | F23: 44287 | G23: =SUM(H23:S23) -> 500000 | H23: 250000 | S23: 250000
A24: 15 | B24: DSL-DHK | C24: Ashikur Rahman | D24: 6080 | E24: `01730046577 | F24: 44565 | G24: =SUM(H24:S24) -> 1000000 | H24: 500000 | S24: 500000
A25: 16 | B25: DSL-DHK | C25: Md. Sujon Hossain | D25: 6078 | F25: 44565 | G25: =SUM(H25:S25) -> 1200000 | H25: 600000 | S25: 600000
A26: 15 | B26: DSL-DHK | C26: Md Jiaur Rahman | D26: 0522 | E26: `01730046577 | F26: 44565 | G26: =SUM(H26:S26) -> 4350000 | H26: 900000 | P26: 850000 | Q26: 850000 | R26: 850000 | S26: 900000
A27: 16 | C27: New-2 | F27: 44565 | G27: =SUM(H27:S27) -> 0 | O27: 0
A28: 17 | C28: New-3 | F28: 44565 | G28: =SUM(H28:S28) -> 0
A29: 18 | C29: New-4 | E29: `01733050093 | G29: =SUM(H29:S29) -> 0
A30: 19 | B30: CTG | C30: Sumon Sen | D30: 8041 | G30: =SUM(H30:S30) -> 2250000 | O30: 450000 | P30: 450000 | Q30: 450000 | R30: 450000 | S30: 450000
A31: 20 | B31: CTG | C31: Tapan Barua | D31: 1475 | G31: =SUM(H31:S31) -> 2250000 | O31: 450000 | P31: 450000 | Q31: 450000 | R31: 450000 | S31: 450000
A32: 21 | B32: CTG | C32: Sozol prince | D32: 6076 | G32: =SUM(H32:S32) -> 2250000 | O32: 450000 | P32: 450000 | Q32: 450000 | R32: 450000 | S32: 450000
A33: 16 | C33: New-5 | F33: 44565 | G33: =SUM(H33:S33) -> 0 | O33: 0
A34: 17 | C34: New-6 | F34: 44565 | G34: =SUM(H34:S34) -> 0
H38: Collection Target = | J38: 0.5 | L38: 0.9 | M38: + | N38: 0.5 | P38: 0.9
A39: Collection Target | E39: of Sales | G39: =$G$4 -> No input▼ | H39: =$G$4 -> No input▼ | I39: =$G$4 -> No input▼ | J39: =$G$4 -> No input▼ | K39: =$G$4 -> No input▼ | L39: =$G$4 -> No input▼ | M39: =$G$4 -> No input▼ | N39: =$G$4 -> No input▼ | ... S39: =$G$4 -> No input▼
A40: Sl. | B40: Wing | C40: Name | D40: ID | E40: Cell No | F40: Joinning Date | G40: Total Yearly Budget | H40: Jul | I40: Aug | J40: Sep | K40: Oct | L40: Nov | M40: Dec | N40: Jan | O40: Feb | P40: Mar | Q40: Apr | R40: May | S40: Jun
A41: =A6 -> 1 | B41: =IF(B6=0,"",B6) -> DSL-DHK | C41: =IF(C6=0,"",C6) -> Md. Shohidul | D41: =IF(D6=0,"",D6) -> 1418 | E41: `01730046583 | G41: =SUM(H41:S41) -> 2205000 | H41: =$J$38*H6*$L$38 -> 225000 | I41: =$J$38*H6*$L$38+$N$38*I6*$P$38 -> 225000 | J41: =$J$38*I6*$L$38+$N$38*J6*$P$38 -> 0 | K41: =$J$38*J6*$L$38+$N$38*K6*$P$38 -> 0 | L41: =$J$38*K6*$L$38+$N$38*L6*$P$38 -> 0 | M41: =$J$38*L6*$L$38+$N$38*M6*$P$38 -> 0 | N41: =$J$38*M6*$L$38+$N$38*N6*$P$38 -> 0 | O41: =$J$38*N6*$L$38+$N$38*O6*$P$38 -> 270000 | P41: =$J$38*O6*$L$38+$N$38*P6*$P$38 -> 405000 | ... S41: =$J$38*R6*$L$38+$N$38*S6*$P$38 -> 405000
A42: =A7 -> 2 | B42: =IF(B7=0,"",B7) -> DSL-DHK | C42: =IF(C7=0,"",C7) -> Sagar Chakrobarti | D42: =IF(D7=0,"",D7) -> 2701 | E42: `01708911660 | G42: =SUM(H42:S42) -> 225000 | H42: =$J$38*H7*$L$38 -> 0 | I42: =$J$38*H7*$L$38+$N$38*I7*$P$38 -> 0 | J42: =$J$38*I7*$L$38+$N$38*J7*$P$38 -> 0 | K42: =$J$38*J7*$L$38+$N$38*K7*$P$38 -> 0 | L42: =$J$38*K7*$L$38+$N$38*L7*$P$38 -> 0 | M42: =$J$38*L7*$L$38+$N$38*M7*$P$38 -> 0 | N42: =$J$38*M7*$L$38+$N$38*N7*$P$38 -> 0 | O42: =$J$38*N7*$L$38+$N$38*O7*$P$38 -> 112500 | P42: =$J$38*O7*$L$38+$N$38*P7*$P$38 -> 112500 | ... S42: =$J$38*R7*$L$38+$N$38*S7*$P$38 -> 0
A43: =A8 -> 3 | B43: =IF(B8=0,"",B8) -> DSL-DHK | C43: =IF(C8=0,"",C8) -> Md. Minhazul Islam | D43: =IF(D8=0,"",D8) -> 2330 | E43: `01762686570 | G43: =SUM(H43:S43) -> 1800000 | H43: =$J$38*H8*$L$38 -> 0 | I43: =$J$38*H8*$L$38+$N$38*I8*$P$38 -> 0 | J43: =$J$38*I8*$L$38+$N$38*J8*$P$38 -> 0 | K43: =$J$38*J8*$L$38+$N$38*K8*$P$38 -> 0 | L43: =$J$38*K8*$L$38+$N$38*L8*$P$38 -> 0 | M43: =$J$38*L8*$L$38+$N$38*M8*$P$38 -> 0 | N43: =$J$38*M8*$L$38+$N$38*N8*$P$38 -> 0 | O43: =$J$38*N8*$L$38+$N$38*O8*$P$38 -> 450000 | P43: =$J$38*O8*$L$38+$N$38*P8*$P$38 -> 900000 | ... S43: =$J$38*R8*$L$38+$N$38*S8*$P$38 -> 0
A44: =A9 -> 4 | B44: =IF(B9=0,"",B9) -> DSL-DHK | C44: =IF(C9=0,"",C9) -> Md. Nazmul Hasan Titu | D44: =IF(D9=0,"",D9) -> 2913 | E44: `01816461480 | G44: =SUM(H44:S44) -> 1237500 | H44: =$J$38*H9*$L$38 -> 112500 | I44: =$J$38*H9*$L$38+$N$38*I9*$P$38 -> 112500 | J44: =$J$38*I9*$L$38+$N$38*J9*$P$38 -> 0 | K44: =$J$38*J9*$L$38+$N$38*K9*$P$38 -> 0 | L44: =$J$38*K9*$L$38+$N$38*L9*$P$38 -> 0 | M44: =$J$38*L9*$L$38+$N$38*M9*$P$38 -> 0 | N44: =$J$38*M9*$L$38+$N$38*N9*$P$38 -> 0 | O44: =$J$38*N9*$L$38+$N$38*O9*$P$38 -> 112500 | P44: =$J$38*O9*$L$38+$N$38*P9*$P$38 -> 225000 | ... S44: =$J$38*R9*$L$38+$N$38*S9*$P$38 -> 225000
A45: =A10 -> 5 | B45: =IF(B10=0,"",B10) -> DSL-DHK | C45: =IF(C10=0,"",C10) -> Md. Zahirul Islam | D45: =IF(D10=0,"",D10) -> 2914 | E45: `01870236390 | G45: =SUM(H45:S45) -> 4590000 | H45: =$J$38*H10*$L$38 -> 450000 | I45: =$J$38*H10*$L$38+$N$38*I10*$P$38 -> 450000 | J45: =$J$38*I10*$L$38+$N$38*J10*$P$38 -> 0 | K45: =$J$38*J10*$L$38+$N$38*K10*$P$38 -> 0 | L45: =$J$38*K10*$L$38+$N$38*L10*$P$38 -> 0 | M45: =$J$38*L10*$L$38+$N$38*M10*$P$38 -> 0 | N45: =$J$38*M10*$L$38+$N$38*N10*$P$38 -> 0 | O45: =$J$38*N10*$L$38+$N$38*O10*$P$38 -> 360000 | P45: =$J$38*O10*$L$38+$N$38*P10*$P$38 -> 720000 | ... S45: =$J$38*R10*$L$38+$N$38*S10*$P$38 -> 900000
A46: =A11 -> 6 | B46: =IF(B11=0,"",B11) -> DSL-DHK | C46: =IF(C11=0,"",C11) -> Md. Rakibul Hasan | D46: =IF(D11=0,"",D11) -> 2927 | E46: `01924011300 | G46: =SUM(H46:S46) -> 1575000 | H46: =$J$38*H11*$L$38 -> 135000 | I46: =$J$38*H11*$L$38+$N$38*I11*$P$38 -> 135000 | J46: =$J$38*I11*$L$38+$N$38*J11*$P$38 -> 0 | K46: =$J$38*J11*$L$38+$N$38*K11*$P$38 -> 0 | L46: =$J$38*K11*$L$38+$N$38*L11*$P$38 -> 0 | M46: =$J$38*L11*$L$38+$N$38*M11*$P$38 -> 0 | N46: =$J$38*M11*$L$38+$N$38*N11*$P$38 -> 0 | O46: =$J$38*N11*$L$38+$N$38*O11*$P$38 -> 180000 | P46: =$J$38*O11*$L$38+$N$38*P11*$P$38 -> 315000 | ... S46: =$J$38*R11*$L$38+$N$38*S11*$P$38 -> 270000
A47: =A12 -> 7 | B47: =IF(B12=0,"",B12) -> DSL-DHK | C47: =IF(C12=0,"",C12) -> Md Ariful Islam | D47: =IF(D12=0,"",D12) -> 2699 | E47: `01977786210 | G47: =SUM(H47:S47) -> 1620000 | H47: =$J$38*H12*$L$38 -> 180000 | I47: =$J$38*H12*$L$38+$N$38*I12*$P$38 -> 180000 | J47: =$J$38*I12*$L$38+$N$38*J12*$P$38 -> 0 | K47: =$J$38*J12*$L$38+$N$38*K12*$P$38 -> 0 | L47: =$J$38*K12*$L$38+$N$38*L12*$P$38 -> 0 | M47: =$J$38*L12*$L$38+$N$38*M12*$P$38 -> 0 | N47: =$J$38*M12*$L$38+$N$38*N12*$P$38 -> 0 | O47: =$J$38*N12*$L$38+$N$38*O12*$P$38 -> 0 | P47: =$J$38*O12*$L$38+$N$38*P12*$P$38 -> 180000 | ... S47: =$J$38*R12*$L$38+$N$38*S12*$P$38 -> 360000
A48: =A13 -> 8 | B48: =IF(B13=0,"",B13) -> DSL-DHK | C48: =IF(C13=0,"",C13) -> Mohammad Jewel Rana | D48: =IF(D13=0,"",D13) -> 3002 | E48: `02031561120 | G48: =SUM(H48:S48) -> 2970000 | H48: =$J$38*H13*$L$38 -> 270000 | I48: =$J$38*H13*$L$38+$N$38*I13*$P$38 -> 270000 | J48: =$J$38*I13*$L$38+$N$38*J13*$P$38 -> 0 | K48: =$J$38*J13*$L$38+$N$38*K13*$P$38 -> 0 | L48: =$J$38*K13*$L$38+$N$38*L13*$P$38 -> 0 | M48: =$J$38*L13*$L$38+$N$38*M13*$P$38 -> 0 | N48: =$J$38*M13*$L$38+$N$38*N13*$P$38 -> 0 | O48: =$J$38*N13*$L$38+$N$38*O13*$P$38 -> 270000 | P48: =$J$38*O13*$L$38+$N$38*P13*$P$38 -> 540000 | ... S48: =$J$38*R13*$L$38+$N$38*S13*$P$38 -> 540000
A49: =A14 -> 9 | B49: =IF(B14=0,"",B14) -> DSL-DHK | C49: =IF(C14=0,"",C14) -> Faysal Ahmed | D49: =IF(D14=0,"",D14) -> 3004 | E49: `02085336030 | G49: =SUM(H49:S49) -> 2970000 | H49: =$J$38*H14*$L$38 -> 270000 | I49: =$J$38*H14*$L$38+$N$38*I14*$P$38 -> 270000 | J49: =$J$38*I14*$L$38+$N$38*J14*$P$38 -> 0 | K49: =$J$38*J14*$L$38+$N$38*K14*$P$38 -> 0 | L49: =$J$38*K14*$L$38+$N$38*L14*$P$38 -> 0 | M49: =$J$38*L14*$L$38+$N$38*M14*$P$38 -> 0 | N49: =$J$38*M14*$L$38+$N$38*N14*$P$38 -> 0 | O49: =$J$38*N14*$L$38+$N$38*O14*$P$38 -> 270000 | P49: =$J$38*O14*$L$38+$N$38*P14*$P$38 -> 540000 | ... S49: =$J$38*R14*$L$38+$N$38*S14*$P$38 -> 540000
A50: =A15 -> 10 | B50: =IF(B15=0,"",B15) -> DSL-DHK | C50: =IF(C15=0,"",C15) -> Rakibul Islam Razib | D50: =IF(D15=0,"",D15) -> 3006 | E50: `02139110940 | G50: =SUM(H50:S50) -> 976500 | H50: =$J$38*H15*$L$38 -> 112500 | I50: =$J$38*H15*$L$38+$N$38*I15*$P$38 -> 112500 | J50: =$J$38*I15*$L$38+$N$38*J15*$P$38 -> 0 | K50: =$J$38*J15*$L$38+$N$38*K15*$P$38 -> 0 | L50: =$J$38*K15*$L$38+$N$38*L15*$P$38 -> 0 | M50: =$J$38*L15*$L$38+$N$38*M15*$P$38 -> 0 | N50: =$J$38*M15*$L$38+$N$38*N15*$P$38 -> 0 | O50: =$J$38*N15*$L$38+$N$38*O15*$P$38 -> 0 | P50: =$J$38*O15*$L$38+$N$38*P15*$P$38 -> 103500 | ... S50: =$J$38*R15*$L$38+$N$38*S15*$P$38 -> 225000
A51: =A16 -> 11 | B51: =IF(B16=0,"",B16) -> DSL-DHK | C51: =IF(C16=0,"",C16) -> Ashraful Islam | D51: =IF(D16=0,"",D16) -> 3003 | E51: `02192885850 | G51: =SUM(H51:S51) -> 3015000 | H51: =$J$38*H16*$L$38 -> 225000 | I51: =$J$38*H16*$L$38+$N$38*I16*$P$38 -> 225000 | J51: =$J$38*I16*$L$38+$N$38*J16*$P$38 -> 0 | K51: =$J$38*J16*$L$38+$N$38*K16*$P$38 -> 0 | L51: =$J$38*K16*$L$38+$N$38*L16*$P$38 -> 0 | M51: =$J$38*L16*$L$38+$N$38*M16*$P$38 -> 0 | N51: =$J$38*M16*$L$38+$N$38*N16*$P$38 -> 0 | O51: =$J$38*N16*$L$38+$N$38*O16*$P$38 -> 360000 | P51: =$J$38*O16*$L$38+$N$38*P16*$P$38 -> 720000 | ... S51: =$J$38*R16*$L$38+$N$38*S16*$P$38 -> 450000
A52: =A17 -> 12 | B52: =IF(B17=0,"",B17) -> DSL-DHK | C52: =IF(C17=0,"",C17) -> Md. Rakibul Islam | D52: =IF(D17=0,"",D17) -> 5690 | E52: `02246660760 | G52: =SUM(H52:S52) -> 2970000 | H52: =$J$38*H17*$L$38 -> 270000 | I52: =$J$38*H17*$L$38+$N$38*I17*$P$38 -> 270000 | J52: =$J$38*I17*$L$38+$N$38*J17*$P$38 -> 0 | K52: =$J$38*J17*$L$38+$N$38*K17*$P$38 -> 0 | L52: =$J$38*K17*$L$38+$N$38*L17*$P$38 -> 0 | M52: =$J$38*L17*$L$38+$N$38*M17*$P$38 -> 0 | N52: =$J$38*M17*$L$38+$N$38*N17*$P$38 -> 0 | O52: =$J$38*N17*$L$38+$N$38*O17*$P$38 -> 270000 | P52: =$J$38*O17*$L$38+$N$38*P17*$P$38 -> 540000 | ... S52: =$J$38*R17*$L$38+$N$38*S17*$P$38 -> 540000
... A69: =A34 -> 17 | B69: =IF(B34=0,"",B34) | C69: =IF(C34=0,"",C34) -> New-6 | D69: =IF(D34=0,"",D34) | E69: `03160834230 | G69: =SUM(H69:S69) -> 0 | H69: =$J$38*H34*$L$38 -> 0 | I69: =$J$38*H34*$L$38+$N$38*I34*$P$38 -> 0 | J69: =$J$38*I34*$L$38+$N$38*J34*$P$38 -> 0 | K69: =$J$38*J34*$L$38+$N$38*K34*$P$38 -> 0 | L69: =$J$38*K34*$L$38+$N$38*L34*$P$38 -> 0 | M69: =$J$38*L34*$L$38+$N$38*M34*$P$38 -> 0 | N69: =$J$38*M34*$L$38+$N$38*N34*$P$38 -> 0 | O69: =$J$38*N34*$L$38+$N$38*O34*$P$38 -> 0 | P69: =$J$38*O34*$L$38+$N$38*P34*$P$38 -> 0 | ... S69: =$J$38*R34*$L$38+$N$38*S34*$P$38 -> 0

Sheet Sheet1
E1: 2701 | F1: 250000 | G1: =VLOOKUP(E1,$K$3:$L$26,2,FALSE) -> 178 | H1: 0
E2: 2330 | F2: 2000000 | G2: =VLOOKUP(E2,$K$3:$L$26,2,FALSE) -> 179 | H2: 0
E3: 2913 | F3: 1500000 | G3: =VLOOKUP(E3,$K$3:$L$26,2,FALSE) -> 180 | H3: 250000 | K3: 1418 | L3: 177 | M3: Md. Shohidul
E4: 2914 | F4: 5600000 | G4: =VLOOKUP(E4,$K$3:$L$26,2,FALSE) -> 181 | H4: 1000000 | K4: 2701 | L4: 178 | M4: Sagar Chakrobarti
E5: 2927 | F5: 1900000 | G5: =VLOOKUP(E5,$K$3:$L$26,2,FALSE) -> 182 | H5: 300000 | K5: 2330 | L5: 179 | M5: Md. Minhazul Islam
E6: 2699 | F6: 2000000 | G6: =VLOOKUP(E6,$K$3:$L$26,2,FALSE) -> 183 | H6: 400000 | K6: 2913 | L6: 180 | M6: Md. Nazmul Hasan Titu
E7: 3002 | F7: 3600000 | G7: =VLOOKUP(E7,$K$3:$L$26,2,FALSE) -> 184 | H7: 600000 | K7: 2914 | L7: 181 | M7: Md. Zahirul Islam
E8: 3004 | F8: 3600000 | G8: =VLOOKUP(E8,$K$3:$L$26,2,FALSE) -> 185 | H8: 600000 | K8: 2927 | L8: 182 | M8: Md. Rakibul Hasan
E9: 3006 | F9: 1210000 | G9: =VLOOKUP(E9,$K$3:$L$26,2,FALSE) -> 186 | H9: 250000 | K9: 2699 | L9: 183 | M9: Md Ariful Islam
E10: 3003 | F10: 3600000 | G10: =VLOOKUP(E10,$K$3:$L$26,2,FALSE) -> 187 | H10: 500000 | K10: 3002 | L10: 184 | M10: Mohammad Jewel Rana
E11: 5690 | F11: 3600000 | G11: =VLOOKUP(E11,$K$3:$L$26,2,FALSE) -> 188 | H11: 600000 | K11: 3004 | L11: 185 | M11: Faysal Ahmed
E12: 5691 | F12: 1900000 | G12: =VLOOKUP(E12,$K$3:$L$26,2,FALSE) -> 189 | H12: 300000 | K12: 3006 | L12: 186 | M12: Rakibul Islam Razib
E13: 5692 | F13: 2700000 | G13: =VLOOKUP(E13,$K$3:$L$26,2,FALSE) -> 190 | H13: 400000 | K13: 3003 | L13: 187 | M13: Ashraful Islam
E14: 5927 | F14: 1150000 | G14: =VLOOKUP(E14,$K$3:$L$26,2,FALSE) -> 191 | H14: 230000 | K14: 5690 | L14: 188 | M14: Md. Rakibul Islam
... E19: 6078 | F19: 1200000 | G19: =VLOOKUP(E19,$K$3:$L$26,2,FALSE) -> 198 | H19: 600000 | K19: 5929 | L19: 193 | M19: Md. Jafor Ikbal
E20: 0522 | F20: 4350000 | G20: =VLOOKUP(E20,$K$3:$L$26,2,FALSE) -> 203 | H20: 900000 | K20: 8041 | L20: 194 | M20: Sumon Sen
E21: 8041 | F21: 2250000 | G21: =VLOOKUP(E21,$K$3:$L$26,2,FALSE) -> 194 | H21: 0 | K21: 1475 | L21: 195 | M21: Tapan Barua
E22: 1475 | F22: 2250000 | G22: =VLOOKUP(E22,$K$3:$L$26,2,FALSE) -> 195 | H22: 0 | K22: 6076 | L22: 196 | M22: Sozol Prince
E23: 6076 | F23: 2250000 | G23: =VLOOKUP(E23,$K$3:$L$26,2,FALSE) -> 196 | H23: 0 | K23: 6080 | L23: 197 | M23: Ashikur Rahman
K24: 6078 | L24: 198 | M24: Md. Sujon Hossain
K25: 6079 | L25: 199 | M25: Md. Habibur Rahman
K26: 0522 | L26: 203 | M26: Md Jiaur Rahman

Sheet Upload
A1: ID | B1: BU | C1: ASEUID | D1: MonthYearName | E1: TargetType | F1: StartDate | G1: EndDate | H1: TargetAmount | I1: AchievedPerc | J1: AchievedAmount | K1: NewContract | L1: RenewContract | M1: UserID | N1: EntryDateTime | O1: HostName
A2: 1001 | B2: 2 | C2: 177 | D2: FY 2022-23 | E2: 2 | F2: 44743 | G2: 45107 | H2: 2700000 | I2: 0 | J2: 25000 | K2: 0 | L2: 0 | M2: 160 | N2: 44805.706 | O2: 127.0.0.1
A3: 1002 | B3: 2 | C3: 178 | D3: FY 2022-24 | E3: 2 | F3: 44743 | G3: 45107 | H3: 250000 | I3: 0 | J3: 25000 | K3: 0 | L3: 0 | M3: 160 | N3: 44805.706 | O3: 127.0.0.1
A4: 1003 | B4: 2 | C4: 179 | D4: FY 2022-25 | E4: 2 | F4: 44743 | G4: 45107 | H4: 2000000 | I4: 0 | J4: 25000 | K4: 0 | L4: 0 | M4: 160 | N4: 44805.706 | O4: 127.0.0.1
A5: 1004 | B5: 2 | C5: 180 | D5: FY 2022-26 | E5: 2 | F5: 44743 | G5: 45107 | H5: 1500000 | I5: 0 | J5: 25000 | K5: 0 | L5: 0 | M5: 160 | N5: 44805.706 | O5: 127.0.0.1
A6: 1005 | B6: 2 | C6: 181 | D6: FY 2022-27 | E6: 2 | F6: 44743 | G6: 45107 | H6: 5600000 | I6: 0 | J6: 25000 | K6: 0 | L6: 0 | M6: 160 | N6: 44805.706 | O6: 127.0.0.1
A7: 1006 | B7: 2 | C7: 182 | D7: FY 2022-28 | E7: 2 | F7: 44743 | G7: 45107 | H7: 1900000 | I7: 0 | J7: 25000 | K7: 0 | L7: 0 | M7: 160 | N7: 44805.706 | O7: 127.0.0.1
A8: 1007 | B8: 2 | C8: 183 | D8: FY 2022-29 | E8: 2 | F8: 44743 | G8: 45107 | H8: 2000000 | I8: 0 | J8: 25000 | K8: 0 | L8: 0 | M8: 160 | N8: 44805.706 | O8: 127.0.0.1
A9: 1008 | B9: 2 | C9: 184 | D9: FY 2022-30 | E9: 2 | F9: 44743 | G9: 45107 | H9: 3600000 | I9: 0 | J9: 25000 | K9: 0 | L9: 0 | M9: 160 | N9: 44805.706 | O9: 127.0.0.1
A10: 1009 | B10: 2 | C10: 185 | D10: FY 2022-31 | E10: 2 | F10: 44743 | G10: 45107 | H10: 3600000 | I10: 0 | J10: 25000 | K10: 0 | L10: 0 | M10: 160 | N10: 44805.706 | O10: 127.0.0.1
A11: 1010 | B11: 2 | C11: 186 | D11: FY 2022-32 | E11: 2 | F11: 44743 | G11: 45107 | H11: 1210000 | I11: 0 | J11: 25000 | K11: 0 | L11: 0 | M11: 160 | N11: 44805.706 | O11: 127.0.0.1
A12: 1011 | B12: 2 | C12: 187 | D12: FY 2022-33 | E12: 2 | F12: 44743 | G12: 45107 | H12: 3600000 | I12: 0 | J12: 25000 | K12: 0 | L12: 0 | M12: 160 | N12: 44805.706 | O12: 127.0.0.1
A13: 1012 | B13: 2 | C13: 188 | D13: FY 2022-34 | E13: 2 | F13: 44743 | G13: 45107 | H13: 3600000 | I13: 0 | J13: 25000 | K13: 0 | L13: 0 | M13: 160 | N13: 44805.706 | O13: 127.0.0.1
... A49: 1048 | B49: 2 | C49: 196 | D49: July, 2022 | E49: 1 | F49: 44743 | G49: 44773 | H49: 0 | I49: 1 | J49: 0 | K49: 0 | L49: 0 | M49: 160 | N49: 44807.047 | O49: 127.0.0.1

Sheet ASE Target vs Ach(Spares)(Inpt)
C2: ='ASE Ach(Lube Oil Sales)'!B2 -> Month | D2: ='ASE Ach(Lube Oil Sales)'!C2 -> Jul | E2: ='ASE Ach(Lube Oil Sales)'!D2 -> <<< No input
B4: Sales (Spares) | G4: input▼ | J4: input▼ | M4: input▼ | P4: input▼ | S4: input▼ | V4: input▼ | Y4: input▼ | AB4: input▼ | AE4: input▼ | AH4: input▼ | AK4: input▼ | AN4: input▼
B5: ='ASE Target (Spares), FY 21-22'!A5 -> Sl. | C5: ='ASE Target (Spares), FY 21-22'!B5 -> Wing | D5: ='ASE Target (Spares), FY 21-22'!C5 -> Name | E5: ='ASE Target (Spares), FY 21-22'!D5 -> ID | F5: Jul | I5: Aug | L5: Sep | O5: Oct | R5: Nov | U5: Dec | X5: Jan | AA5: Feb | AD5: Mar | AG5: Apr | AJ5: May | AM5: Jun | AP5: Total (Jul-May)
F6: Target | G6: Ach | H6: Ach (%) | I6: Target | J6: Ach | K6: Ach (%) | L6: Target | M6: Ach | N6: Ach (%) | O6: Target | P6: Ach | Q6: Ach (%) | R6: Target | S6: Ach | T6: Ach (%) | U6: Target | V6: Ach | W6: Ach (%) | X6: Target | Y6: Ach | Z6: Ach (%) | AA6: Target | AB6: Ach | AC6: Ach (%) | AD6: Target | AE6: Ach | AF6: Ach (%) | AG6: Target | AH6: Ach | AI6: Ach (%) | AJ6: Target | AK6: Ach | AL6: Ach (%) | AM6: Target | AN6: Ach | AO6: Ach (%) | AP6: Target | AQ6: Ach | AR6: Ach (%)
B7: ='ASE Target (Spares), FY 21-22'!A6 -> 1 | C7: =IF('ASE Target (Spares), FY 21-22'!B6=0,"",'ASE Target (Spares), FY 21-22'!B6) -> DSL-DHK | D7: =IF('ASE Target (Spares), FY 21-22'!C6=0,"",'ASE Target (Spares), FY 21-22'!C6) -> Md. Shohidul | E7: =IF('ASE Target (Spares), FY 21-22'!D6=0,"",'ASE Target (Spares), FY 21-22'!D6) -> 1418 | F7: =IFERROR(VLOOKUP(D7,'ASE Target (Spares), FY 21-22'!$C$5:$H$39,6,0),"") -> 500000 | G7: 1547635 | H7: =IFERROR(G7/F7,"") -> 3.09527 | I7: =IFERROR(VLOOKUP(D7,'ASE Target (Spares), FY 21-22'!$C$5:$I$39,7,0),"") -> 0 | K7: =IFERROR(J7/I7,"") | L7: =IFERROR(VLOOKUP(D7,'ASE Target (Spares), FY 21-22'!$C$5:$J$39,8,0),"") -> 0 | N7: =IFERROR(M7/L7,"") | O7: =IFERROR(VLOOKUP(D7,'ASE Target (Spares), FY 21-22'!$C$5:$K$39,9,0),"") -> 0 | Q7: =IFERROR(P7/O7,"") | R7: =IFERROR(VLOOKUP(D7,'ASE Target (Spares), FY 21-22'!$C$5:$L$39,10,0),"") -> 0 | T7: =IFERROR(S7/R7,"") | U7: =IFERROR(VLOOKUP(D7,'ASE Target (Spares), FY 21-22'!$C$5:$M$39,11,0),"") -> 0 | W7: =IFERROR(V7/U7,"") | X7: =IFERROR(VLOOKUP(D7,'ASE Target (Spares), FY 21-22'!$C$5:$N$39,12,0),"") -> 0 | Z7: =IFERROR(Y7/X7,"") | AA7: =IFERROR(VLOOKUP(D7,'ASE Target (Spares), FY 21-22'!$C$5:$O$39,13,0),"") -> 600000 | AC7: =IFERROR(AB7/AA7,"") -> 0 | AD7: =IFERROR(VLOOKUP(D7,'ASE Target (Spares), FY 21-22'!$C$5:$P$39,14,0),"") -> 300000 | AF7: =IFERROR(AE7/AD7,"") -> 0 | AG7: =IFERROR(VLOOKUP(D7,'ASE Target (Spares), FY 21-22'!$C$5:$Q$39,15,0),"") -> 400000 | AI7: =IFERROR(AH7/AG7,"") -> 0 | AJ7: =IFERROR(VLOOKUP(D7,'ASE Target (Spares), FY 21-22'!$C$5:$R$39,16,0),"") -> 400000 | AL7: =IFERROR(AK7/AJ7,"") -> 0 | AM7: =IFERROR(VLOOKUP(D7,'ASE Target (Spares), FY 21-22'!$C$5:$S$39,17,0),"") -> 500000 | AO7: =IFERROR(AN7/AM7,"") -> 0 | AP7: =IFERROR(F7+I7+L7+O7+R7+U7+X7+AA7+AD7+AG7+AJ7+AM7,"") -> 2700000 | AQ7: =IFERROR(G7+J7+M7+P7+S7+V7+Y7+AB7+AE7+AH7+AK7+AN7,"") -> 1547635 | AR7: =IFERROR(AQ7/AP7,"") -> 0.57319815
B8: ='ASE Target (Spares), FY 21-22'!A7 -> 2 | C8: =IF('ASE Target (Spares), FY 21-22'!B7=0,"",'ASE Target (Spares), FY 21-22'!B7) -> DSL-DHK | D8: =IF('ASE Target (Spares), FY 21-22'!C7=0,"",'ASE Target (Spares), FY 21-22'!C7) -> Sagar Chakrobarti | E8: =IF('ASE Target (Spares), FY 21-22'!D7=0,"",'ASE Target (Spares), FY 21-22'!D7) -> 2701 | F8: =IFERROR(VLOOKUP(D8,'ASE Target (Spares), FY 21-22'!$C$5:$H$39,6,0),"") -> 0 | H8: =IFERROR(G8/F8,"") | I8: =IFERROR(VLOOKUP(D8,'ASE Target (Spares), FY 21-22'!$C$5:$I$39,7,0),"") -> 0 | K8: =IFERROR(J8/I8,"") | L8: =IFERROR(VLOOKUP(D8,'ASE Target (Spares), FY 21-22'!$C$5:$J$39,8,0),"") -> 0 | N8: =IFERROR(M8/L8,"") | O8: =IFERROR(VLOOKUP(D8,'ASE Target (Spares), FY 21-22'!$C$5:$K$39,9,0),"") -> 0 | Q8: =IFERROR(P8/O8,"") | R8: =IFERROR(VLOOKUP(D8,'ASE Target (Spares), FY 21-22'!$C$5:$L$39,10,0),"") -> 0 | T8: =IFERROR(S8/R8,"") | U8: =IFERROR(VLOOKUP(D8,'ASE Target (Spares), FY 21-22'!$C$5:$M$39,11,0),"") -> 0 | W8: =IFERROR(V8/U8,"") | X8: =IFERROR(VLOOKUP(D8,'ASE Target (Spares), FY 21-22'!$C$5:$N$39,12,0),"") -> 0 | Z8: =IFERROR(Y8/X8,"") | AA8: =IFERROR(VLOOKUP(D8,'ASE Target (Spares), FY 21-22'!$C$5:$O$39,13,0),"") -> 250000 | AC8: =IFERROR(AB8/AA8,"") -> 0 | AD8: =IFERROR(VLOOKUP(D8,'ASE Target (Spares), FY 21-22'!$C$5:$P$39,14,0),"") -> 0 | AF8: =IFERROR(AE8/AD8,"") | AG8: =IFERROR(VLOOKUP(D8,'ASE Target (Spares), FY 21-22'!$C$5:$Q$39,15,0),"") -> 0 | AI8: =IFERROR(AH8/AG8,"") | AJ8: =IFERROR(VLOOKUP(D8,'ASE Target (Spares), FY 21-22'!$C$5:$R$39,16,0),"") -> 0 | AL8: =IFERROR(AK8/AJ8,"") | AM8: =IFERROR(VLOOKUP(D8,'ASE Target (Spares), FY 21-22'!$C$5:$S$39,17,0),"") -> 0 | AO8: =IFERROR(AN8/AM8,"") | AP8: =IFERROR(F8+I8+L8+O8+R8+U8+X8+AA8+AD8+AG8+AJ8+AM8,"") -> 250000 | AQ8: =IFERROR(G8+J8+M8+P8+S8+V8+Y8+AB8+AE8+AH8+AK8+AN8,"") -> 0 | AR8: =IFERROR(AQ8/AP8,"") -> 0
B9: ='ASE Target (Spares), FY 21-22'!A8 -> 3 | C9: =IF('ASE Target (Spares), FY 21-22'!B8=0,"",'ASE Target (Spares), FY 21-22'!B8) -> DSL-DHK | D9: =IF('ASE Target (Spares), FY 21-22'!C8=0,"",'ASE Target (Spares), FY 21-22'!C8) -> Md. Minhazul Islam | E9: =IF('ASE Target (Spares), FY 21-22'!D8=0,"",'ASE Target (Spares), FY 21-22'!D8) -> 2330 | F9: =IFERROR(VLOOKUP(D9,'ASE Target (Spares), FY 21-22'!$C$5:$H$39,6,0),"") -> 0 | H9: =IFERROR(G9/F9,"") | I9: =IFERROR(VLOOKUP(D9,'ASE Target (Spares), FY 21-22'!$C$5:$I$39,7,0),"") -> 0 | K9: =IFERROR(J9/I9,"") | L9: =IFERROR(VLOOKUP(D9,'ASE Target (Spares), FY 21-22'!$C$5:$J$39,8,0),"") -> 0 | N9: =IFERROR(M9/L9,"") | O9: =IFERROR(VLOOKUP(D9,'ASE Target (Spares), FY 21-22'!$C$5:$K$39,9,0),"") -> 0 | Q9: =IFERROR(P9/O9,"") | R9: =IFERROR(VLOOKUP(D9,'ASE Target (Spares), FY 21-22'!$C$5:$L$39,10,0),"") -> 0 | T9: =IFERROR(S9/R9,"") | U9: =IFERROR(VLOOKUP(D9,'ASE Target (Spares), FY 21-22'!$C$5:$M$39,11,0),"") -> 0 | W9: =IFERROR(V9/U9,"") | X9: =IFERROR(VLOOKUP(D9,'ASE Target (Spares), FY 21-22'!$C$5:$N$39,12,0),"") -> 0 | Z9: =IFERROR(Y9/X9,"") | AA9: =IFERROR(VLOOKUP(D9,'ASE Target (Spares), FY 21-22'!$C$5:$O$39,13,0),"") -> 1000000 | AC9: =IFERROR(AB9/AA9,"") -> 0 | AD9: =IFERROR(VLOOKUP(D9,'ASE Target (Spares), FY 21-22'!$C$5:$P$39,14,0),"") -> 1000000 | AF9: =IFERROR(AE9/AD9,"") -> 0 | AG9: =IFERROR(VLOOKUP(D9,'ASE Target (Spares), FY 21-22'!$C$5:$Q$39,15,0),"") -> 0 | AI9: =IFERROR(AH9/AG9,"") | AJ9: =IFERROR(VLOOKUP(D9,'ASE Target (Spares), FY 21-22'!$C$5:$R$39,16,0),"") -> 0 | AL9: =IFERROR(AK9/AJ9,"") | AM9: =IFERROR(VLOOKUP(D9,'ASE Target (Spares), FY 21-22'!$C$5:$S$39,17,0),"") -> 0 | AO9: =IFERROR(AN9/AM9,"") | AP9: =IFERROR(F9+I9+L9+O9+R9+U9+X9+AA9+AD9+AG9+AJ9+AM9,"") -> 2000000 | AQ9: =IFERROR(G9+J9+M9+P9+S9+V9+Y9+AB9+AE9+AH9+AK9+AN9,"") -> 0 | AR9: =IFERROR(AQ9/AP9,"") -> 0
B10: ='ASE Target (Spares), FY 21-22'!A9 -> 4 | C10: =IF('ASE Target (Spares), FY 21-22'!B9=0,"",'ASE Target (Spares), FY 21-22'!B9) -> DSL-DHK | D10: =IF('ASE Target (Spares), FY 21-22'!C9=0,"",'ASE Target (Spares), FY 21-22'!C9) -> Md. Nazmul Hasan Titu | E10: =IF('ASE Target (Spares), FY 21-22'!D9=0,"",'ASE Target (Spares), FY 21-22'!D9) -> 2913 | F10: =IFERROR(VLOOKUP(D10,'ASE Target (Spares), FY 21-22'!$C$5:$H$39,6,0),"") -> 250000 | G10: 709063 | H10: =IFERROR(G10/F10,"") -> 2.836252 | I10: =IFERROR(VLOOKUP(D10,'ASE Target (Spares), FY 21-22'!$C$5:$I$39,7,0),"") -> 0 | K10: =IFERROR(J10/I10,"") | L10: =IFERROR(VLOOKUP(D10,'ASE Target (Spares), FY 21-22'!$C$5:$J$39,8,0),"") -> 0 | N10: =IFERROR(M10/L10,"") | O10: =IFERROR(VLOOKUP(D10,'ASE Target (Spares), FY 21-22'!$C$5:$K$39,9,0),"") -> 0 | Q10: =IFERROR(P10/O10,"") | R10: =IFERROR(VLOOKUP(D10,'ASE Target (Spares), FY 21-22'!$C$5:$L$39,10,0),"") -> 0 | T10: =IFERROR(S10/R10,"") | U10: =IFERROR(VLOOKUP(D10,'ASE Target (Spares), FY 21-22'!$C$5:$M$39,11,0),"") -> 0 | W10: =IFERROR(V10/U10,"") | X10: =IFERROR(VLOOKUP(D10,'ASE Target (Spares), FY 21-22'!$C$5:$N$39,12,0),"") -> 0 | Z10: =IFERROR(Y10/X10,"") | AA10: =IFERROR(VLOOKUP(D10,'ASE Target (Spares), FY 21-22'!$C$5:$O$39,13,0),"") -> 250000 | AC10: =IFERROR(AB10/AA10,"") -> 0 | AD10: =IFERROR(VLOOKUP(D10,'ASE Target (Spares), FY 21-22'!$C$5:$P$39,14,0),"") -> 250000 | AF10: =IFERROR(AE10/AD10,"") -> 0 | AG10: =IFERROR(VLOOKUP(D10,'ASE Target (Spares), FY 21-22'!$C$5:$Q$39,15,0),"") -> 250000 | AI10: =IFERROR(AH10/AG10,"") -> 0 | AJ10: =IFERROR(VLOOKUP(D10,'ASE Target (Spares), FY 21-22'!$C$5:$R$39,16,0),"") -> 250000 | AL10: =IFERROR(AK10/AJ10,"") -> 0 | AM10: =IFERROR(VLOOKUP(D10,'ASE Target (Spares), FY 21-22'!$C$5:$S$39,17,0),"") -> 250000 | AO10: =IFERROR(AN10/AM10,"") -> 0 | AP10: =IFERROR(F10+I10+L10+O10+R10+U10+X10+AA10+AD10+AG10+AJ10+AM10,"") -> 1500000 | AQ10: =IFERROR(G10+J10+M10+P10+S10+V10+Y10+AB10+AE10+AH10+AK10+AN10,"") -> 709063 | AR10: =IFERROR(AQ10/AP10,"") -> 0.47270867
B11: ='ASE Target (Spares), FY 21-22'!A10 -> 5 | C11: =IF('ASE Target (Spares), FY 21-22'!B10=0,"",'ASE Target (Spares), FY 21-22'!B10) -> DSL-DHK | D11: =IF('ASE Target (Spares), FY 21-22'!C10=0,"",'ASE Target (Spares), FY 21-22'!C10) -> Md. Zahirul Islam | E11: =IF('ASE Target (Spares), FY 21-22'!D10=0,"",'ASE Target (Spares), FY 21-22'!D10) -> 2914 | F11: =IFERROR(VLOOKUP(D11,'ASE Target (Spares), FY 21-22'!$C$5:$H$39,6,0),"") -> 1000000 | G11: 764379 | H11: =IFERROR(G11/F11,"") -> 0.764379 | I11: =IFERROR(VLOOKUP(D11,'ASE Target (Spares), FY 21-22'!$C$5:$I$39,7,0),"") -> 0 | K11: =IFERROR(J11/I11,"") | L11: =IFERROR(VLOOKUP(D11,'ASE Target (Spares), FY 21-22'!$C$5:$J$39,8,0),"") -> 0 | N11: =IFERROR(M11/L11,"") | O11: =IFERROR(VLOOKUP(D11,'ASE Target (Spares), FY 21-22'!$C$5:$K$39,9,0),"") -> 0 | Q11: =IFERROR(P11/O11,"") | R11: =IFERROR(VLOOKUP(D11,'ASE Target (Spares), FY 21-22'!$C$5:$L$39,10,0),"") -> 0 | T11: =IFERROR(S11/R11,"") | U11: =IFERROR(VLOOKUP(D11,'ASE Target (Spares), FY 21-22'!$C$5:$M$39,11,0),"") -> 0 | W11: =IFERROR(V11/U11,"") | X11: =IFERROR(VLOOKUP(D11,'ASE Target (Spares), FY 21-22'!$C$5:$N$39,12,0),"") -> 0 | Z11: =IFERROR(Y11/X11,"") | AA11: =IFERROR(VLOOKUP(D11,'ASE Target (Spares), FY 21-22'!$C$5:$O$39,13,0),"") -> 800000 | AC11: =IFERROR(AB11/AA11,"") -> 0 | AD11: =IFERROR(VLOOKUP(D11,'ASE Target (Spares), FY 21-22'!$C$5:$P$39,14,0),"") -> 800000 | AF11: =IFERROR(AE11/AD11,"") -> 0 | AG11: =IFERROR(VLOOKUP(D11,'ASE Target (Spares), FY 21-22'!$C$5:$Q$39,15,0),"") -> 1000000 | AI11: =IFERROR(AH11/AG11,"") -> 0 | AJ11: =IFERROR(VLOOKUP(D11,'ASE Target (Spares), FY 21-22'!$C$5:$R$39,16,0),"") -> 1000000 | AL11: =IFERROR(AK11/AJ11,"") -> 0 | AM11: =IFERROR(VLOOKUP(D11,'ASE Target (Spares), FY 21-22'!$C$5:$S$39,17,0),"") -> 1000000 | AO11: =IFERROR(AN11/AM11,"") -> 0 | AP11: =IFERROR(F11+I11+L11+O11+R11+U11+X11+AA11+AD11+AG11+AJ11+AM11,"") -> 5600000 | AQ11: =IFERROR(G11+J11+M11+P11+S11+V11+Y11+AB11+AE11+AH11+AK11+AN11,"") -> 764379 | AR11: =IFERROR(AQ11/AP11,"") -> 0.13649625
B12: ='ASE Target (Spares), FY 21-22'!A11 -> 6 | C12: =IF('ASE Target (Spares), FY 21-22'!B11=0,"",'ASE Target (Spares), FY 21-22'!B11) -> DSL-DHK | D12: =IF('ASE Target (Spares), FY 21-22'!C11=0,"",'ASE Target (Spares), FY 21-22'!C11) -> Md. Rakibul Hasan | E12: =IF('ASE Target (Spares), FY 21-22'!D11=0,"",'ASE Target (Spares), FY 21-22'!D11) -> 2927 | F12: =IFERROR(VLOOKUP(D12,'ASE Target (Spares), FY 21-22'!$C$5:$H$39,6,0),"") -> 300000 | G12: 1061650 | H12: =IFERROR(G12/F12,"") -> 3.5388333 | I12: =IFERROR(VLOOKUP(D12,'ASE Target (Spares), FY 21-22'!$C$5:$I$39,7,0),"") -> 0 | K12: =IFERROR(J12/I12,"") | L12: =IFERROR(VLOOKUP(D12,'ASE Target (Spares), FY 21-22'!$C$5:$J$39,8,0),"") -> 0 | N12: =IFERROR(M12/L12,"") | O12: =IFERROR(VLOOKUP(D12,'ASE Target (Spares), FY 21-22'!$C$5:$K$39,9,0),"") -> 0 | Q12: =IFERROR(P12/O12,"") | R12: =IFERROR(VLOOKUP(D12,'ASE Target (Spares), FY 21-22'!$C$5:$L$39,10,0),"") -> 0 | T12: =IFERROR(S12/R12,"") | U12: =IFERROR(VLOOKUP(D12,'ASE Target (Spares), FY 21-22'!$C$5:$M$39,11,0),"") -> 0 | W12: =IFERROR(V12/U12,"") | X12: =IFERROR(VLOOKUP(D12,'ASE Target (Spares), FY 21-22'!$C$5:$N$39,12,0),"") -> 0 | Z12: =IFERROR(Y12/X12,"") | AA12: =IFERROR(VLOOKUP(D12,'ASE Target (Spares), FY 21-22'!$C$5:$O$39,13,0),"") -> 400000 | AC12: =IFERROR(AB12/AA12,"") -> 0 | AD12: =IFERROR(VLOOKUP(D12,'ASE Target (Spares), FY 21-22'!$C$5:$P$39,14,0),"") -> 300000 | AF12: =IFERROR(AE12/AD12,"") -> 0 | AG12: =IFERROR(VLOOKUP(D12,'ASE Target (Spares), FY 21-22'!$C$5:$Q$39,15,0),"") -> 300000 | AI12: =IFERROR(AH12/AG12,"") -> 0 | AJ12: =IFERROR(VLOOKUP(D12,'ASE Target (Spares), FY 21-22'!$C$5:$R$39,16,0),"") -> 300000 | AL12: =IFERROR(AK12/AJ12,"") -> 0 | AM12: =IFERROR(VLOOKUP(D12,'ASE Target (Spares), FY 21-22'!$C$5:$S$39,17,0),"") -> 300000 | AO12: =IFERROR(AN12/AM12,"") -> 0 | AP12: =IFERROR(F12+I12+L12+O12+R12+U12+X12+AA12+AD12+AG12+AJ12+AM12,"") -> 1900000 | AQ12: =IFERROR(G12+J12+M12+P12+S12+V12+Y12+AB12+AE12+AH12+AK12+AN12,"") -> 1061650 | AR12: =IFERROR(AQ12/AP12,"") -> 0.55876316
B13: ='ASE Target (Spares), FY 21-22'!A12 -> 7 | C13: =IF('ASE Target (Spares), FY 21-22'!B12=0,"",'ASE Target (Spares), FY 21-22'!B12) -> DSL-DHK | D13: =IF('ASE Target (Spares), FY 21-22'!C12=0,"",'ASE Target (Spares), FY 21-22'!C12) -> Md Ariful Islam | E13: =IF('ASE Target (Spares), FY 21-22'!D12=0,"",'ASE Target (Spares), FY 21-22'!D12) -> 2699 | F13: =IFERROR(VLOOKUP(D13,'ASE Target (Spares), FY 21-22'!$C$5:$H$39,6,0),"") -> 400000 | H13: =IFERROR(G13/F13,"") -> 0 | I13: =IFERROR(VLOOKUP(D13,'ASE Target (Spares), FY 21-22'!$C$5:$I$39,7,0),"") -> 0 | K13: =IFERROR(J13/I13,"") | L13: =IFERROR(VLOOKUP(D13,'ASE Target (Spares), FY 21-22'!$C$5:$J$39,8,0),"") -> 0 | N13: =IFERROR(M13/L13,"") | O13: =IFERROR(VLOOKUP(D13,'ASE Target (Spares), FY 21-22'!$C$5:$K$39,9,0),"") -> 0 | Q13: =IFERROR(P13/O13,"") | R13: =IFERROR(VLOOKUP(D13,'ASE Target (Spares), FY 21-22'!$C$5:$L$39,10,0),"") -> 0 | T13: =IFERROR(S13/R13,"") | U13: =IFERROR(VLOOKUP(D13,'ASE Target (Spares), FY 21-22'!$C$5:$M$39,11,0),"") -> 0 | W13: =IFERROR(V13/U13,"") | X13: =IFERROR(VLOOKUP(D13,'ASE Target (Spares), FY 21-22'!$C$5:$N$39,12,0),"") -> 0 | Z13: =IFERROR(Y13/X13,"") | AA13: =IFERROR(VLOOKUP(D13,'ASE Target (Spares), FY 21-22'!$C$5:$O$39,13,0),"") -> 0 | AC13: =IFERROR(AB13/AA13,"") | AD13: =IFERROR(VLOOKUP(D13,'ASE Target (Spares), FY 21-22'!$C$5:$P$39,14,0),"") -> 400000 | AF13: =IFERROR(AE13/AD13,"") -> 0 | AG13: =IFERROR(VLOOKUP(D13,'ASE Target (Spares), FY 21-22'!$C$5:$Q$39,15,0),"") -> 400000 | AI13: =IFERROR(AH13/AG13,"") -> 0 | AJ13: =IFERROR(VLOOKUP(D13,'ASE Target (Spares), FY 21-22'!$C$5:$R$39,16,0),"") -> 400000 | AL13: =IFERROR(AK13/AJ13,"") -> 0 | AM13: =IFERROR(VLOOKUP(D13,'ASE Target (Spares), FY 21-22'!$C$5:$S$39,17,0),"") -> 400000 | AO13: =IFERROR(AN13/AM13,"") -> 0 | AP13: =IFERROR(F13+I13+L13+O13+R13+U13+X13+AA13+AD13+AG13+AJ13+AM13,"") -> 2000000 | AQ13: =IFERROR(G13+J13+M13+P13+S13+V13+Y13+AB13+AE13+AH13+AK13+AN13,"") -> 0 | AR13: =IFERROR(AQ13/AP13,"") -> 0
B14: ='ASE Target (Spares), FY 21-22'!A13 -> 8 | C14: =IF('ASE Target (Spares), FY 21-22'!B13=0,"",'ASE Target (Spares), FY 21-22'!B13) -> DSL-DHK | D14: =IF('ASE Target (Spares), FY 21-22'!C13=0,"",'ASE Target (Spares), FY 21-22'!C13) -> Mohammad Jewel Rana | E14: =IF('ASE Target (Spares), FY 21-22'!D13=0,"",'ASE Target (Spares), FY 21-22'!D13) -> 3002 | F14: =IFERROR(VLOOKUP(D14,'ASE Target (Spares), FY 21-22'!$C$5:$H$39,6,0),"") -> 600000 | G14: 437175 | H14: =IFERROR(G14/F14,"") -> 0.728625 | I14: =IFERROR(VLOOKUP(D14,'ASE Target (Spares), FY 21-22'!$C$5:$I$39,7,0),"") -> 0 | K14: =IFERROR(J14/I14,"") | L14: =IFERROR(VLOOKUP(D14,'ASE Target (Spares), FY 21-22'!$C$5:$J$39,8,0),"") -> 0 | N14: =IFERROR(M14/L14,"") | O14: =IFERROR(VLOOKUP(D14,'ASE Target (Spares), FY 21-22'!$C$5:$K$39,9,0),"") -> 0 | Q14: =IFERROR(P14/O14,"") | R14: =IFERROR(VLOOKUP(D14,'ASE Target (Spares), FY 21-22'!$C$5:$L$39,10,0),"") -> 0 | T14: =IFERROR(S14/R14,"") | U14: =IFERROR(VLOOKUP(D14,'ASE Target (Spares), FY 21-22'!$C$5:$M$39,11,0),"") -> 0 | W14: =IFERROR(V14/U14,"") | X14: =IFERROR(VLOOKUP(D14,'ASE Target (Spares), FY 21-22'!$C$5:$N$39,12,0),"") -> 0 | Z14: =IFERROR(Y14/X14,"") | AA14: =IFERROR(VLOOKUP(D14,'ASE Target (Spares), FY 21-22'!$C$5:$O$39,13,0),"") -> 600000 | AC14: =IFERROR(AB14/AA14,"") -> 0 | AD14: =IFERROR(VLOOKUP(D14,'ASE Target (Spares), FY 21-22'!$C$5:$P$39,14,0),"") -> 600000 | AF14: =IFERROR(AE14/AD14,"") -> 0 | AG14: =IFERROR(VLOOKUP(D14,'ASE Target (Spares), FY 21-22'!$C$5:$Q$39,15,0),"") -> 600000 | AI14: =IFERROR(AH14/AG14,"") -> 0 | AJ14: =IFERROR(VLOOKUP(D14,'ASE Target (Spares), FY 21-22'!$C$5:$R$39,16,0),"") -> 600000 | AL14: =IFERROR(AK14/AJ14,"") -> 0 | AM14: =IFERROR(VLOOKUP(D14,'ASE Target (Spares), FY 21-22'!$C$5:$S$39,17,0),"") -> 600000 | AO14: =IFERROR(AN14/AM14,"") -> 0 | AP14: =IFERROR(F14+I14+L14+O14+R14+U14+X14+AA14+AD14+AG14+AJ14+AM14,"") -> 3600000 | AQ14: =IFERROR(G14+J14+M14+P14+S14+V14+Y14+AB14+AE14+AH14+AK14+AN14,"") -> 437175 | AR14: =IFERROR(AQ14/AP14,"") -> 0.1214375
B15: ='ASE Target (Spares), FY 21-22'!A14 -> 9 | C15: =IF('ASE Target (Spares), FY 21-22'!B14=0,"",'ASE Target (Spares), FY 21-22'!B14) -> DSL-DHK | D15: =IF('ASE Target (Spares), FY 21-22'!C14=0,"",'ASE Target (Spares), FY 21-22'!C14) -> Faysal Ahmed | E15: =IF('ASE Target (Spares), FY 21-22'!D14=0,"",'ASE Target (Spares), FY 21-22'!D14) -> 3004 | F15: =IFERROR(VLOOKUP(D15,'ASE Target (Spares), FY 21-22'!$C$5:$H$39,6,0),"") -> 600000 | G15: 505895 | H15: =IFERROR(G15/F15,"") -> 0.84315833 | I15: =IFERROR(VLOOKUP(D15,'ASE Target (Spares), FY 21-22'!$C$5:$I$39,7,0),"") -> 0 | K15: =IFERROR(J15/I15,"") | L15: =IFERROR(VLOOKUP(D15,'ASE Target (Spares), FY 21-22'!$C$5:$J$39,8,0),"") -> 0 | N15: =IFERROR(M15/L15,"") | O15: =IFERROR(VLOOKUP(D15,'ASE Target (Spares), FY 21-22'!$C$5:$K$39,9,0),"") -> 0 | Q15: =IFERROR(P15/O15,"") | R15: =IFERROR(VLOOKUP(D15,'ASE Target (Spares), FY 21-22'!$C$5:$L$39,10,0),"") -> 0 | T15: =IFERROR(S15/R15,"") | U15: =IFERROR(VLOOKUP(D15,'ASE Target (Spares), FY 21-22'!$C$5:$M$39,11,0),"") -> 0 | W15: =IFERROR(V15/U15,"") | X15: =IFERROR(VLOOKUP(D15,'ASE Target (Spares), FY 21-22'!$C$5:$N$39,12,0),"") -> 0 | Z15: =IFERROR(Y15/X15,"") | AA15: =IFERROR(VLOOKUP(D15,'ASE Target (Spares), FY 21-22'!$C$5:$O$39,13,0),"") -> 600000 | AC15: =IFERROR(AB15/AA15,"") -> 0 | AD15: =IFERROR(VLOOKUP(D15,'ASE Target (Spares), FY 21-22'!$C$5:$P$39,14,0),"") -> 600000 | AF15: =IFERROR(AE15/AD15,"") -> 0 | AG15: =IFERROR(VLOOKUP(D15,'ASE Target (Spares), FY 21-22'!$C$5:$Q$39,15,0),"") -> 600000 | AI15: =IFERROR(AH15/AG15,"") -> 0 | AJ15: =IFERROR(VLOOKUP(D15,'ASE Target (Spares), FY 21-22'!$C$5:$R$39,16,0),"") -> 600000 | AL15: =IFERROR(AK15/AJ15,"") -> 0 | AM15: =IFERROR(VLOOKUP(D15,'ASE Target (Spares), FY 21-22'!$C$5:$S$39,17,0),"") -> 600000 | AO15: =IFERROR(AN15/AM15,"") -> 0 | AP15: =IFERROR(F15+I15+L15+O15+R15+U15+X15+AA15+AD15+AG15+AJ15+AM15,"") -> 3600000 | AQ15: =IFERROR(G15+J15+M15+P15+S15+V15+Y15+AB15+AE15+AH15+AK15+AN15,"") -> 505895 | AR15: =IFERROR(AQ15/AP15,"") -> 0.14052639
B16: ='ASE Target (Spares), FY 21-22'!A15 -> 10 | C16: =IF('ASE Target (Spares), FY 21-22'!B15=0,"",'ASE Target (Spares), FY 21-22'!B15) -> DSL-DHK | D16: =IF('ASE Target (Spares), FY 21-22'!C15=0,"",'ASE Target (Spares), FY 21-22'!C15) -> Rakibul Islam Razib | E16: =IF('ASE Target (Spares), FY 21-22'!D15=0,"",'ASE Target (Spares), FY 21-22'!D15) -> 3006 | F16: =IFERROR(VLOOKUP(D16,'ASE Target (Spares), FY 21-22'!$C$5:$H$39,6,0),"") -> 250000 | G16: 129195 | H16: =IFERROR(G16/F16,"") -> 0.51678 | I16: =IFERROR(VLOOKUP(D16,'ASE Target (Spares), FY 21-22'!$C$5:$I$39,7,0),"") -> 0 | K16: =IFERROR(J16/I16,"") | L16: =IFERROR(VLOOKUP(D16,'ASE Target (Spares), FY 21-22'!$C$5:$J$39,8,0),"") -> 0 | N16: =IFERROR(M16/L16,"") | O16: =IFERROR(VLOOKUP(D16,'ASE Target (Spares), FY 21-22'!$C$5:$K$39,9,0),"") -> 0 | Q16: =IFERROR(P16/O16,"") | R16: =IFERROR(VLOOKUP(D16,'ASE Target (Spares), FY 21-22'!$C$5:$L$39,10,0),"") -> 0 | T16: =IFERROR(S16/R16,"") | U16: =IFERROR(VLOOKUP(D16,'ASE Target (Spares), FY 21-22'!$C$5:$M$39,11,0),"") -> 0 | W16: =IFERROR(V16/U16,"") | X16: =IFERROR(VLOOKUP(D16,'ASE Target (Spares), FY 21-22'!$C$5:$N$39,12,0),"") -> 0 | Z16: =IFERROR(Y16/X16,"") | AA16: =IFERROR(VLOOKUP(D16,'ASE Target (Spares), FY 21-22'!$C$5:$O$39,13,0),"") -> 0 | AC16: =IFERROR(AB16/AA16,"") | AD16: =IFERROR(VLOOKUP(D16,'ASE Target (Spares), FY 21-22'!$C$5:$P$39,14,0),"") -> 230000 | AF16: =IFERROR(AE16/AD16,"") -> 0 | AG16: =IFERROR(VLOOKUP(D16,'ASE Target (Spares), FY 21-22'!$C$5:$Q$39,15,0),"") -> 230000 | AI16: =IFERROR(AH16/AG16,"") -> 0 | AJ16: =IFERROR(VLOOKUP(D16,'ASE Target (Spares), FY 21-22'!$C$5:$R$39,16,0),"") -> 250000 | AL16: =IFERROR(AK16/AJ16,"") -> 0 | AM16: =IFERROR(VLOOKUP(D16,'ASE Target (Spares), FY 21-22'!$C$5:$S$39,17,0),"") -> 250000 | AO16: =IFERROR(AN16/AM16,"") -> 0 | AP16: =IFERROR(F16+I16+L16+O16+R16+U16+X16+AA16+AD16+AG16+AJ16+AM16,"") -> 1210000 | AQ16: =IFERROR(G16+J16+M16+P16+S16+V16+Y16+AB16+AE16+AH16+AK16+AN16,"") -> 129195 | AR16: =IFERROR(AQ16/AP16,"") -> 0.10677273
B17: ='ASE Target (Spares), FY 21-22'!A16 -> 11 | C17: =IF('ASE Target (Spares), FY 21-22'!B16=0,"",'ASE Target (Spares), FY 21-22'!B16) -> DSL-DHK | D17: =IF('ASE Target (Spares), FY 21-22'!C16=0,"",'ASE Target (Spares), FY 21-22'!C16) -> Ashraful Islam | E17: =IF('ASE Target (Spares), FY 21-22'!D16=0,"",'ASE Target (Spares), FY 21-22'!D16) -> 3003 | F17: =IFERROR(VLOOKUP(D17,'ASE Target (Spares), FY 21-22'!$C$5:$H$39,6,0),"") -> 500000 | G17: 747948 | H17: =IFERROR(G17/F17,"") -> 1.495896 | I17: =IFERROR(VLOOKUP(D17,'ASE Target (Spares), FY 21-22'!$C$5:$I$39,7,0),"") -> 0 | K17: =IFERROR(J17/I17,"") | L17: =IFERROR(VLOOKUP(D17,'ASE Target (Spares), FY 21-22'!$C$5:$J$39,8,0),"") -> 0 | N17: =IFERROR(M17/L17,"") | O17: =IFERROR(VLOOKUP(D17,'ASE Target (Spares), FY 21-22'!$C$5:$K$39,9,0),"") -> 0 | Q17: =IFERROR(P17/O17,"") | R17: =IFERROR(VLOOKUP(D17,'ASE Target (Spares), FY 21-22'!$C$5:$L$39,10,0),"") -> 0 | T17: =IFERROR(S17/R17,"") | U17: =IFERROR(VLOOKUP(D17,'ASE Target (Spares), FY 21-22'!$C$5:$M$39,11,0),"") -> 0 | W17: =IFERROR(V17/U17,"") | X17: =IFERROR(VLOOKUP(D17,'ASE Target (Spares), FY 21-22'!$C$5:$N$39,12,0),"") -> 0 | Z17: =IFERROR(Y17/X17,"") | AA17: =IFERROR(VLOOKUP(D17,'ASE Target (Spares), FY 21-22'!$C$5:$O$39,13,0),"") -> 800000 | AC17: =IFERROR(AB17/AA17,"") -> 0 | AD17: =IFERROR(VLOOKUP(D17,'ASE Target (Spares), FY 21-22'!$C$5:$P$39,14,0),"") -> 800000 | AF17: =IFERROR(AE17/AD17,"") -> 0 | AG17: =IFERROR(VLOOKUP(D17,'ASE Target (Spares), FY 21-22'!$C$5:$Q$39,15,0),"") -> 500000 | AI17: =IFERROR(AH17/AG17,"") -> 0 | AJ17: =IFERROR(VLOOKUP(D17,'ASE Target (Spares), FY 21-22'!$C$5:$R$39,16,0),"") -> 500000 | AL17: =IFERROR(AK17/AJ17,"") -> 0 | AM17: =IFERROR(VLOOKUP(D17,'ASE Target (Spares), FY 21-22'!$C$5:$S$39,17,0),"") -> 500000 | AO17: =IFERROR(AN17/AM17,"") -> 0 | AP17: =IFERROR(F17+I17+L17+O17+R17+U17+X17+AA17+AD17+AG17+AJ17+AM17,"") -> 3600000 | AQ17: =IFERROR(G17+J17+M17+P17+S17+V17+Y17+AB17+AE17+AH17+AK17+AN17,"") -> 747948 | AR17: =IFERROR(AQ17/AP17,"") -> 0.20776333
B18: ='ASE Target (Spares), FY 21-22'!A17 -> 12 | C18: =IF('ASE Target (Spares), FY 21-22'!B17=0,"",'ASE Target (Spares), FY 21-22'!B17) -> DSL-DHK | D18: =IF('ASE Target (Spares), FY 21-22'!C17=0,"",'ASE Target (Spares), FY 21-22'!C17) -> Md. Rakibul Islam | E18: =IF('ASE Target (Spares), FY 21-22'!D17=0,"",'ASE Target (Spares), FY 21-22'!D17) -> 5690 | F18: =IFERROR(VLOOKUP(D18,'ASE Target (Spares), FY 21-22'!$C$5:$H$39,6,0),"") -> 600000 | G18: 542743 | H18: =IFERROR(G18/F18,"") -> 0.90457167 | I18: =IFERROR(VLOOKUP(D18,'ASE Target (Spares), FY 21-22'!$C$5:$I$39,7,0),"") -> 0 | K18: =IFERROR(J18/I18,"") | L18: =IFERROR(VLOOKUP(D18,'ASE Target (Spares), FY 21-22'!$C$5:$J$39,8,0),"") -> 0 | N18: =IFERROR(M18/L18,"") | O18: =IFERROR(VLOOKUP(D18,'ASE Target (Spares), FY 21-22'!$C$5:$K$39,9,0),"") -> 0 | Q18: =IFERROR(P18/O18,"") | R18: =IFERROR(VLOOKUP(D18,'ASE Target (Spares), FY 21-22'!$C$5:$L$39,10,0),"") -> 0 | T18: =IFERROR(S18/R18,"") | U18: =IFERROR(VLOOKUP(D18,'ASE Target (Spares), FY 21-22'!$C$5:$M$39,11,0),"") -> 0 | W18: =IFERROR(V18/U18,"") | X18: =IFERROR(VLOOKUP(D18,'ASE Target (Spares), FY 21-22'!$C$5:$N$39,12,0),"") -> 0 | Z18: =IFERROR(Y18/X18,"") | AA18: =IFERROR(VLOOKUP(D18,'ASE Target (Spares), FY 21-22'!$C$5:$O$39,13,0),"") -> 600000 | AC18: =IFERROR(AB18/AA18,"") -> 0 | AD18: =IFERROR(VLOOKUP(D18,'ASE Target (Spares), FY 21-22'!$C$5:$P$39,14,0),"") -> 600000 | AF18: =IFERROR(AE18/AD18,"") -> 0 | AG18: =IFERROR(VLOOKUP(D18,'ASE Target (Spares), FY 21-22'!$C$5:$Q$39,15,0),"") -> 600000 | AI18: =IFERROR(AH18/AG18,"") -> 0 | AJ18: =IFERROR(VLOOKUP(D18,'ASE Target (Spares), FY 21-22'!$C$5:$R$39,16,0),"") -> 600000 | AL18: =IFERROR(AK18/AJ18,"") -> 0 | AM18: =IFERROR(VLOOKUP(D18,'ASE Target (Spares), FY 21-22'!$C$5:$S$39,17,0),"") -> 600000 | AO18: =IFERROR(AN18/AM18,"") -> 0 | AP18: =IFERROR(F18+I18+L18+O18+R18+U18+X18+AA18+AD18+AG18+AJ18+AM18,"") -> 3600000 | AQ18: =IFERROR(G18+J18+M18+P18+S18+V18+Y18+AB18+AE18+AH18+AK18+AN18,"") -> 542743 | AR18: =IFERROR(AQ18/AP18,"") -> 0.15076194
B19: ='ASE Target (Spares), FY 21-22'!A18 -> 13 | C19: =IF('ASE Target (Spares), FY 21-22'!B18=0,"",'ASE Target (Spares), FY 21-22'!B18) -> DSL-DHK | D19: =IF('ASE Target (Spares), FY 21-22'!C18=0,"",'ASE Target (Spares), FY 21-22'!C18) -> Ohid Hasan Saikat | E19: =IF('ASE Target (Spares), FY 21-22'!D18=0,"",'ASE Target (Spares), FY 21-22'!D18) -> 5691 | F19: =IFERROR(VLOOKUP(D19,'ASE Target (Spares), FY 21-22'!$C$5:$H$39,6,0),"") -> 300000 | H19: =IFERROR(G19/F19,"") -> 0 | I19: =IFERROR(VLOOKUP(D19,'ASE Target (Spares), FY 21-22'!$C$5:$I$39,7,0),"") -> 0 | K19: =IFERROR(J19/I19,"") | L19: =IFERROR(VLOOKUP(D19,'ASE Target (Spares), FY 21-22'!$C$5:$J$39,8,0),"") -> 0 | N19: =IFERROR(M19/L19,"") | O19: =IFERROR(VLOOKUP(D19,'ASE Target (Spares), FY 21-22'!$C$5:$K$39,9,0),"") -> 0 | Q19: =IFERROR(P19/O19,"") | R19: =IFERROR(VLOOKUP(D19,'ASE Target (Spares), FY 21-22'!$C$5:$L$39,10,0),"") -> 0 | T19: =IFERROR(S19/R19,"") | U19: =IFERROR(VLOOKUP(D19,'ASE Target (Spares), FY 21-22'!$C$5:$M$39,11,0),"") -> 0 | W19: =IFERROR(V19/U19,"") | X19: =IFERROR(VLOOKUP(D19,'ASE Target (Spares), FY 21-22'!$C$5:$N$39,12,0),"") -> 0 | Z19: =IFERROR(Y19/X19,"") | AA19: =IFERROR(VLOOKUP(D19,'ASE Target (Spares), FY 21-22'!$C$5:$O$39,13,0),"") -> 300000 | AC19: =IFERROR(AB19/AA19,"") -> 0 | AD19: =IFERROR(VLOOKUP(D19,'ASE Target (Spares), FY 21-22'!$C$5:$P$39,14,0),"") -> 400000 | AF19: =IFERROR(AE19/AD19,"") -> 0 | AG19: =IFERROR(VLOOKUP(D19,'ASE Target (Spares), FY 21-22'!$C$5:$Q$39,15,0),"") -> 300000 | AI19: =IFERROR(AH19/AG19,"") -> 0 | AJ19: =IFERROR(VLOOKUP(D19,'ASE Target (Spares), FY 21-22'!$C$5:$R$39,16,0),"") -> 300000 | AL19: =IFERROR(AK19/AJ19,"") -> 0 | AM19: =IFERROR(VLOOKUP(D19,'ASE Target (Spares), FY 21-22'!$C$5:$S$39,17,0),"") -> 300000 | AO19: =IFERROR(AN19/AM19,"") -> 0 | AP19: =IFERROR(F19+I19+L19+O19+R19+U19+X19+AA19+AD19+AG19+AJ19+AM19,"") -> 1900000 | AQ19: =IFERROR(G19+J19+M19+P19+S19+V19+Y19+AB19+AE19+AH19+AK19+AN19,"") -> 0 | AR19: =IFERROR(AQ19/AP19,"") -> 0
B20: ='ASE Target (Spares), FY 21-22'!A19 -> 14 | C20: =IF('ASE Target (Spares), FY 21-22'!B19=0,"",'ASE Target (Spares), FY 21-22'!B19) -> DSL-DHK | D20: =IF('ASE Target (Spares), FY 21-22'!C19=0,"",'ASE Target (Spares), FY 21-22'!C19) -> Abdullah Al Mahmud | E20: =IF('ASE Target (Spares), FY 21-22'!D19=0,"",'ASE Target (Spares), FY 21-22'!D19) -> 5692 | F20: =IFERROR(VLOOKUP(D20,'ASE Target (Spares), FY 21-22'!$C$5:$H$39,6,0),"") -> 400000 | H20: =IFERROR(G20/F20,"") -> 0 | I20: =IFERROR(VLOOKUP(D20,'ASE Target (Spares), FY 21-22'!$C$5:$I$39,7,0),"") -> 0 | K20: =IFERROR(J20/I20,"") | L20: =IFERROR(VLOOKUP(D20,'ASE Target (Spares), FY 21-22'!$C$5:$J$39,8,0),"") -> 0 | N20: =IFERROR(M20/L20,"") | O20: =IFERROR(VLOOKUP(D20,'ASE Target (Spares), FY 21-22'!$C$5:$K$39,9,0),"") -> 0 | Q20: =IFERROR(P20/O20,"") | R20: =IFERROR(VLOOKUP(D20,'ASE Target (Spares), FY 21-22'!$C$5:$L$39,10,0),"") -> 0 | T20: =IFERROR(S20/R20,"") | U20: =IFERROR(VLOOKUP(D20,'ASE Target (Spares), FY 21-22'!$C$5:$M$39,11,0),"") -> 0 | W20: =IFERROR(V20/U20,"") | X20: =IFERROR(VLOOKUP(D20,'ASE Target (Spares), FY 21-22'!$C$5:$N$39,12,0),"") -> 0 | Z20: =IFERROR(Y20/X20,"") | AA20: =IFERROR(VLOOKUP(D20,'ASE Target (Spares), FY 21-22'!$C$5:$O$39,13,0),"") -> 700000 | AC20: =IFERROR(AB20/AA20,"") -> 0 | AD20: =IFERROR(VLOOKUP(D20,'ASE Target (Spares), FY 21-22'!$C$5:$P$39,14,0),"") -> 400000 | AF20: =IFERROR(AE20/AD20,"") -> 0 | AG20: =IFERROR(VLOOKUP(D20,'ASE Target (Spares), FY 21-22'!$C$5:$Q$39,15,0),"") -> 400000 | AI20: =IFERROR(AH20/AG20,"") -> 0 | AJ20: =IFERROR(VLOOKUP(D20,'ASE Target (Spares), FY 21-22'!$C$5:$R$39,16,0),"") -> 400000 | AL20: =IFERROR(AK20/AJ20,"") -> 0 | AM20: =IFERROR(VLOOKUP(D20,'ASE Target (Spares), FY 21-22'!$C$5:$S$39,17,0),"") -> 400000 | AO20: =IFERROR(AN20/AM20,"") -> 0 | AP20: =IFERROR(F20+I20+L20+O20+R20+U20+X20+AA20+AD20+AG20+AJ20+AM20,"") -> 2700000 | AQ20: =IFERROR(G20+J20+M20+P20+S20+V20+Y20+AB20+AE20+AH20+AK20+AN20,"") -> 0 | AR20: =IFERROR(AQ20/AP20,"") -> 0
B21: ='ASE Target (Spares), FY 21-22'!A20 -> 15 | C21: =IF('ASE Target (Spares), FY 21-22'!B20=0,"",'ASE Target (Spares), FY 21-22'!B20) -> DSL-DHK | D21: =IF('ASE Target (Spares), FY 21-22'!C20=0,"",'ASE Target (Spares), FY 21-22'!C20) -> Apurba Kumar Gain | E21: =IF('ASE Target (Spares), FY 21-22'!D20=0,"",'ASE Target (Spares), FY 21-22'!D20) -> 5927 | F21: =IFERROR(VLOOKUP(D21,'ASE Target (Spares), FY 21-22'!$C$5:$H$39,6,0),"") -> 230000 | G21: 80890 | H21: =IFERROR(G21/F21,"") -> 0.35169565 | I21: =IFERROR(VLOOKUP(D21,'ASE Target (Spares), FY 21-22'!$C$5:$I$39,7,0),"") -> 0 | K21: =IFERROR(J21/I21,"") | L21: =IFERROR(VLOOKUP(D21,'ASE Target (Spares), FY 21-22'!$C$5:$J$39,8,0),"") -> 0 | N21: =IFERROR(M21/L21,"") | O21: =IFERROR(VLOOKUP(D21,'ASE Target (Spares), FY 21-22'!$C$5:$K$39,9,0),"") -> 0 | Q21: =IFERROR(P21/O21,"") | R21: =IFERROR(VLOOKUP(D21,'ASE Target (Spares), FY 21-22'!$C$5:$L$39,10,0),"") -> 0 | T21: =IFERROR(S21/R21,"") | U21: =IFERROR(VLOOKUP(D21,'ASE Target (Spares), FY 21-22'!$C$5:$M$39,11,0),"") -> 0 | W21: =IFERROR(V21/U21,"") | X21: =IFERROR(VLOOKUP(D21,'ASE Target (Spares), FY 21-22'!$C$5:$N$39,12,0),"") -> 0 | Z21: =IFERROR(Y21/X21,"") | AA21: =IFERROR(VLOOKUP(D21,'ASE Target (Spares), FY 21-22'!$C$5:$O$39,13,0),"") -> 0 | AC21: =IFERROR(AB21/AA21,"") | AD21: =IFERROR(VLOOKUP(D21,'ASE Target (Spares), FY 21-22'!$C$5:$P$39,14,0),"") -> 230000 | AF21: =IFERROR(AE21/AD21,"") -> 0 | AG21: =IFERROR(VLOOKUP(D21,'ASE Target (Spares), FY 21-22'!$C$5:$Q$39,15,0),"") -> 230000 | AI21: =IFERROR(AH21/AG21,"") -> 0 | AJ21: =IFERROR(VLOOKUP(D21,'ASE Target (Spares), FY 21-22'!$C$5:$R$39,16,0),"") -> 230000 | AL21: =IFERROR(AK21/AJ21,"") -> 0 | AM21: =IFERROR(VLOOKUP(D21,'ASE Target (Spares), FY 21-22'!$C$5:$S$39,17,0),"") -> 230000 | AO21: =IFERROR(AN21/AM21,"") -> 0 | AP21: =IFERROR(F21+I21+L21+O21+R21+U21+X21+AA21+AD21+AG21+AJ21+AM21,"") -> 1150000 | AQ21: =IFERROR(G21+J21+M21+P21+S21+V21+Y21+AB21+AE21+AH21+AK21+AN21,"") -> 80890 | AR21: =IFERROR(AQ21/AP21,"") -> 0.07033913
B22: ='ASE Target (Spares), FY 21-22'!A21 -> 16 | C22: =IF('ASE Target (Spares), FY 21-22'!B21=0,"",'ASE Target (Spares), FY 21-22'!B21) -> DSL-DHK | D22: =IF('ASE Target (Spares), FY 21-22'!C21=0,"",'ASE Target (Spares), FY 21-22'!C21) -> Amirul Islam | E22: =IF('ASE Target (Spares), FY 21-22'!D21=0,"",'ASE Target (Spares), FY 21-22'!D21) -> 5928 | F22: =IFERROR(VLOOKUP(D22,'ASE Target (Spares), FY 21-22'!$C$5:$H$39,6,0),"") -> 250000 | H22: =IFERROR(G22/F22,"") -> 0 | I22: =IFERROR(VLOOKUP(D22,'ASE Target (Spares), FY 21-22'!$C$5:$I$39,7,0),"") -> 0 | K22: =IFERROR(J22/I22,"") | L22: =IFERROR(VLOOKUP(D22,'ASE Target (Spares), FY 21-22'!$C$5:$J$39,8,0),"") -> 0 | N22: =IFERROR(M22/L22,"") | O22: =IFERROR(VLOOKUP(D22,'ASE Target (Spares), FY 21-22'!$C$5:$K$39,9,0),"") -> 0 | Q22: =IFERROR(P22/O22,"") | R22: =IFERROR(VLOOKUP(D22,'ASE Target (Spares), FY 21-22'!$C$5:$L$39,10,0),"") -> 0 | T22: =IFERROR(S22/R22,"") | U22: =IFERROR(VLOOKUP(D22,'ASE Target (Spares), FY 21-22'!$C$5:$M$39,11,0),"") -> 0 | W22: =IFERROR(V22/U22,"") | X22: =IFERROR(VLOOKUP(D22,'ASE Target (Spares), FY 21-22'!$C$5:$N$39,12,0),"") -> 0 | Z22: =IFERROR(Y22/X22,"") | AA22: =IFERROR(VLOOKUP(D22,'ASE Target (Spares), FY 21-22'!$C$5:$O$39,13,0),"") -> 0 | AC22: =IFERROR(AB22/AA22,"") | AD22: =IFERROR(VLOOKUP(D22,'ASE Target (Spares), FY 21-22'!$C$5:$P$39,14,0),"") -> 250000 | AF22: =IFERROR(AE22/AD22,"") -> 0 | AG22: =IFERROR(VLOOKUP(D22,'ASE Target (Spares), FY 21-22'!$C$5:$Q$39,15,0),"") -> 250000 | AI22: =IFERROR(AH22/AG22,"") -> 0 | AJ22: =IFERROR(VLOOKUP(D22,'ASE Target (Spares), FY 21-22'!$C$5:$R$39,16,0),"") -> 250000 | AL22: =IFERROR(AK22/AJ22,"") -> 0 | AM22: =IFERROR(VLOOKUP(D22,'ASE Target (Spares), FY 21-22'!$C$5:$S$39,17,0),"") -> 250000 | AO22: =IFERROR(AN22/AM22,"") -> 0 | AP22: =IFERROR(F22+I22+L22+O22+R22+U22+X22+AA22+AD22+AG22+AJ22+AM22,"") -> 1250000 | AQ22: =IFERROR(G22+J22+M22+P22+S22+V22+Y22+AB22+AE22+AH22+AK22+AN22,"") -> 0 | AR22: =IFERROR(AQ22/AP22,"") -> 0
B23: ='ASE Target (Spares), FY 21-22'!A22 -> 17 | C23: =IF('ASE Target (Spares), FY 21-22'!B22=0,"",'ASE Target (Spares), FY 21-22'!B22) -> DSL-DHK | D23: =IF('ASE Target (Spares), FY 21-22'!C22=0,"",'ASE Target (Spares), FY 21-22'!C22) -> Md. Jafor Ikbal | E23: =IF('ASE Target (Spares), FY 21-22'!D22=0,"",'ASE Target (Spares), FY 21-22'!D22) -> 5929 | F23: =IFERROR(VLOOKUP(D23,'ASE Target (Spares), FY 21-22'!$C$5:$H$39,6,0),"") -> 0 | H23: =IFERROR(G23/F23,"") | I23: =IFERROR(VLOOKUP(D23,'ASE Target (Spares), FY 21-22'!$C$5:$I$39,7,0),"") -> 0 | K23: =IFERROR(J23/I23,"") | L23: =IFERROR(VLOOKUP(D23,'ASE Target (Spares), FY 21-22'!$C$5:$J$39,8,0),"") -> 0 | N23: =IFERROR(M23/L23,"") | O23: =IFERROR(VLOOKUP(D23,'ASE Target (Spares), FY 21-22'!$C$5:$K$39,9,0),"") -> 0 | Q23: =IFERROR(P23/O23,"") | R23: =IFERROR(VLOOKUP(D23,'ASE Target (Spares), FY 21-22'!$C$5:$L$39,10,0),"") -> 0 | T23: =IFERROR(S23/R23,"") | U23: =IFERROR(VLOOKUP(D23,'ASE Target (Spares), FY 21-22'!$C$5:$M$39,11,0),"") -> 0 | W23: =IFERROR(V23/U23,"") | X23: =IFERROR(VLOOKUP(D23,'ASE Target (Spares), FY 21-22'!$C$5:$N$39,12,0),"") -> 0 | Z23: =IFERROR(Y23/X23,"") | AA23: =IFERROR(VLOOKUP(D23,'ASE Target (Spares), FY 21-22'!$C$5:$O$39,13,0),"") -> 0 | AC23: =IFERROR(AB23/AA23,"") | AD23: =IFERROR(VLOOKUP(D23,'ASE Target (Spares), FY 21-22'!$C$5:$P$39,14,0),"") -> 0 | AF23: =IFERROR(AE23/AD23,"") | AG23: =IFERROR(VLOOKUP(D23,'ASE Target (Spares), FY 21-22'!$C$5:$Q$39,15,0),"") -> 0 | AI23: =IFERROR(AH23/AG23,"") | AJ23: =IFERROR(VLOOKUP(D23,'ASE Target (Spares), FY 21-22'!$C$5:$R$39,16,0),"") -> 0 | AL23: =IFERROR(AK23/AJ23,"") | AM23: =IFERROR(VLOOKUP(D23,'ASE Target (Spares), FY 21-22'!$C$5:$S$39,17,0),"") -> 0 | AO23: =IFERROR(AN23/AM23,"") | AP23: =IFERROR(F23+I23+L23+O23+R23+U23+X23+AA23+AD23+AG23+AJ23+AM23,"") -> 0 | AQ23: =IFERROR(G23+J23+M23+P23+S23+V23+Y23+AB23+AE23+AH23+AK23+AN23,"") -> 0 | AR23: =IFERROR(AQ23/AP23,"")
B24: ='ASE Target (Spares), FY 21-22'!A29 -> 18 | C24: =IF('ASE Target (Spares), FY 21-22'!B23=0,"",'ASE Target (Spares), FY 21-22'!B23) -> DSL-DHK | D24: =IF('ASE Target (Spares), FY 21-22'!C23=0,"",'ASE Target (Spares), FY 21-22'!C23) -> Md. Habibur Rahman | E24: =IF('ASE Target (Spares), FY 21-22'!D23=0,"",'ASE Target (Spares), FY 21-22'!D23) -> 6079 | F24: =IFERROR(VLOOKUP(D24,'ASE Target (Spares), FY 21-22'!$C$5:$H$39,6,0),"") -> 250000 | G24: 263694 | H24: =IFERROR(G24/F24,"") -> 1.054776 | I24: =IFERROR(VLOOKUP(D24,'ASE Target (Spares), FY 21-22'!$C$5:$I$39,7,0),"") -> 0 | K24: =IFERROR(J24/I24,"") | L24: =IFERROR(VLOOKUP(D24,'ASE Target (Spares), FY 21-22'!$C$5:$J$39,8,0),"") -> 0 | N24: =IFERROR(M24/L24,"") | O24: =IFERROR(VLOOKUP(D24,'ASE Target (Spares), FY 21-22'!$C$5:$K$39,9,0),"") -> 0 | Q24: =IFERROR(P24/O24,"") | R24: =IFERROR(VLOOKUP(D24,'ASE Target (Spares), FY 21-22'!$C$5:$L$39,10,0),"") -> 0 | T24: =IFERROR(S24/R24,"") | U24: =IFERROR(VLOOKUP(D24,'ASE Target (Spares), FY 21-22'!$C$5:$M$39,11,0),"") -> 0 | W24: =IFERROR(V24/U24,"") | X24: =IFERROR(VLOOKUP(D24,'ASE Target (Spares), FY 21-22'!$C$5:$N$39,12,0),"") -> 0 | Z24: =IFERROR(Y24/X24,"") | AA24: =IFERROR(VLOOKUP(D24,'ASE Target (Spares), FY 21-22'!$C$5:$O$39,13,0),"") -> 0 | AC24: =IFERROR(AB24/AA24,"") | AD24: =IFERROR(VLOOKUP(D24,'ASE Target (Spares), FY 21-22'!$C$5:$P$39,14,0),"") -> 0 | AF24: =IFERROR(AE24/AD24,"") | AG24: =IFERROR(VLOOKUP(D24,'ASE Target (Spares), FY 21-22'!$C$5:$Q$39,15,0),"") -> 0 | AI24: =IFERROR(AH24/AG24,"") | AJ24: =IFERROR(VLOOKUP(D24,'ASE Target (Spares), FY 21-22'!$C$5:$R$39,16,0),"") -> 0 | AL24: =IFERROR(AK24/AJ24,"") | AM24: =IFERROR(VLOOKUP(D24,'ASE Target (Spares), FY 21-22'!$C$5:$S$39,17,0),"") -> 250000 | AO24: =IFERROR(AN24/AM24,"") -> 0 | AP24: =IFERROR(F24+I24+L24+O24+R24+U24+X24+AA24+AD24+AG24+AJ24+AM24,"") -> 500000 | AQ24: =IFERROR(G24+J24+M24+P24+S24+V24+Y24+AB24+AE24+AH24+AK24+AN24,"") -> 263694 | AR24: =IFERROR(AQ24/AP24,"") -> 0.527388
B25: ='ASE Target (Spares), FY 21-22'!A30 -> 19 | C25: =IF('ASE Target (Spares), FY 21-22'!B24=0,"",'ASE Target (Spares), FY 21-22'!B24) -> DSL-DHK | D25: =IF('ASE Target (Spares), FY 21-22'!C24=0,"",'ASE Target (Spares), FY 21-22'!C24) -> Ashikur Rahman | E25: =IF('ASE Target (Spares), FY 21-22'!D24=0,"",'ASE Target (Spares), FY 21-22'!D24) -> 6080 | F25: =IFERROR(VLOOKUP(D25,'ASE Target (Spares), FY 21-22'!$C$5:$H$39,6,0),"") -> 500000 | H25: =IFERROR(G25/F25,"") -> 0 | I25: =IFERROR(VLOOKUP(D25,'ASE Target (Spares), FY 21-22'!$C$5:$I$39,7,0),"") -> 0 | K25: =IFERROR(J25/I25,"") | L25: =IFERROR(VLOOKUP(D25,'ASE Target (Spares), FY 21-22'!$C$5:$J$39,8,0),"") -> 0 | N25: =IFERROR(M25/L25,"") | O25: =IFERROR(VLOOKUP(D25,'ASE Target (Spares), FY 21-22'!$C$5:$K$39,9,0),"") -> 0 | Q25: =IFERROR(P25/O25,"") | R25: =IFERROR(VLOOKUP(D25,'ASE Target (Spares), FY 21-22'!$C$5:$L$39,10,0),"") -> 0 | T25: =IFERROR(S25/R25,"") | U25: =IFERROR(VLOOKUP(D25,'ASE Target (Spares), FY 21-22'!$C$5:$M$39,11,0),"") -> 0 | W25: =IFERROR(V25/U25,"") | X25: =IFERROR(VLOOKUP(D25,'ASE Target (Spares), FY 21-22'!$C$5:$N$39,12,0),"") -> 0 | Z25: =IFERROR(Y25/X25,"") | AA25: =IFERROR(VLOOKUP(D25,'ASE Target (Spares), FY 21-22'!$C$5:$O$39,13,0),"") -> 0 | AC25: =IFERROR(AB25/AA25,"") | AD25: =IFERROR(VLOOKUP(D25,'ASE Target (Spares), FY 21-22'!$C$5:$P$39,14,0),"") -> 0 | AF25: =IFERROR(AE25/AD25,"") | AG25: =IFERROR(VLOOKUP(D25,'ASE Target (Spares), FY 21-22'!$C$5:$Q$39,15,0),"") -> 0 | AI25: =IFERROR(AH25/AG25,"") | AJ25: =IFERROR(VLOOKUP(D25,'ASE Target (Spares), FY 21-22'!$C$5:$R$39,16,0),"") -> 0 | AL25: =IFERROR(AK25/AJ25,"") | AM25: =IFERROR(VLOOKUP(D25,'ASE Target (Spares), FY 21-22'!$C$5:$S$39,17,0),"") -> 500000 | AO25: =IFERROR(AN25/AM25,"") -> 0 | AP25: =IFERROR(F25+I25+L25+O25+R25+U25+X25+AA25+AD25+AG25+AJ25+AM25,"") -> 1000000 | AQ25: =IFERROR(G25+J25+M25+P25+S25+V25+Y25+AB25+AE25+AH25+AK25+AN25,"") -> 0 | AR25: =IFERROR(AQ25/AP25,"") -> 0
B26: ='ASE Target (Spares), FY 21-22'!A31 -> 20 | C26: =IF('ASE Target (Spares), FY 21-22'!B25=0,"",'ASE Target (Spares), FY 21-22'!B25) -> DSL-DHK | D26: =IF('ASE Target (Spares), FY 21-22'!C25=0,"",'ASE Target (Spares), FY 21-22'!C25) -> Md. Sujon Hossain | E26: =IF('ASE Target (Spares), FY 21-22'!D25=0,"",'ASE Target (Spares), FY 21-22'!D25) -> 6078 | F26: =IFERROR(VLOOKUP(D26,'ASE Target (Spares), FY 21-22'!$C$5:$H$39,6,0),"") -> 600000 | G26: 290128 | H26: =IFERROR(G26/F26,"") -> 0.48354667 | I26: =IFERROR(VLOOKUP(D26,'ASE Target (Spares), FY 21-22'!$C$5:$I$39,7,0),"") -> 0 | K26: =IFERROR(J26/I26,"") | L26: =IFERROR(VLOOKUP(D26,'ASE Target (Spares), FY 21-22'!$C$5:$J$39,8,0),"") -> 0 | N26: =IFERROR(M26/L26,"") | O26: =IFERROR(VLOOKUP(D26,'ASE Target (Spares), FY 21-22'!$C$5:$K$39,9,0),"") -> 0 | Q26: =IFERROR(P26/O26,"") | R26: =IFERROR(VLOOKUP(D26,'ASE Target (Spares), FY 21-22'!$C$5:$L$39,10,0),"") -> 0 | T26: =IFERROR(S26/R26,"") | U26: =IFERROR(VLOOKUP(D26,'ASE Target (Spares), FY 21-22'!$C$5:$M$39,11,0),"") -> 0 | W26: =IFERROR(V26/U26,"") | X26: =IFERROR(VLOOKUP(D26,'ASE Target (Spares), FY 21-22'!$C$5:$N$39,12,0),"") -> 0 | Z26: =IFERROR(Y26/X26,"") | AA26: =IFERROR(VLOOKUP(D26,'ASE Target (Spares), FY 21-22'!$C$5:$O$39,13,0),"") -> 0 | AC26: =IFERROR(AB26/AA26,"") | AD26: =IFERROR(VLOOKUP(D26,'ASE Target (Spares), FY 21-22'!$C$5:$P$39,14,0),"") -> 0 | AF26: =IFERROR(AE26/AD26,"") | AG26: =IFERROR(VLOOKUP(D26,'ASE Target (Spares), FY 21-22'!$C$5:$Q$39,15,0),"") -> 0 | AI26: =IFERROR(AH26/AG26,"") | AJ26: =IFERROR(VLOOKUP(D26,'ASE Target (Spares), FY 21-22'!$C$5:$R$39,16,0),"") -> 0 | AL26: =IFERROR(AK26/AJ26,"") | AM26: =IFERROR(VLOOKUP(D26,'ASE Target (Spares), FY 21-22'!$C$5:$S$39,17,0),"") -> 600000 | AO26: =IFERROR(AN26/AM26,"") -> 0 | AP26: =IFERROR(F26+I26+L26+O26+R26+U26+X26+AA26+AD26+AG26+AJ26+AM26,"") -> 1200000 | AQ26: =IFERROR(G26+J26+M26+P26+S26+V26+Y26+AB26+AE26+AH26+AK26+AN26,"") -> 290128 | AR26: =IFERROR(AQ26/AP26,"") -> 0.24177333
B27: ='ASE Target (Spares), FY 21-22'!A32 -> 21 | C27: =IF('ASE Target (Spares), FY 21-22'!B26=0,"",'ASE Target (Spares), FY 21-22'!B26) -> DSL-DHK | D27: =IF('ASE Target (Spares), FY 21-22'!C26=0,"",'ASE Target (Spares), FY 21-22'!C26) -> Md Jiaur Rahman | E27: =IF('ASE Target (Spares), FY 21-22'!D26=0,"",'ASE Target (Spares), FY 21-22'!D26) -> 0522 | F27: =IFERROR(VLOOKUP(D27,'ASE Target (Spares), FY 21-22'!$C$5:$H$39,6,0),"") -> 900000 | H27: =IFERROR(G27/F27,"") -> 0 | I27: =IFERROR(VLOOKUP(D27,'ASE Target (Spares), FY 21-22'!$C$5:$I$39,7,0),"") -> 0 | K27: =IFERROR(J27/I27,"") | L27: =IFERROR(VLOOKUP(D27,'ASE Target (Spares), FY 21-22'!$C$5:$J$39,8,0),"") -> 0 | N27: =IFERROR(M27/L27,"") | O27: =IFERROR(VLOOKUP(D27,'ASE Target (Spares), FY 21-22'!$C$5:$K$39,9,0),"") -> 0 | Q27: =IFERROR(P27/O27,"") | R27: =IFERROR(VLOOKUP(D27,'ASE Target (Spares), FY 21-22'!$C$5:$L$39,10,0),"") -> 0 | T27: =IFERROR(S27/R27,"") | U27: =IFERROR(VLOOKUP(D27,'ASE Target (Spares), FY 21-22'!$C$5:$M$39,11,0),"") -> 0 | W27: =IFERROR(V27/U27,"") | X27: =IFERROR(VLOOKUP(D27,'ASE Target (Spares), FY 21-22'!$C$5:$N$39,12,0),"") -> 0 | Z27: =IFERROR(Y27/X27,"") | AA27: =IFERROR(VLOOKUP(D27,'ASE Target (Spares), FY 21-22'!$C$5:$O$39,13,0),"") -> 0 | AC27: =IFERROR(AB27/AA27,"") | AD27: =IFERROR(VLOOKUP(D27,'ASE Target (Spares), FY 21-22'!$C$5:$P$39,14,0),"") -> 850000 | AF27: =IFERROR(AE27/AD27,"") -> 0 | AG27: =IFERROR(VLOOKUP(D27,'ASE Target (Spares), FY 21-22'!$C$5:$Q$39,15,0),"") -> 850000 | AI27: =IFERROR(AH27/AG27,"") -> 0 | AJ27: =IFERROR(VLOOKUP(D27,'ASE Target (Spares), FY 21-22'!$C$5:$R$39,16,0),"") -> 850000 | AL27: =IFERROR(AK27/AJ27,"") -> 0 | AM27: =IFERROR(VLOOKUP(D27,'ASE Target (Spares), FY 21-22'!$C$5:$S$39,17,0),"") -> 900000 | AO27: =IFERROR(AN27/AM27,"") -> 0 | AP27: =IFERROR(F27+I27+L27+O27+R27+U27+X27+AA27+AD27+AG27+AJ27+AM27,"") -> 4350000 | AQ27: =IFERROR(G27+J27+M27+P27+S27+V27+Y27+AB27+AE27+AH27+AK27+AN27,"") -> 0 | AR27: =IFERROR(AQ27/AP27,"") -> 0
B28: ='ASE Target (Spares), FY 21-22'!A36 -> 0 | C28: =IF('ASE Target (Spares), FY 21-22'!B27=0,"",'ASE Target (Spares), FY 21-22'!B27) | D28: =IF('ASE Target (Spares), FY 21-22'!C27=0,"",'ASE Target (Spares), FY 21-22'!C27) -> New-2 | E28: =IF('ASE Target (Spares), FY 21-22'!D27=0,"",'ASE Target (Spares), FY 21-22'!D27) | F28: =IFERROR(VLOOKUP(D28,'ASE Target (Spares), FY 21-22'!$C$5:$H$39,6,0),"") -> 0 | H28: =IFERROR(G28/F28,"") | I28: =IFERROR(VLOOKUP(D28,'ASE Target (Spares), FY 21-22'!$C$5:$I$39,7,0),"") -> 0 | K28: =IFERROR(J28/I28,"") | L28: =IFERROR(VLOOKUP(D28,'ASE Target (Spares), FY 21-22'!$C$5:$J$39,8,0),"") -> 0 | N28: =IFERROR(M28/L28,"") | O28: =IFERROR(VLOOKUP(D28,'ASE Target (Spares), FY 21-22'!$C$5:$K$39,9,0),"") -> 0 | Q28: =IFERROR(P28/O28,"") | R28: =IFERROR(VLOOKUP(D28,'ASE Target (Spares), FY 21-22'!$C$5:$L$39,10,0),"") -> 0 | T28: =IFERROR(S28/R28,"") | U28: =IFERROR(VLOOKUP(D28,'ASE Target (Spares), FY 21-22'!$C$5:$M$39,11,0),"") -> 0 | W28: =IFERROR(V28/U28,"") | X28: =IFERROR(VLOOKUP(D28,'ASE Target (Spares), FY 21-22'!$C$5:$N$39,12,0),"") -> 0 | Z28: =IFERROR(Y28/X28,"") | AA28: =IFERROR(VLOOKUP(D28,'ASE Target (Spares), FY 21-22'!$C$5:$O$39,13,0),"") -> 0 | AC28: =IFERROR(AB28/AA28,"") | AD28: =IFERROR(VLOOKUP(D28,'ASE Target (Spares), FY 21-22'!$C$5:$P$39,14,0),"") -> 0 | AF28: =IFERROR(AE28/AD28,"") | AG28: =IFERROR(VLOOKUP(D28,'ASE Target (Spares), FY 21-22'!$C$5:$Q$39,15,0),"") -> 0 | AI28: =IFERROR(AH28/AG28,"") | AJ28: =IFERROR(VLOOKUP(D28,'ASE Target (Spares), FY 21-22'!$C$5:$R$39,16,0),"") -> 0 | AL28: =IFERROR(AK28/AJ28,"") | AM28: =IFERROR(VLOOKUP(D28,'ASE Target (Spares), FY 21-22'!$C$5:$S$39,17,0),"") -> 0 | AO28: =IFERROR(AN28/AM28,"") | AP28: =IFERROR(F28+I28+L28+O28+R28+U28+X28+AA28+AD28+AG28+AJ28+AM28,"") -> 0 | AQ28: =IFERROR(G28+J28+M28+P28+S28+V28+Y28+AB28+AE28+AH28+AK28+AN28,"") -> 0 | AR28: =IFERROR(AQ28/AP28,"")
C29: =IF('ASE Target (Spares), FY 21-22'!B28=0,"",'ASE Target (Spares), FY 21-22'!B28) | D29: =IF('ASE Target (Spares), FY 21-22'!C28=0,"",'ASE Target (Spares), FY 21-22'!C28) -> New-3 | E29: =IF('ASE Target (Spares), FY 21-22'!D28=0,"",'ASE Target (Spares), FY 21-22'!D28) | F29: =IFERROR(VLOOKUP(D29,'ASE Target (Spares), FY 21-22'!$C$5:$H$39,6,0),"") -> 0 | H29: =IFERROR(G29/F29,"") | I29: =IFERROR(VLOOKUP(D29,'ASE Target (Spares), FY 21-22'!$C$5:$I$39,7,0),"") -> 0 | K29: =IFERROR(J29/I29,"") | L29: =IFERROR(VLOOKUP(D29,'ASE Target (Spares), FY 21-22'!$C$5:$J$39,8,0),"") -> 0 | N29: =IFERROR(M29/L29,"") | O29: =IFERROR(VLOOKUP(D29,'ASE Target (Spares), FY 21-22'!$C$5:$K$39,9,0),"") -> 0 | Q29: =IFERROR(P29/O29,"") | R29: =IFERROR(VLOOKUP(D29,'ASE Target (Spares), FY 21-22'!$C$5:$L$39,10,0),"") -> 0 | T29: =IFERROR(S29/R29,"") | U29: =IFERROR(VLOOKUP(D29,'ASE Target (Spares), FY 21-22'!$C$5:$M$39,11,0),"") -> 0 | W29: =IFERROR(V29/U29,"") | X29: =IFERROR(VLOOKUP(D29,'ASE Target (Spares), FY 21-22'!$C$5:$N$39,12,0),"") -> 0 | Z29: =IFERROR(Y29/X29,"") | AA29: =IFERROR(VLOOKUP(D29,'ASE Target (Spares), FY 21-22'!$C$5:$O$39,13,0),"") -> 0 | AC29: =IFERROR(AB29/AA29,"") | AD29: =IFERROR(VLOOKUP(D29,'ASE Target (Spares), FY 21-22'!$C$5:$P$39,14,0),"") -> 0 | AF29: =IFERROR(AE29/AD29,"") | AG29: =IFERROR(VLOOKUP(D29,'ASE Target (Spares), FY 21-22'!$C$5:$Q$39,15,0),"") -> 0 | AI29: =IFERROR(AH29/AG29,"") | AJ29: =IFERROR(VLOOKUP(D29,'ASE Target (Spares), FY 21-22'!$C$5:$R$39,16,0),"") -> 0 | AL29: =IFERROR(AK29/AJ29,"") | AM29: =IFERROR(VLOOKUP(D29,'ASE Target (Spares), FY 21-22'!$C$5:$S$39,17,0),"") -> 0 | AO29: =IFERROR(AN29/AM29,"") | AP29: =IFERROR(F29+I29+L29+O29+R29+U29+X29+AA29+AD29+AG29+AJ29+AM29,"") -> 0 | AQ29: =IFERROR(G29+J29+M29+P29+S29+V29+Y29+AB29+AE29+AH29+AK29+AN29,"") -> 0 | AR29: =IFERROR(AQ29/AP29,"")
C30: =IF('ASE Target (Spares), FY 21-22'!B29=0,"",'ASE Target (Spares), FY 21-22'!B29) | D30: =IF('ASE Target (Spares), FY 21-22'!C29=0,"",'ASE Target (Spares), FY 21-22'!C29) -> New-4 | E30: =IF('ASE Target (Spares), FY 21-22'!D29=0,"",'ASE Target (Spares), FY 21-22'!D29) | F30: =IFERROR(VLOOKUP(D30,'ASE Target (Spares), FY 21-22'!$C$5:$H$39,6,0),"") -> 0 | H30: =IFERROR(G30/F30,"") | I30: =IFERROR(VLOOKUP(D30,'ASE Target (Spares), FY 21-22'!$C$5:$I$39,7,0),"") -> 0 | K30: =IFERROR(J30/I30,"") | L30: =IFERROR(VLOOKUP(D30,'ASE Target (Spares), FY 21-22'!$C$5:$J$39,8,0),"") -> 0 | N30: =IFERROR(M30/L30,"") | O30: =IFERROR(VLOOKUP(D30,'ASE Target (Spares), FY 21-22'!$C$5:$K$39,9,0),"") -> 0 | Q30: =IFERROR(P30/O30,"") | R30: =IFERROR(VLOOKUP(D30,'ASE Target (Spares), FY 21-22'!$C$5:$L$39,10,0),"") -> 0 | T30: =IFERROR(S30/R30,"") | U30: =IFERROR(VLOOKUP(D30,'ASE Target (Spares), FY 21-22'!$C$5:$M$39,11,0),"") -> 0 | W30: =IFERROR(V30/U30,"") | X30: =IFERROR(VLOOKUP(D30,'ASE Target (Spares), FY 21-22'!$C$5:$N$39,12,0),"") -> 0 | Z30: =IFERROR(Y30/X30,"") | AA30: =IFERROR(VLOOKUP(D30,'ASE Target (Spares), FY 21-22'!$C$5:$O$39,13,0),"") -> 0 | AC30: =IFERROR(AB30/AA30,"") | AD30: =IFERROR(VLOOKUP(D30,'ASE Target (Spares), FY 21-22'!$C$5:$P$39,14,0),"") -> 0 | AF30: =IFERROR(AE30/AD30,"") | AG30: =IFERROR(VLOOKUP(D30,'ASE Target (Spares), FY 21-22'!$C$5:$Q$39,15,0),"") -> 0 | AI30: =IFERROR(AH30/AG30,"") | AJ30: =IFERROR(VLOOKUP(D30,'ASE Target (Spares), FY 21-22'!$C$5:$R$39,16,0),"") -> 0 | AL30: =IFERROR(AK30/AJ30,"") | AM30: =IFERROR(VLOOKUP(D30,'ASE Target (Spares), FY 21-22'!$C$5:$S$39,17,0),"") -> 0 | AO30: =IFERROR(AN30/AM30,"") | AP30: =IFERROR(F30+I30+L30+O30+R30+U30+X30+AA30+AD30+AG30+AJ30+AM30,"") -> 0 | AQ30: =IFERROR(G30+J30+M30+P30+S30+V30+Y30+AB30+AE30+AH30+AK30+AN30,"") -> 0 | AR30: =IFERROR(AQ30/AP30,"")
C31: =IF('ASE Target (Spares), FY 21-22'!B30=0,"",'ASE Target (Spares), FY 21-22'!B30) -> CTG | D31: =IF('ASE Target (Spares), FY 21-22'!C30=0,"",'ASE Target (Spares), FY 21-22'!C30) -> Sumon Sen | E31: =IF('ASE Target (Spares), FY 21-22'!D30=0,"",'ASE Target (Spares), FY 21-22'!D30) -> 8041 | F31: =IFERROR(VLOOKUP(D31,'ASE Target (Spares), FY 21-22'!$C$5:$H$39,6,0),"") -> 0 | H31: =IFERROR(G31/F31,"") | I31: =IFERROR(VLOOKUP(D31,'ASE Target (Spares), FY 21-22'!$C$5:$I$39,7,0),"") -> 0 | K31: =IFERROR(J31/I31,"") | L31: =IFERROR(VLOOKUP(D31,'ASE Target (Spares), FY 21-22'!$C$5:$J$39,8,0),"") -> 0 | N31: =IFERROR(M31/L31,"") | O31: =IFERROR(VLOOKUP(D31,'ASE Target (Spares), FY 21-22'!$C$5:$K$39,9,0),"") -> 0 | Q31: =IFERROR(P31/O31,"") | R31: =IFERROR(VLOOKUP(D31,'ASE Target (Spares), FY 21-22'!$C$5:$L$39,10,0),"") -> 0 | T31: =IFERROR(S31/R31,"") | U31: =IFERROR(VLOOKUP(D31,'ASE Target (Spares), FY 21-22'!$C$5:$M$39,11,0),"") -> 0 | W31: =IFERROR(V31/U31,"") | X31: =IFERROR(VLOOKUP(D31,'ASE Target (Spares), FY 21-22'!$C$5:$N$39,12,0),"") -> 0 | Z31: =IFERROR(Y31/X31,"") | AA31: =IFERROR(VLOOKUP(D31,'ASE Target (Spares), FY 21-22'!$C$5:$O$39,13,0),"") -> 450000 | AC31: =IFERROR(AB31/AA31,"") -> 0 | AD31: =IFERROR(VLOOKUP(D31,'ASE Target (Spares), FY 21-22'!$C$5:$P$39,14,0),"") -> 450000 | AF31: =IFERROR(AE31/AD31,"") -> 0 | AG31: =IFERROR(VLOOKUP(D31,'ASE Target (Spares), FY 21-22'!$C$5:$Q$39,15,0),"") -> 450000 | AI31: =IFERROR(AH31/AG31,"") -> 0 | AJ31: =IFERROR(VLOOKUP(D31,'ASE Target (Spares), FY 21-22'!$C$5:$R$39,16,0),"") -> 450000 | AL31: =IFERROR(AK31/AJ31,"") -> 0 | AM31: =IFERROR(VLOOKUP(D31,'ASE Target (Spares), FY 21-22'!$C$5:$S$39,17,0),"") -> 450000 | AO31: =IFERROR(AN31/AM31,"") -> 0 | AP31: =IFERROR(F31+I31+L31+O31+R31+U31+X31+AA31+AD31+AG31+AJ31+AM31,"") -> 2250000 | AQ31: =IFERROR(G31+J31+M31+P31+S31+V31+Y31+AB31+AE31+AH31+AK31+AN31,"") -> 0 | AR31: =IFERROR(AQ31/AP31,"") -> 0
C32: =IF('ASE Target (Spares), FY 21-22'!B31=0,"",'ASE Target (Spares), FY 21-22'!B31) -> CTG | D32: =IF('ASE Target (Spares), FY 21-22'!C31=0,"",'ASE Target (Spares), FY 21-22'!C31) -> Tapan Barua | E32: =IF('ASE Target (Spares), FY 21-22'!D31=0,"",'ASE Target (Spares), FY 21-22'!D31) -> 1475 | F32: =IFERROR(VLOOKUP(D32,'ASE Target (Spares), FY 21-22'!$C$5:$H$39,6,0),"") -> 0 | H32: =IFERROR(G32/F32,"") | I32: =IFERROR(VLOOKUP(D32,'ASE Target (Spares), FY 21-22'!$C$5:$I$39,7,0),"") -> 0 | K32: =IFERROR(J32/I32,"") | L32: =IFERROR(VLOOKUP(D32,'ASE Target (Spares), FY 21-22'!$C$5:$J$39,8,0),"") -> 0 | N32: =IFERROR(M32/L32,"") | O32: =IFERROR(VLOOKUP(D32,'ASE Target (Spares), FY 21-22'!$C$5:$K$39,9,0),"") -> 0 | Q32: =IFERROR(P32/O32,"") | R32: =IFERROR(VLOOKUP(D32,'ASE Target (Spares), FY 21-22'!$C$5:$L$39,10,0),"") -> 0 | T32: =IFERROR(S32/R32,"") | U32: =IFERROR(VLOOKUP(D32,'ASE Target (Spares), FY 21-22'!$C$5:$M$39,11,0),"") -> 0 | W32: =IFERROR(V32/U32,"") | X32: =IFERROR(VLOOKUP(D32,'ASE Target (Spares), FY 21-22'!$C$5:$N$39,12,0),"") -> 0 | Z32: =IFERROR(Y32/X32,"") | AA32: =IFERROR(VLOOKUP(D32,'ASE Target (Spares), FY 21-22'!$C$5:$O$39,13,0),"") -> 450000 | AC32: =IFERROR(AB32/AA32,"") -> 0 | AD32: =IFERROR(VLOOKUP(D32,'ASE Target (Spares), FY 21-22'!$C$5:$P$39,14,0),"") -> 450000 | AF32: =IFERROR(AE32/AD32,"") -> 0 | AG32: =IFERROR(VLOOKUP(D32,'ASE Target (Spares), FY 21-22'!$C$5:$Q$39,15,0),"") -> 450000 | AI32: =IFERROR(AH32/AG32,"") -> 0 | AJ32: =IFERROR(VLOOKUP(D32,'ASE Target (Spares), FY 21-22'!$C$5:$R$39,16,0),"") -> 450000 | AL32: =IFERROR(AK32/AJ32,"") -> 0 | AM32: =IFERROR(VLOOKUP(D32,'ASE Target (Spares), FY 21-22'!$C$5:$S$39,17,0),"") -> 450000 | AO32: =IFERROR(AN32/AM32,"") -> 0 | AP32: =IFERROR(F32+I32+L32+O32+R32+U32+X32+AA32+AD32+AG32+AJ32+AM32,"") -> 2250000 | AQ32: =IFERROR(G32+J32+M32+P32+S32+V32+Y32+AB32+AE32+AH32+AK32+AN32,"") -> 0 | AR32: =IFERROR(AQ32/AP32,"") -> 0
C33: =IF('ASE Target (Spares), FY 21-22'!B32=0,"",'ASE Target (Spares), FY 21-22'!B32) -> CTG | D33: =IF('ASE Target (Spares), FY 21-22'!C32=0,"",'ASE Target (Spares), FY 21-22'!C32) -> Sozol prince | E33: =IF('ASE Target (Spares), FY 21-22'!D32=0,"",'ASE Target (Spares), FY 21-22'!D32) -> 6076 | F33: =IFERROR(VLOOKUP(D33,'ASE Target (Spares), FY 21-22'!$C$5:$H$39,6,0),"") -> 0 | H33: =IFERROR(G33/F33,"") | I33: =IFERROR(VLOOKUP(D33,'ASE Target (Spares), FY 21-22'!$C$5:$I$39,7,0),"") -> 0 | K33: =IFERROR(J33/I33,"") | L33: =IFERROR(VLOOKUP(D33,'ASE Target (Spares), FY 21-22'!$C$5:$J$39,8,0),"") -> 0 | N33: =IFERROR(M33/L33,"") | O33: =IFERROR(VLOOKUP(D33,'ASE Target (Spares), FY 21-22'!$C$5:$K$39,9,0),"") -> 0 | Q33: =IFERROR(P33/O33,"") | R33: =IFERROR(VLOOKUP(D33,'ASE Target (Spares), FY 21-22'!$C$5:$L$39,10,0),"") -> 0 | T33: =IFERROR(S33/R33,"") | U33: =IFERROR(VLOOKUP(D33,'ASE Target (Spares), FY 21-22'!$C$5:$M$39,11,0),"") -> 0 | W33: =IFERROR(V33/U33,"") | X33: =IFERROR(VLOOKUP(D33,'ASE Target (Spares), FY 21-22'!$C$5:$N$39,12,0),"") -> 0 | Z33: =IFERROR(Y33/X33,"") | AA33: =IFERROR(VLOOKUP(D33,'ASE Target (Spares), FY 21-22'!$C$5:$O$39,13,0),"") -> 450000 | AC33: =IFERROR(AB33/AA33,"") -> 0 | AD33: =IFERROR(VLOOKUP(D33,'ASE Target (Spares), FY 21-22'!$C$5:$P$39,14,0),"") -> 450000 | AF33: =IFERROR(AE33/AD33,"") -> 0 | AG33: =IFERROR(VLOOKUP(D33,'ASE Target (Spares), FY 21-22'!$C$5:$Q$39,15,0),"") -> 450000 | AI33: =IFERROR(AH33/AG33,"") -> 0 | AJ33: =IFERROR(VLOOKUP(D33,'ASE Target (Spares), FY 21-22'!$C$5:$R$39,16,0),"") -> 450000 | AL33: =IFERROR(AK33/AJ33,"") -> 0 | AM33: =IFERROR(VLOOKUP(D33,'ASE Target (Spares), FY 21-22'!$C$5:$S$39,17,0),"") -> 450000 | AO33: =IFERROR(AN33/AM33,"") -> 0 | AP33: =IFERROR(F33+I33+L33+O33+R33+U33+X33+AA33+AD33+AG33+AJ33+AM33,"") -> 2250000 | AQ33: =IFERROR(G33+J33+M33+P33+S33+V33+Y33+AB33+AE33+AH33+AK33+AN33,"") -> 0 | AR33: =IFERROR(AQ33/AP33,"") -> 0
C34: =IF('ASE Target (Spares), FY 21-22'!B33=0,"",'ASE Target (Spares), FY 21-22'!B33) | D34: =IF('ASE Target (Spares), FY 21-22'!C33=0,"",'ASE Target (Spares), FY 21-22'!C33) -> New-5 | E34: =IF('ASE Target (Spares), FY 21-22'!D33=0,"",'ASE Target (Spares), FY 21-22'!D33) | F34: =IFERROR(VLOOKUP(D34,'ASE Target (Spares), FY 21-22'!$C$5:$H$39,6,0),"") -> 0 | H34: =IFERROR(G34/F34,"") | I34: =IFERROR(VLOOKUP(D34,'ASE Target (Spares), FY 21-22'!$C$5:$I$39,7,0),"") -> 0 | K34: =IFERROR(J34/I34,"") | L34: =IFERROR(VLOOKUP(D34,'ASE Target (Spares), FY 21-22'!$C$5:$J$39,8,0),"") -> 0 | N34: =IFERROR(M34/L34,"") | O34: =IFERROR(VLOOKUP(D34,'ASE Target (Spares), FY 21-22'!$C$5:$K$39,9,0),"") -> 0 | Q34: =IFERROR(P34/O34,"") | R34: =IFERROR(VLOOKUP(D34,'ASE Target (Spares), FY 21-22'!$C$5:$L$39,10,0),"") -> 0 | T34: =IFERROR(S34/R34,"") | U34: =IFERROR(VLOOKUP(D34,'ASE Target (Spares), FY 21-22'!$C$5:$M$39,11,0),"") -> 0 | W34: =IFERROR(V34/U34,"") | X34: =IFERROR(VLOOKUP(D34,'ASE Target (Spares), FY 21-22'!$C$5:$N$39,12,0),"") -> 0 | Z34: =IFERROR(Y34/X34,"") | AA34: =IFERROR(VLOOKUP(D34,'ASE Target (Spares), FY 21-22'!$C$5:$O$39,13,0),"") -> 0 | AC34: =IFERROR(AB34/AA34,"") | AD34: =IFERROR(VLOOKUP(D34,'ASE Target (Spares), FY 21-22'!$C$5:$P$39,14,0),"") -> 0 | AF34: =IFERROR(AE34/AD34,"") | AG34: =IFERROR(VLOOKUP(D34,'ASE Target (Spares), FY 21-22'!$C$5:$Q$39,15,0),"") -> 0 | AI34: =IFERROR(AH34/AG34,"") | AJ34: =IFERROR(VLOOKUP(D34,'ASE Target (Spares), FY 21-22'!$C$5:$R$39,16,0),"") -> 0 | AL34: =IFERROR(AK34/AJ34,"") | AM34: =IFERROR(VLOOKUP(D34,'ASE Target (Spares), FY 21-22'!$C$5:$S$39,17,0),"") -> 0 | AO34: =IFERROR(AN34/AM34,"") | AP34: =IFERROR(F34+I34+L34+O34+R34+U34+X34+AA34+AD34+AG34+AJ34+AM34,"") -> 0 | AQ34: =IFERROR(G34+J34+M34+P34+S34+V34+Y34+AB34+AE34+AH34+AK34+AN34,"") -> 0 | AR34: =IFERROR(AQ34/AP34,"")
C35: =IF('ASE Target (Spares), FY 21-22'!B34=0,"",'ASE Target (Spares), FY 21-22'!B34) | D35: =IF('ASE Target (Spares), FY 21-22'!C34=0,"",'ASE Target (Spares), FY 21-22'!C34) -> New-6 | E35: =IF('ASE Target (Spares), FY 21-22'!D34=0,"",'ASE Target (Spares), FY 21-22'!D34) | F35: =IFERROR(VLOOKUP(D35,'ASE Target (Spares), FY 21-22'!$C$5:$H$39,6,0),"") -> 0 | H35: =IFERROR(G35/F35,"") | I35: =IFERROR(VLOOKUP(D35,'ASE Target (Spares), FY 21-22'!$C$5:$I$39,7,0),"") -> 0 | K35: =IFERROR(J35/I35,"") | L35: =IFERROR(VLOOKUP(D35,'ASE Target (Spares), FY 21-22'!$C$5:$J$39,8,0),"") -> 0 | N35: =IFERROR(M35/L35,"") | O35: =IFERROR(VLOOKUP(D35,'ASE Target (Spares), FY 21-22'!$C$5:$K$39,9,0),"") -> 0 | Q35: =IFERROR(P35/O35,"") | R35: =IFERROR(VLOOKUP(D35,'ASE Target (Spares), FY 21-22'!$C$5:$L$39,10,0),"") -> 0 | T35: =IFERROR(S35/R35,"") | U35: =IFERROR(VLOOKUP(D35,'ASE Target (Spares), FY 21-22'!$C$5:$M$39,11,0),"") -> 0 | W35: =IFERROR(V35/U35,"") | X35: =IFERROR(VLOOKUP(D35,'ASE Target (Spares), FY 21-22'!$C$5:$N$39,12,0),"") -> 0 | Z35: =IFERROR(Y35/X35,"") | AA35: =IFERROR(VLOOKUP(D35,'ASE Target (Spares), FY 21-22'!$C$5:$O$39,13,0),"") -> 0 | AC35: =IFERROR(AB35/AA35,"") | AD35: =IFERROR(VLOOKUP(D35,'ASE Target (Spares), FY 21-22'!$C$5:$P$39,14,0),"") -> 0 | AF35: =IFERROR(AE35/AD35,"") | AG35: =IFERROR(VLOOKUP(D35,'ASE Target (Spares), FY 21-22'!$C$5:$Q$39,15,0),"") -> 0 | AI35: =IFERROR(AH35/AG35,"") | AJ35: =IFERROR(VLOOKUP(D35,'ASE Target (Spares), FY 21-22'!$C$5:$R$39,16,0),"") -> 0 | AL35: =IFERROR(AK35/AJ35,"") | AM35: =IFERROR(VLOOKUP(D35,'ASE Target (Spares), FY 21-22'!$C$5:$S$39,17,0),"") -> 0 | AO35: =IFERROR(AN35/AM35,"") | AP35: =IFERROR(F35+I35+L35+O35+R35+U35+X35+AA35+AD35+AG35+AJ35+AM35,"") -> 0 | AQ35: =IFERROR(G35+J35+M35+P35+S35+V35+Y35+AB35+AE35+AH35+AK35+AN35,"") -> 0 | AR35: =IFERROR(AQ35/AP35,"")
C36: =IF('ASE Target (Spares), FY 21-22'!B35=0,"",'ASE Target (Spares), FY 21-22'!B35) | D36: =IF('ASE Target (Spares), FY 21-22'!C35=0,"",'ASE Target (Spares), FY 21-22'!C35) | E36: =IF('ASE Target (Spares), FY 21-22'!D35=0,"",'ASE Target (Spares), FY 21-22'!D35)
B39: Collection (Spares) | G39: input▼ | J39: input▼ | M39: input▼ | P39: input▼ | S39: input▼ | V39: input▼ | Y39: input▼ | AB39: input▼ | AE39: input▼ | AH39: input▼ | AK39: input▼ | AN39: input▼
B40: =B5 -> Sl. | C40: =C5 -> Wing | D40: =D5 -> Name | E40: =E5 -> ID | F40: Jul | I40: Aug | L40: Sep | O40: Oct | R40: Nov | U40: Dec | X40: Jan | AA40: Feb | AD40: Mar | AG40: Apr | AJ40: May | AM40: Jun | AP40: Total (Jul-May)
F41: Target | G41: Ach | H41: Ach (%) | I41: Target | J41: Ach | K41: Ach (%) | L41: Target | M41: Ach | N41: Ach (%) | O41: Target | P41: Ach | Q41: Ach (%) | R41: Target | S41: Ach | T41: Ach (%) | U41: Target | V41: Ach | W41: Ach (%) | X41: Target | Y41: Ach | Z41: Ach (%) | AA41: Target | AB41: Ach | AC41: Ach (%) | AD41: Target | AE41: Ach | AF41: Ach (%) | AG41: Target | AH41: Ach | AI41: Ach (%) | AJ41: Target | AK41: Ach | AL41: Ach (%) | AM41: Target | AN41: Ach | AO41: Ach (%) | AP41: Target | AQ41: Ach | AR41: Ach (%)
B42: =B7 -> 1 | C42: =IF(C7=0,"",C7) -> DSL-DHK | D42: =IF(D7=0,"",D7) -> Md. Shohidul | E42: =IF(E7=0,"",E7) -> 1418 | F42: =IFERROR(VLOOKUP(D42,'ASE Target (Spares), FY 21-22'!$C$40:$H$69,6,0),"") -> 225000 | G42: 327024 | H42: =IFERROR(G42/F42,"") -> 1.45344 | I42: =IFERROR(VLOOKUP(D42,'ASE Target (Spares), FY 21-22'!$C$40:$I$69,7,0),"") -> 225000 | K42: =IFERROR(J42/I42,"") -> 0 | L42: =IFERROR(VLOOKUP(D42,'ASE Target (Spares), FY 21-22'!$C$40:$J$69,8,0),"") -> 0 | N42: =IFERROR(M42/L42,"") | O42: =IFERROR(VLOOKUP(D42,'ASE Target (Spares), FY 21-22'!$C$40:$K$69,9,0),"") -> 0 | Q42: =IFERROR(P42/O42,"") | R42: =IFERROR(VLOOKUP(D42,'ASE Target (Spares), FY 21-22'!$C$40:$L$69,10,0),"") -> 0 | T42: =IFERROR(S42/R42,"") | U42: =IFERROR(VLOOKUP(D42,'ASE Target (Spares), FY 21-22'!$C$40:$M$69,11,0),"") -> 0 | W42: =IFERROR(V42/U42,"") | X42: =IFERROR(VLOOKUP(D42,'ASE Target (Spares), FY 21-22'!$C$40:$N$69,12,0),"") -> 0 | Z42: =IFERROR(Y42/X42,"") | AA42: =IFERROR(VLOOKUP(D42,'ASE Target (Spares), FY 21-22'!$C$40:$O$69,13,0),"") -> 270000 | AC42: =IFERROR(AB42/AA42,"") -> 0 | AD42: =IFERROR(VLOOKUP(D42,'ASE Target (Spares), FY 21-22'!$C$40:$P$69,14,0),"") -> 405000 | AF42: =IFERROR(AE42/AD42,"") -> 0 | AG42: =IFERROR(VLOOKUP(D42,'ASE Target (Spares), FY 21-22'!$C$40:$Q$69,15,0),"") -> 315000 | AI42: =IFERROR(AH42/AG42,"") -> 0 | AJ42: =IFERROR(VLOOKUP(D42,'ASE Target (Spares), FY 21-22'!$C$40:$R$69,16,0),"") -> 360000 | AL42: =IFERROR(AK42/AJ42,"") -> 0 | AM42: =IFERROR(VLOOKUP(D42,'ASE Target (Spares), FY 21-22'!$C$40:$S$69,17,0),"") -> 405000 | AN42: 524292 | AO42: =IFERROR(AN42/AM42,"") -> 1.2945481 | AP42: =IFERROR(F42+I42+L42+O42+R42+U42+X42+AA42+AD42+AG42+AJ42+AM42,"") -> 2205000 | AQ42: =IFERROR(G42+J42+M42+P42+S42+V42+Y42+AB42+AE42+AH42+AK42+AN42,"") -> 851316 | AR42: =IFERROR(AQ42/AP42,"") -> 0.38608435
B43: =B8 -> 2 | C43: =IF(C8=0,"",C8) -> DSL-DHK | D43: =IF(D8=0,"",D8) -> Sagar Chakrobarti | E43: =IF(E8=0,"",E8) -> 2701 | F43: =IFERROR(VLOOKUP(D43,'ASE Target (Spares), FY 21-22'!$C$40:$H$69,6,0),"") -> 0 | H43: =IFERROR(G43/F43,"") | I43: =IFERROR(VLOOKUP(D43,'ASE Target (Spares), FY 21-22'!$C$40:$I$69,7,0),"") -> 0 | K43: =IFERROR(J43/I43,"") | L43: =IFERROR(VLOOKUP(D43,'ASE Target (Spares), FY 21-22'!$C$40:$J$69,8,0),"") -> 0 | N43: =IFERROR(M43/L43,"") | O43: =IFERROR(VLOOKUP(D43,'ASE Target (Spares), FY 21-22'!$C$40:$K$69,9,0),"") -> 0 | Q43: =IFERROR(P43/O43,"") | R43: =IFERROR(VLOOKUP(D43,'ASE Target (Spares), FY 21-22'!$C$40:$L$69,10,0),"") -> 0 | T43: =IFERROR(S43/R43,"") | U43: =IFERROR(VLOOKUP(D43,'ASE Target (Spares), FY 21-22'!$C$40:$M$69,11,0),"") -> 0 | W43: =IFERROR(V43/U43,"") | X43: =IFERROR(VLOOKUP(D43,'ASE Target (Spares), FY 21-22'!$C$40:$N$69,12,0),"") -> 0 | Z43: =IFERROR(Y43/X43,"") | AA43: =IFERROR(VLOOKUP(D43,'ASE Target (Spares), FY 21-22'!$C$40:$O$69,13,0),"") -> 112500 | AC43: =IFERROR(AB43/AA43,"") -> 0 | AD43: =IFERROR(VLOOKUP(D43,'ASE Target (Spares), FY 21-22'!$C$40:$P$69,14,0),"") -> 112500 | AF43: =IFERROR(AE43/AD43,"") -> 0 | AG43: =IFERROR(VLOOKUP(D43,'ASE Target (Spares), FY 21-22'!$C$40:$Q$69,15,0),"") -> 0 | AI43: =IFERROR(AH43/AG43,"") | AJ43: =IFERROR(VLOOKUP(D43,'ASE Target (Spares), FY 21-22'!$C$40:$R$69,16,0),"") -> 0 | AL43: =IFERROR(AK43/AJ43,"") | AM43: =IFERROR(VLOOKUP(D43,'ASE Target (Spares), FY 21-22'!$C$40:$S$69,17,0),"") -> 0 | AO43: =IFERROR(AN43/AM43,"") | AP43: =IFERROR(F43+I43+L43+O43+R43+U43+X43+AA43+AD43+AG43+AJ43+AM43,"") -> 225000 | AQ43: =IFERROR(G43+J43+M43+P43+S43+V43+Y43+AB43+AE43+AH43+AK43+AN43,"") -> 0 | AR43: =IFERROR(AQ43/AP43,"") -> 0
B44: =B9 -> 3 | C44: =IF(C9=0,"",C9) -> DSL-DHK | D44: =IF(D9=0,"",D9) -> Md. Minhazul Islam | E44: =IF(E9=0,"",E9) -> 2330 | F44: =IFERROR(VLOOKUP(D44,'ASE Target (Spares), FY 21-22'!$C$40:$H$69,6,0),"") -> 0 | H44: =IFERROR(G44/F44,"") | I44: =IFERROR(VLOOKUP(D44,'ASE Target (Spares), FY 21-22'!$C$40:$I$69,7,0),"") -> 0 | K44: =IFERROR(J44/I44,"") | L44: =IFERROR(VLOOKUP(D44,'ASE Target (Spares), FY 21-22'!$C$40:$J$69,8,0),"") -> 0 | N44: =IFERROR(M44/L44,"") | O44: =IFERROR(VLOOKUP(D44,'ASE Target (Spares), FY 21-22'!$C$40:$K$69,9,0),"") -> 0 | Q44: =IFERROR(P44/O44,"") | R44: =IFERROR(VLOOKUP(D44,'ASE Target (Spares), FY 21-22'!$C$40:$L$69,10,0),"") -> 0 | T44: =IFERROR(S44/R44,"") | U44: =IFERROR(VLOOKUP(D44,'ASE Target (Spares), FY 21-22'!$C$40:$M$69,11,0),"") -> 0 | W44: =IFERROR(V44/U44,"") | X44: =IFERROR(VLOOKUP(D44,'ASE Target (Spares), FY 21-22'!$C$40:$N$69,12,0),"") -> 0 | Z44: =IFERROR(Y44/X44,"") | AA44: =IFERROR(VLOOKUP(D44,'ASE Target (Spares), FY 21-22'!$C$40:$O$69,13,0),"") -> 450000 | AC44: =IFERROR(AB44/AA44,"") -> 0 | AD44: =IFERROR(VLOOKUP(D44,'ASE Target (Spares), FY 21-22'!$C$40:$P$69,14,0),"") -> 900000 | AF44: =IFERROR(AE44/AD44,"") -> 0 | AG44: =IFERROR(VLOOKUP(D44,'ASE Target (Spares), FY 21-22'!$C$40:$Q$69,15,0),"") -> 450000 | AI44: =IFERROR(AH44/AG44,"") -> 0 | AJ44: =IFERROR(VLOOKUP(D44,'ASE Target (Spares), FY 21-22'!$C$40:$R$69,16,0),"") -> 0 | AL44: =IFERROR(AK44/AJ44,"") | AM44: =IFERROR(VLOOKUP(D44,'ASE Target (Spares), FY 21-22'!$C$40:$S$69,17,0),"") -> 0 | AO44: =IFERROR(AN44/AM44,"") | AP44: =IFERROR(F44+I44+L44+O44+R44+U44+X44+AA44+AD44+AG44+AJ44+AM44,"") -> 1800000 | AQ44: =IFERROR(G44+J44+M44+P44+S44+V44+Y44+AB44+AE44+AH44+AK44+AN44,"") -> 0 | AR44: =IFERROR(AQ44/AP44,"") -> 0
B45: =B10 -> 4 | C45: =IF(C10=0,"",C10) -> DSL-DHK | D45: =IF(D10=0,"",D10) -> Md. Nazmul Hasan Titu | E45: =IF(E10=0,"",E10) -> 2913 | F45: =IFERROR(VLOOKUP(D45,'ASE Target (Spares), FY 21-22'!$C$40:$H$69,6,0),"") -> 112500 | G45: 709063 | H45: =IFERROR(G45/F45,"") -> 6.3027822 | I45: =IFERROR(VLOOKUP(D45,'ASE Target (Spares), FY 21-22'!$C$40:$I$69,7,0),"") -> 112500 | K45: =IFERROR(J45/I45,"") -> 0 | L45: =IFERROR(VLOOKUP(D45,'ASE Target (Spares), FY 21-22'!$C$40:$J$69,8,0),"") -> 0 | N45: =IFERROR(M45/L45,"") | O45: =IFERROR(VLOOKUP(D45,'ASE Target (Spares), FY 21-22'!$C$40:$K$69,9,0),"") -> 0 | Q45: =IFERROR(P45/O45,"") | R45: =IFERROR(VLOOKUP(D45,'ASE Target (Spares), FY 21-22'!$C$40:$L$69,10,0),"") -> 0 | T45: =IFERROR(S45/R45,"") | U45: =IFERROR(VLOOKUP(D45,'ASE Target (Spares), FY 21-22'!$C$40:$M$69,11,0),"") -> 0 | W45: =IFERROR(V45/U45,"") | X45: =IFERROR(VLOOKUP(D45,'ASE Target (Spares), FY 21-22'!$C$40:$N$69,12,0),"") -> 0 | Z45: =IFERROR(Y45/X45,"") | AA45: =IFERROR(VLOOKUP(D45,'ASE Target (Spares), FY 21-22'!$C$40:$O$69,13,0),"") -> 112500 | AC45: =IFERROR(AB45/AA45,"") -> 0 | AD45: =IFERROR(VLOOKUP(D45,'ASE Target (Spares), FY 21-22'!$C$40:$P$69,14,0),"") -> 225000 | AF45: =IFERROR(AE45/AD45,"") -> 0 | AG45: =IFERROR(VLOOKUP(D45,'ASE Target (Spares), FY 21-22'!$C$40:$Q$69,15,0),"") -> 225000 | AI45: =IFERROR(AH45/AG45,"") -> 0 | AJ45: =IFERROR(VLOOKUP(D45,'ASE Target (Spares), FY 21-22'!$C$40:$R$69,16,0),"") -> 225000 | AL45: =IFERROR(AK45/AJ45,"") -> 0 | AM45: =IFERROR(VLOOKUP(D45,'ASE Target (Spares), FY 21-22'!$C$40:$S$69,17,0),"") -> 225000 | AO45: =IFERROR(AN45/AM45,"") -> 0 | AP45: =IFERROR(F45+I45+L45+O45+R45+U45+X45+AA45+AD45+AG45+AJ45+AM45,"") -> 1237500 | AQ45: =IFERROR(G45+J45+M45+P45+S45+V45+Y45+AB45+AE45+AH45+AK45+AN45,"") -> 709063 | AR45: =IFERROR(AQ45/AP45,"") -> 0.5729802
B46: =B11 -> 5 | C46: =IF(C11=0,"",C11) -> DSL-DHK | D46: =IF(D11=0,"",D11) -> Md. Zahirul Islam | E46: =IF(E11=0,"",E11) -> 2914 | F46: =IFERROR(VLOOKUP(D46,'ASE Target (Spares), FY 21-22'!$C$40:$H$69,6,0),"") -> 450000 | G46: 764379 | H46: =IFERROR(G46/F46,"") -> 1.69862 | I46: =IFERROR(VLOOKUP(D46,'ASE Target (Spares), FY 21-22'!$C$40:$I$69,7,0),"") -> 450000 | K46: =IFERROR(J46/I46,"") -> 0 | L46: =IFERROR(VLOOKUP(D46,'ASE Target (Spares), FY 21-22'!$C$40:$J$69,8,0),"") -> 0 | N46: =IFERROR(M46/L46,"") | O46: =IFERROR(VLOOKUP(D46,'ASE Target (Spares), FY 21-22'!$C$40:$K$69,9,0),"") -> 0 | Q46: =IFERROR(P46/O46,"") | R46: =IFERROR(VLOOKUP(D46,'ASE Target (Spares), FY 21-22'!$C$40:$L$69,10,0),"") -> 0 | T46: =IFERROR(S46/R46,"") | U46: =IFERROR(VLOOKUP(D46,'ASE Target (Spares), FY 21-22'!$C$40:$M$69,11,0),"") -> 0 | W46: =IFERROR(V46/U46,"") | X46: =IFERROR(VLOOKUP(D46,'ASE Target (Spares), FY 21-22'!$C$40:$N$69,12,0),"") -> 0 | Z46: =IFERROR(Y46/X46,"") | AA46: =IFERROR(VLOOKUP(D46,'ASE Target (Spares), FY 21-22'!$C$40:$O$69,13,0),"") -> 360000 | AC46: =IFERROR(AB46/AA46,"") -> 0 | AD46: =IFERROR(VLOOKUP(D46,'ASE Target (Spares), FY 21-22'!$C$40:$P$69,14,0),"") -> 720000 | AF46: =IFERROR(AE46/AD46,"") -> 0 | AG46: =IFERROR(VLOOKUP(D46,'ASE Target (Spares), FY 21-22'!$C$40:$Q$69,15,0),"") -> 810000 | AI46: =IFERROR(AH46/AG46,"") -> 0 | AJ46: =IFERROR(VLOOKUP(D46,'ASE Target (Spares), FY 21-22'!$C$40:$R$69,16,0),"") -> 900000 | AL46: =IFERROR(AK46/AJ46,"") -> 0 | AM46: =IFERROR(VLOOKUP(D46,'ASE Target (Spares), FY 21-22'!$C$40:$S$69,17,0),"") -> 900000 | AN46: 379543 | AO46: =IFERROR(AN46/AM46,"") -> 0.42171444 | AP46: =IFERROR(F46+I46+L46+O46+R46+U46+X46+AA46+AD46+AG46+AJ46+AM46,"") -> 4590000 | AQ46: =IFERROR(G46+J46+M46+P46+S46+V46+Y46+AB46+AE46+AH46+AK46+AN46,"") -> 1143922 | AR46: =IFERROR(AQ46/AP46,"") -> 0.24922048
B47: =B12 -> 6 | C47: =IF(C12=0,"",C12) -> DSL-DHK | D47: =IF(D12=0,"",D12) -> Md. Rakibul Hasan | E47: =IF(E12=0,"",E12) -> 2927 | F47: =IFERROR(VLOOKUP(D47,'ASE Target (Spares), FY 21-22'!$C$40:$H$69,6,0),"") -> 135000 | G47: 517716 | H47: =IFERROR(G47/F47,"") -> 3.8349333 | I47: =IFERROR(VLOOKUP(D47,'ASE Target (Spares), FY 21-22'!$C$40:$I$69,7,0),"") -> 135000 | K47: =IFERROR(J47/I47,"") -> 0 | L47: =IFERROR(VLOOKUP(D47,'ASE Target (Spares), FY 21-22'!$C$40:$J$69,8,0),"") -> 0 | N47: =IFERROR(M47/L47,"") | O47: =IFERROR(VLOOKUP(D47,'ASE Target (Spares), FY 21-22'!$C$40:$K$69,9,0),"") -> 0 | Q47: =IFERROR(P47/O47,"") | R47: =IFERROR(VLOOKUP(D47,'ASE Target (Spares), FY 21-22'!$C$40:$L$69,10,0),"") -> 0 | T47: =IFERROR(S47/R47,"") | U47: =IFERROR(VLOOKUP(D47,'ASE Target (Spares), FY 21-22'!$C$40:$M$69,11,0),"") -> 0 | W47: =IFERROR(V47/U47,"") | X47: =IFERROR(VLOOKUP(D47,'ASE Target (Spares), FY 21-22'!$C$40:$N$69,12,0),"") -> 0 | Z47: =IFERROR(Y47/X47,"") | AA47: =IFERROR(VLOOKUP(D47,'ASE Target (Spares), FY 21-22'!$C$40:$O$69,13,0),"") -> 180000 | AC47: =IFERROR(AB47/AA47,"") -> 0 | AD47: =IFERROR(VLOOKUP(D47,'ASE Target (Spares), FY 21-22'!$C$40:$P$69,14,0),"") -> 315000 | AF47: =IFERROR(AE47/AD47,"") -> 0 | AG47: =IFERROR(VLOOKUP(D47,'ASE Target (Spares), FY 21-22'!$C$40:$Q$69,15,0),"") -> 270000 | AI47: =IFERROR(AH47/AG47,"") -> 0 | AJ47: =IFERROR(VLOOKUP(D47,'ASE Target (Spares), FY 21-22'!$C$40:$R$69,16,0),"") -> 270000 | AL47: =IFERROR(AK47/AJ47,"") -> 0 | AM47: =IFERROR(VLOOKUP(D47,'ASE Target (Spares), FY 21-22'!$C$40:$S$69,17,0),"") -> 270000 | AO47: =IFERROR(AN47/AM47,"") -> 0 | AP47: =IFERROR(F47+I47+L47+O47+R47+U47+X47+AA47+AD47+AG47+AJ47+AM47,"") -> 1575000 | AQ47: =IFERROR(G47+J47+M47+P47+S47+V47+Y47+AB47+AE47+AH47+AK47+AN47,"") -> 517716 | AR47: =IFERROR(AQ47/AP47,"") -> 0.32870857
B48: =B13 -> 7 | C48: =IF(C13=0,"",C13) -> DSL-DHK | D48: =IF(D13=0,"",D13) -> Md Ariful Islam | E48: =IF(E13=0,"",E13) -> 2699 | F48: =IFERROR(VLOOKUP(D48,'ASE Target (Spares), FY 21-22'!$C$40:$H$69,6,0),"") -> 180000 | H48: =IFERROR(G48/F48,"") -> 0 | I48: =IFERROR(VLOOKUP(D48,'ASE Target (Spares), FY 21-22'!$C$40:$I$69,7,0),"") -> 180000 | K48: =IFERROR(J48/I48,"") -> 0 | L48: =IFERROR(VLOOKUP(D48,'ASE Target (Spares), FY 21-22'!$C$40:$J$69,8,0),"") -> 0 | N48: =IFERROR(M48/L48,"") | O48: =IFERROR(VLOOKUP(D48,'ASE Target (Spares), FY 21-22'!$C$40:$K$69,9,0),"") -> 0 | Q48: =IFERROR(P48/O48,"") | R48: =IFERROR(VLOOKUP(D48,'ASE Target (Spares), FY 21-22'!$C$40:$L$69,10,0),"") -> 0 | T48: =IFERROR(S48/R48,"") | U48: =IFERROR(VLOOKUP(D48,'ASE Target (Spares), FY 21-22'!$C$40:$M$69,11,0),"") -> 0 | W48: =IFERROR(V48/U48,"") | X48: =IFERROR(VLOOKUP(D48,'ASE Target (Spares), FY 21-22'!$C$40:$N$69,12,0),"") -> 0 | Z48: =IFERROR(Y48/X48,"") | AA48: =IFERROR(VLOOKUP(D48,'ASE Target (Spares), FY 21-22'!$C$40:$O$69,13,0),"") -> 0 | AC48: =IFERROR(AB48/AA48,"") | AD48: =IFERROR(VLOOKUP(D48,'ASE Target (Spares), FY 21-22'!$C$40:$P$69,14,0),"") -> 180000 | AF48: =IFERROR(AE48/AD48,"") -> 0 | AG48: =IFERROR(VLOOKUP(D48,'ASE Target (Spares), FY 21-22'!$C$40:$Q$69,15,0),"") -> 360000 | AI48: =IFERROR(AH48/AG48,"") -> 0 | AJ48: =IFERROR(VLOOKUP(D48,'ASE Target (Spares), FY 21-22'!$C$40:$R$69,16,0),"") -> 360000 | AL48: =IFERROR(AK48/AJ48,"") -> 0 | AM48: =IFERROR(VLOOKUP(D48,'ASE Target (Spares), FY 21-22'!$C$40:$S$69,17,0),"") -> 360000 | AO48: =IFERROR(AN48/AM48,"") -> 0 | AP48: =IFERROR(F48+I48+L48+O48+R48+U48+X48+AA48+AD48+AG48+AJ48+AM48,"") -> 1620000 | AQ48: =IFERROR(G48+J48+M48+P48+S48+V48+Y48+AB48+AE48+AH48+AK48+AN48,"") -> 0 | AR48: =IFERROR(AQ48/AP48,"") -> 0
B49: =B14 -> 8 | C49: =IF(C14=0,"",C14) -> DSL-DHK | D49: =IF(D14=0,"",D14) -> Mohammad Jewel Rana | E49: =IF(E14=0,"",E14) -> 3002 | F49: =IFERROR(VLOOKUP(D49,'ASE Target (Spares), FY 21-22'!$C$40:$H$69,6,0),"") -> 270000 | G49: 437175 | H49: =IFERROR(G49/F49,"") -> 1.6191667 | I49: =IFERROR(VLOOKUP(D49,'ASE Target (Spares), FY 21-22'!$C$40:$I$69,7,0),"") -> 270000 | K49: =IFERROR(J49/I49,"") -> 0 | L49: =IFERROR(VLOOKUP(D49,'ASE Target (Spares), FY 21-22'!$C$40:$J$69,8,0),"") -> 0 | N49: =IFERROR(M49/L49,"") | O49: =IFERROR(VLOOKUP(D49,'ASE Target (Spares), FY 21-22'!$C$40:$K$69,9,0),"") -> 0 | Q49: =IFERROR(P49/O49,"") | R49: =IFERROR(VLOOKUP(D49,'ASE Target (Spares), FY 21-22'!$C$40:$L$69,10,0),"") -> 0 | T49: =IFERROR(S49/R49,"") | U49: =IFERROR(VLOOKUP(D49,'ASE Target (Spares), FY 21-22'!$C$40:$M$69,11,0),"") -> 0 | W49: =IFERROR(V49/U49,"") | X49: =IFERROR(VLOOKUP(D49,'ASE Target (Spares), FY 21-22'!$C$40:$N$69,12,0),"") -> 0 | Z49: =IFERROR(Y49/X49,"") | AA49: =IFERROR(VLOOKUP(D49,'ASE Target (Spares), FY 21-22'!$C$40:$O$69,13,0),"") -> 270000 | AC49: =IFERROR(AB49/AA49,"") -> 0 | AD49: =IFERROR(VLOOKUP(D49,'ASE Target (Spares), FY 21-22'!$C$40:$P$69,14,0),"") -> 540000 | AF49: =IFERROR(AE49/AD49,"") -> 0 | AG49: =IFERROR(VLOOKUP(D49,'ASE Target (Spares), FY 21-22'!$C$40:$Q$69,15,0),"") -> 540000 | AI49: =IFERROR(AH49/AG49,"") -> 0 | AJ49: =IFERROR(VLOOKUP(D49,'ASE Target (Spares), FY 21-22'!$C$40:$R$69,16,0),"") -> 540000 | AL49: =IFERROR(AK49/AJ49,"") -> 0 | AM49: =IFERROR(VLOOKUP(D49,'ASE Target (Spares), FY 21-22'!$C$40:$S$69,17,0),"") -> 540000 | AN49: 204229 | AO49: =IFERROR(AN49/AM49,"") -> 0.37820185 | AP49: =IFERROR(F49+I49+L49+O49+R49+U49+X49+AA49+AD49+AG49+AJ49+AM49,"") -> 2970000 | AQ49: =IFERROR(G49+J49+M49+P49+S49+V49+Y49+AB49+AE49+AH49+AK49+AN49,"") -> 641404 | AR49: =IFERROR(AQ49/AP49,"") -> 0.21596094
B50: =B15 -> 9 | C50: =IF(C15=0,"",C15) -> DSL-DHK | D50: =IF(D15=0,"",D15) -> Faysal Ahmed | E50: =IF(E15=0,"",E15) -> 3004 | F50: =IFERROR(VLOOKUP(D50,'ASE Target (Spares), FY 21-22'!$C$40:$H$69,6,0),"") -> 270000 | G50: 505895 | H50: =IFERROR(G50/F50,"") -> 1.8736852 | I50: =IFERROR(VLOOKUP(D50,'ASE Target (Spares), FY 21-22'!$C$40:$I$69,7,0),"") -> 270000 | K50: =IFERROR(J50/I50,"") -> 0 | L50: =IFERROR(VLOOKUP(D50,'ASE Target (Spares), FY 21-22'!$C$40:$J$69,8,0),"") -> 0 | N50: =IFERROR(M50/L50,"") | O50: =IFERROR(VLOOKUP(D50,'ASE Target (Spares), FY 21-22'!$C$40:$K$69,9,0),"") -> 0 | Q50: =IFERROR(P50/O50,"") | R50: =IFERROR(VLOOKUP(D50,'ASE Target (Spares), FY 21-22'!$C$40:$L$69,10,0),"") -> 0 | T50: =IFERROR(S50/R50,"") | U50: =IFERROR(VLOOKUP(D50,'ASE Target (Spares), FY 21-22'!$C$40:$M$69,11,0),"") -> 0 | W50: =IFERROR(V50/U50,"") | X50: =IFERROR(VLOOKUP(D50,'ASE Target (Spares), FY 21-22'!$C$40:$N$69,12,0),"") -> 0 | Z50: =IFERROR(Y50/X50,"") | AA50: =IFERROR(VLOOKUP(D50,'ASE Target (Spares), FY 21-22'!$C$40:$O$69,13,0),"") -> 270000 | AC50: =IFERROR(AB50/AA50,"") -> 0 | AD50: =IFERROR(VLOOKUP(D50,'ASE Target (Spares), FY 21-22'!$C$40:$P$69,14,0),"") -> 540000 | AF50: =IFERROR(AE50/AD50,"") -> 0 | AG50: =IFERROR(VLOOKUP(D50,'ASE Target (Spares), FY 21-22'!$C$40:$Q$69,15,0),"") -> 540000 | AI50: =IFERROR(AH50/AG50,"") -> 0 | AJ50: =IFERROR(VLOOKUP(D50,'ASE Target (Spares), FY 21-22'!$C$40:$R$69,16,0),"") -> 540000 | AL50: =IFERROR(AK50/AJ50,"") -> 0 | AM50: =IFERROR(VLOOKUP(D50,'ASE Target (Spares), FY 21-22'!$C$40:$S$69,17,0),"") -> 540000 | AN50: 704720 | AO50: =IFERROR(AN50/AM50,"") -> 1.305037 | AP50: =IFERROR(F50+I50+L50+O50+R50+U50+X50+AA50+AD50+AG50+AJ50+AM50,"") -> 2970000 | AQ50: =IFERROR(G50+J50+M50+P50+S50+V50+Y50+AB50+AE50+AH50+AK50+AN50,"") -> 1210615 | AR50: =IFERROR(AQ50/AP50,"") -> 0.40761448
B51: =B16 -> 10 | C51: =IF(C16=0,"",C16) -> DSL-DHK | D51: =IF(D16=0,"",D16) -> Rakibul Islam Razib | E51: =IF(E16=0,"",E16) -> 3006 | F51: =IFERROR(VLOOKUP(D51,'ASE Target (Spares), FY 21-22'!$C$40:$H$69,6,0),"") -> 112500 | G51: 129195 | H51: =IFERROR(G51/F51,"") -> 1.1484 | I51: =IFERROR(VLOOKUP(D51,'ASE Target (Spares), FY 21-22'!$C$40:$I$69,7,0),"") -> 112500 | K51: =IFERROR(J51/I51,"") -> 0 | L51: =IFERROR(VLOOKUP(D51,'ASE Target (Spares), FY 21-22'!$C$40:$J$69,8,0),"") -> 0 | N51: =IFERROR(M51/L51,"") | O51: =IFERROR(VLOOKUP(D51,'ASE Target (Spares), FY 21-22'!$C$40:$K$69,9,0),"") -> 0 | Q51: =IFERROR(P51/O51,"") | R51: =IFERROR(VLOOKUP(D51,'ASE Target (Spares), FY 21-22'!$C$40:$L$69,10,0),"") -> 0 | T51: =IFERROR(S51/R51,"") | U51: =IFERROR(VLOOKUP(D51,'ASE Target (Spares), FY 21-22'!$C$40:$M$69,11,0),"") -> 0 | W51: =IFERROR(V51/U51,"") | X51: =IFERROR(VLOOKUP(D51,'ASE Target (Spares), FY 21-22'!$C$40:$N$69,12,0),"") -> 0 | Z51: =IFERROR(Y51/X51,"") | AA51: =IFERROR(VLOOKUP(D51,'ASE Target (Spares), FY 21-22'!$C$40:$O$69,13,0),"") -> 0 | AC51: =IFERROR(AB51/AA51,"") | AD51: =IFERROR(VLOOKUP(D51,'ASE Target (Spares), FY 21-22'!$C$40:$P$69,14,0),"") -> 103500 | AF51: =IFERROR(AE51/AD51,"") -> 0 | AG51: =IFERROR(VLOOKUP(D51,'ASE Target (Spares), FY 21-22'!$C$40:$Q$69,15,0),"") -> 207000 | AI51: =IFERROR(AH51/AG51,"") -> 0 | AJ51: =IFERROR(VLOOKUP(D51,'ASE Target (Spares), FY 21-22'!$C$40:$R$69,16,0),"") -> 216000 | AL51: =IFERROR(AK51/AJ51,"") -> 0 | AM51: =IFERROR(VLOOKUP(D51,'ASE Target (Spares), FY 21-22'!$C$40:$S$69,17,0),"") -> 225000 | AN51: 143022 | AO51: =IFERROR(AN51/AM51,"") -> 0.63565333 | AP51: =IFERROR(F51+I51+L51+O51+R51+U51+X51+AA51+AD51+AG51+AJ51+AM51,"") -> 976500 | AQ51: =IFERROR(G51+J51+M51+P51+S51+V51+Y51+AB51+AE51+AH51+AK51+AN51,"") -> 272217 | AR51: =IFERROR(AQ51/AP51,"") -> 0.27876805
B52: =B17 -> 11 | C52: =IF(C17=0,"",C17) -> DSL-DHK | D52: =IF(D17=0,"",D17) -> Ashraful Islam | E52: =IF(E17=0,"",E17) -> 3003 | F52: =IFERROR(VLOOKUP(D52,'ASE Target (Spares), FY 21-22'!$C$40:$H$69,6,0),"") -> 225000 | G52: 747948 | H52: =IFERROR(G52/F52,"") -> 3.3242133 | I52: =IFERROR(VLOOKUP(D52,'ASE Target (Spares), FY 21-22'!$C$40:$I$69,7,0),"") -> 225000 | K52: =IFERROR(J52/I52,"") -> 0 | L52: =IFERROR(VLOOKUP(D52,'ASE Target (Spares), FY 21-22'!$C$40:$J$69,8,0),"") -> 0 | N52: =IFERROR(M52/L52,"") | O52: =IFERROR(VLOOKUP(D52,'ASE Target (Spares), FY 21-22'!$C$40:$K$69,9,0),"") -> 0 | Q52: =IFERROR(P52/O52,"") | R52: =IFERROR(VLOOKUP(D52,'ASE Target (Spares), FY 21-22'!$C$40:$L$69,10,0),"") -> 0 | T52: =IFERROR(S52/R52,"") | U52: =IFERROR(VLOOKUP(D52,'ASE Target (Spares), FY 21-22'!$C$40:$M$69,11,0),"") -> 0 | W52: =IFERROR(V52/U52,"") | X52: =IFERROR(VLOOKUP(D52,'ASE Target (Spares), FY 21-22'!$C$40:$N$69,12,0),"") -> 0 | Z52: =IFERROR(Y52/X52,"") | AA52: =IFERROR(VLOOKUP(D52,'ASE Target (Spares), FY 21-22'!$C$40:$O$69,13,0),"") -> 360000 | AC52: =IFERROR(AB52/AA52,"") -> 0 | AD52: =IFERROR(VLOOKUP(D52,'ASE Target (Spares), FY 21-22'!$C$40:$P$69,14,0),"") -> 720000 | AF52: =IFERROR(AE52/AD52,"") -> 0 | AG52: =IFERROR(VLOOKUP(D52,'ASE Target (Spares), FY 21-22'!$C$40:$Q$69,15,0),"") -> 585000 | AI52: =IFERROR(AH52/AG52,"") -> 0 | AJ52: =IFERROR(VLOOKUP(D52,'ASE Target (Spares), FY 21-22'!$C$40:$R$69,16,0),"") -> 450000 | AL52: =IFERROR(AK52/AJ52,"") -> 0 | AM52: =IFERROR(VLOOKUP(D52,'ASE Target (Spares), FY 21-22'!$C$40:$S$69,17,0),"") -> 450000 | AN52: 738191 | AO52: =IFERROR(AN52/AM52,"") -> 1.6404244 | AP52: =IFERROR(F52+I52+L52+O52+R52+U52+X52+AA52+AD52+AG52+AJ52+AM52,"") -> 3015000 | AQ52: =IFERROR(G52+J52+M52+P52+S52+V52+Y52+AB52+AE52+AH52+AK52+AN52,"") -> 1486139 | AR52: =IFERROR(AQ52/AP52,"") -> 0.49291509
B53: =B18 -> 12 | C53: =IF(C18=0,"",C18) -> DSL-DHK | D53: =IF(D18=0,"",D18) -> Md. Rakibul Islam | E53: =IF(E18=0,"",E18) -> 5690 | F53: =IFERROR(VLOOKUP(D53,'ASE Target (Spares), FY 21-22'!$C$40:$H$69,6,0),"") -> 270000 | G53: 542743 | H53: =IFERROR(G53/F53,"") -> 2.0101593 | I53: =IFERROR(VLOOKUP(D53,'ASE Target (Spares), FY 21-22'!$C$40:$I$69,7,0),"") -> 270000 | K53: =IFERROR(J53/I53,"") -> 0 | L53: =IFERROR(VLOOKUP(D53,'ASE Target (Spares), FY 21-22'!$C$40:$J$69,8,0),"") -> 0 | N53: =IFERROR(M53/L53,"") | O53: =IFERROR(VLOOKUP(D53,'ASE Target (Spares), FY 21-22'!$C$40:$K$69,9,0),"") -> 0 | Q53: =IFERROR(P53/O53,"") | R53: =IFERROR(VLOOKUP(D53,'ASE Target (Spares), FY 21-22'!$C$40:$L$69,10,0),"") -> 0 | T53: =IFERROR(S53/R53,"") | U53: =IFERROR(VLOOKUP(D53,'ASE Target (Spares), FY 21-22'!$C$40:$M$69,11,0),"") -> 0 | W53: =IFERROR(V53/U53,"") | X53: =IFERROR(VLOOKUP(D53,'ASE Target (Spares), FY 21-22'!$C$40:$N$69,12,0),"") -> 0 | Z53: =IFERROR(Y53/X53,"") | AA53: =IFERROR(VLOOKUP(D53,'ASE Target (Spares), FY 21-22'!$C$40:$O$69,13,0),"") -> 270000 | AC53: =IFERROR(AB53/AA53,"") -> 0 | AD53: =IFERROR(VLOOKUP(D53,'ASE Target (Spares), FY 21-22'!$C$40:$P$69,14,0),"") -> 540000 | AF53: =IFERROR(AE53/AD53,"") -> 0 | AG53: =IFERROR(VLOOKUP(D53,'ASE Target (Spares), FY 21-22'!$C$40:$Q$69,15,0),"") -> 540000 | AI53: =IFERROR(AH53/AG53,"") -> 0 | AJ53: =IFERROR(VLOOKUP(D53,'ASE Target (Spares), FY 21-22'!$C$40:$R$69,16,0),"") -> 540000 | AL53: =IFERROR(AK53/AJ53,"") -> 0 | AM53: =IFERROR(VLOOKUP(D53,'ASE Target (Spares), FY 21-22'!$C$40:$S$69,17,0),"") -> 540000 | AN53: 886998 | AO53: =IFERROR(AN53/AM53,"") -> 1.6425889 | AP53: =IFERROR(F53+I53+L53+O53+R53+U53+X53+AA53+AD53+AG53+AJ53+AM53,"") -> 2970000 | AQ53: =IFERROR(G53+J53+M53+P53+S53+V53+Y53+AB53+AE53+AH53+AK53+AN53,"") -> 1429741 | AR53: =IFERROR(AQ53/AP53,"") -> 0.48139428
B54: =B19 -> 13 | C54: =IF(C19=0,"",C19) -> DSL-DHK | D54: =IF(D19=0,"",D19) -> Ohid Hasan Saikat | E54: =IF(E19=0,"",E19) -> 5691 | F54: =IFERROR(VLOOKUP(D54,'ASE Target (Spares), FY 21-22'!$C$40:$H$69,6,0),"") -> 135000 | H54: =IFERROR(G54/F54,"") -> 0 | I54: =IFERROR(VLOOKUP(D54,'ASE Target (Spares), FY 21-22'!$C$40:$I$69,7,0),"") -> 135000 | K54: =IFERROR(J54/I54,"") -> 0 | L54: =IFERROR(VLOOKUP(D54,'ASE Target (Spares), FY 21-22'!$C$40:$J$69,8,0),"") -> 0 | N54: =IFERROR(M54/L54,"") | O54: =IFERROR(VLOOKUP(D54,'ASE Target (Spares), FY 21-22'!$C$40:$K$69,9,0),"") -> 0 | Q54: =IFERROR(P54/O54,"") | R54: =IFERROR(VLOOKUP(D54,'ASE Target (Spares), FY 21-22'!$C$40:$L$69,10,0),"") -> 0 | T54: =IFERROR(S54/R54,"") | U54: =IFERROR(VLOOKUP(D54,'ASE Target (Spares), FY 21-22'!$C$40:$M$69,11,0),"") -> 0 | W54: =IFERROR(V54/U54,"") | X54: =IFERROR(VLOOKUP(D54,'ASE Target (Spares), FY 21-22'!$C$40:$N$69,12,0),"") -> 0 | Z54: =IFERROR(Y54/X54,"") | AA54: =IFERROR(VLOOKUP(D54,'ASE Target (Spares), FY 21-22'!$C$40:$O$69,13,0),"") -> 135000 | AC54: =IFERROR(AB54/AA54,"") -> 0 | AD54: =IFERROR(VLOOKUP(D54,'ASE Target (Spares), FY 21-22'!$C$40:$P$69,14,0),"") -> 315000 | AF54: =IFERROR(AE54/AD54,"") -> 0 | AG54: =IFERROR(VLOOKUP(D54,'ASE Target (Spares), FY 21-22'!$C$40:$Q$69,15,0),"") -> 315000 | AI54: =IFERROR(AH54/AG54,"") -> 0 | AJ54: =IFERROR(VLOOKUP(D54,'ASE Target (Spares), FY 21-22'!$C$40:$R$69,16,0),"") -> 270000 | AL54: =IFERROR(AK54/AJ54,"") -> 0 | AM54: =IFERROR(VLOOKUP(D54,'ASE Target (Spares), FY 21-22'!$C$40:$S$69,17,0),"") -> 270000 | AN54: 177651 | AO54: =IFERROR(AN54/AM54,"") -> 0.65796667 | AP54: =IFERROR(F54+I54+L54+O54+R54+U54+X54+AA54+AD54+AG54+AJ54+AM54,"") -> 1575000 | AQ54: =IFERROR(G54+J54+M54+P54+S54+V54+Y54+AB54+AE54+AH54+AK54+AN54,"") -> 177651 | AR54: =IFERROR(AQ54/AP54,"") -> 0.11279429
B55: =B20 -> 14 | C55: =IF(C20=0,"",C20) -> DSL-DHK | D55: =IF(D20=0,"",D20) -> Abdullah Al Mahmud | E55: =IF(E20=0,"",E20) -> 5692 | F55: =IFERROR(VLOOKUP(D55,'ASE Target (Spares), FY 21-22'!$C$40:$H$69,6,0),"") -> 180000 | H55: =IFERROR(G55/F55,"") -> 0 | I55: =IFERROR(VLOOKUP(D55,'ASE Target (Spares), FY 21-22'!$C$40:$I$69,7,0),"") -> 180000 | K55: =IFERROR(J55/I55,"") -> 0 | L55: =IFERROR(VLOOKUP(D55,'ASE Target (Spares), FY 21-22'!$C$40:$J$69,8,0),"") -> 0 | N55: =IFERROR(M55/L55,"") | O55: =IFERROR(VLOOKUP(D55,'ASE Target (Spares), FY 21-22'!$C$40:$K$69,9,0),"") -> 0 | Q55: =IFERROR(P55/O55,"") | R55: =IFERROR(VLOOKUP(D55,'ASE Target (Spares), FY 21-22'!$C$40:$L$69,10,0),"") -> 0 | T55: =IFERROR(S55/R55,"") | U55: =IFERROR(VLOOKUP(D55,'ASE Target (Spares), FY 21-22'!$C$40:$M$69,11,0),"") -> 0 | W55: =IFERROR(V55/U55,"") | X55: =IFERROR(VLOOKUP(D55,'ASE Target (Spares), FY 21-22'!$C$40:$N$69,12,0),"") -> 0 | Z55: =IFERROR(Y55/X55,"") | AA55: =IFERROR(VLOOKUP(D55,'ASE Target (Spares), FY 21-22'!$C$40:$O$69,13,0),"") -> 315000 | AC55: =IFERROR(AB55/AA55,"") -> 0 | AD55: =IFERROR(VLOOKUP(D55,'ASE Target (Spares), FY 21-22'!$C$40:$P$69,14,0),"") -> 495000 | AF55: =IFERROR(AE55/AD55,"") -> 0 | AG55: =IFERROR(VLOOKUP(D55,'ASE Target (Spares), FY 21-22'!$C$40:$Q$69,15,0),"") -> 360000 | AI55: =IFERROR(AH55/AG55,"") -> 0 | AJ55: =IFERROR(VLOOKUP(D55,'ASE Target (Spares), FY 21-22'!$C$40:$R$69,16,0),"") -> 360000 | AL55: =IFERROR(AK55/AJ55,"") -> 0 | AM55: =IFERROR(VLOOKUP(D55,'ASE Target (Spares), FY 21-22'!$C$40:$S$69,17,0),"") -> 360000 | AN55: 213650 | AO55: =IFERROR(AN55/AM55,"") -> 0.59347222 | AP55: =IFERROR(F55+I55+L55+O55+R55+U55+X55+AA55+AD55+AG55+AJ55+AM55,"") -> 2250000 | AQ55: =IFERROR(G55+J55+M55+P55+S55+V55+Y55+AB55+AE55+AH55+AK55+AN55,"") -> 213650 | AR55: =IFERROR(AQ55/AP55,"") -> 0.094955556
B56: =B21 -> 15 | C56: =IF(C21=0,"",C21) -> DSL-DHK | D56: =IF(D21=0,"",D21) -> Apurba Kumar Gain | E56: =IF(E21=0,"",E21) -> 5927 | F56: =IFERROR(VLOOKUP(D56,'ASE Target (Spares), FY 21-22'!$C$40:$H$69,6,0),"") -> 103500 | G56: 75251 | H56: =IFERROR(G56/F56,"") -> 0.7270628 | I56: =IFERROR(VLOOKUP(D56,'ASE Target (Spares), FY 21-22'!$C$40:$I$69,7,0),"") -> 103500 | K56: =IFERROR(J56/I56,"") -> 0 | L56: =IFERROR(VLOOKUP(D56,'ASE Target (Spares), FY 21-22'!$C$40:$J$69,8,0),"") -> 0 | N56: =IFERROR(M56/L56,"") | O56: =IFERROR(VLOOKUP(D56,'ASE Target (Spares), FY 21-22'!$C$40:$K$69,9,0),"") -> 0 | Q56: =IFERROR(P56/O56,"") | R56: =IFERROR(VLOOKUP(D56,'ASE Target (Spares), FY 21-22'!$C$40:$L$69,10,0),"") -> 0 | T56: =IFERROR(S56/R56,"") | U56: =IFERROR(VLOOKUP(D56,'ASE Target (Spares), FY 21-22'!$C$40:$M$69,11,0),"") -> 0 | W56: =IFERROR(V56/U56,"") | X56: =IFERROR(VLOOKUP(D56,'ASE Target (Spares), FY 21-22'!$C$40:$N$69,12,0),"") -> 0 | Z56: =IFERROR(Y56/X56,"") | AA56: =IFERROR(VLOOKUP(D56,'ASE Target (Spares), FY 21-22'!$C$40:$O$69,13,0),"") -> 0 | AC56: =IFERROR(AB56/AA56,"") | AD56: =IFERROR(VLOOKUP(D56,'ASE Target (Spares), FY 21-22'!$C$40:$P$69,14,0),"") -> 103500 | AF56: =IFERROR(AE56/AD56,"") -> 0 | AG56: =IFERROR(VLOOKUP(D56,'ASE Target (Spares), FY 21-22'!$C$40:$Q$69,15,0),"") -> 207000 | AI56: =IFERROR(AH56/AG56,"") -> 0 | AJ56: =IFERROR(VLOOKUP(D56,'ASE Target (Spares), FY 21-22'!$C$40:$R$69,16,0),"") -> 207000 | AL56: =IFERROR(AK56/AJ56,"") -> 0 | AM56: =IFERROR(VLOOKUP(D56,'ASE Target (Spares), FY 21-22'!$C$40:$S$69,17,0),"") -> 207000 | AN56: 119715 | AO56: =IFERROR(AN56/AM56,"") -> 0.57833333 | AP56: =IFERROR(F56+I56+L56+O56+R56+U56+X56+AA56+AD56+AG56+AJ56+AM56,"") -> 931500 | AQ56: =IFERROR(G56+J56+M56+P56+S56+V56+Y56+AB56+AE56+AH56+AK56+AN56,"") -> 194966 | AR56: =IFERROR(AQ56/AP56,"") -> 0.20930327
B57: =B22 -> 16 | C57: =IF(C22=0,"",C22) -> DSL-DHK | D57: =IF(D22=0,"",D22) -> Amirul Islam | E57: =IF(E22=0,"",E22) -> 5928 | F57: =IFERROR(VLOOKUP(D57,'ASE Target (Spares), FY 21-22'!$C$40:$H$69,6,0),"") -> 112500 | H57: =IFERROR(G57/F57,"") -> 0 | I57: =IFERROR(VLOOKUP(D57,'ASE Target (Spares), FY 21-22'!$C$40:$I$69,7,0),"") -> 112500 | K57: =IFERROR(J57/I57,"") -> 0 | L57: =IFERROR(VLOOKUP(D57,'ASE Target (Spares), FY 21-22'!$C$40:$J$69,8,0),"") -> 0 | N57: =IFERROR(M57/L57,"") | O57: =IFERROR(VLOOKUP(D57,'ASE Target (Spares), FY 21-22'!$C$40:$K$69,9,0),"") -> 0 | Q57: =IFERROR(P57/O57,"") | R57: =IFERROR(VLOOKUP(D57,'ASE Target (Spares), FY 21-22'!$C$40:$L$69,10,0),"") -> 0 | T57: =IFERROR(S57/R57,"") | U57: =IFERROR(VLOOKUP(D57,'ASE Target (Spares), FY 21-22'!$C$40:$M$69,11,0),"") -> 0 | W57: =IFERROR(V57/U57,"") | X57: =IFERROR(VLOOKUP(D57,'ASE Target (Spares), FY 21-22'!$C$40:$N$69,12,0),"") -> 0 | Z57: =IFERROR(Y57/X57,"") | AA57: =IFERROR(VLOOKUP(D57,'ASE Target (Spares), FY 21-22'!$C$40:$O$69,13,0),"") -> 0 | AC57: =IFERROR(AB57/AA57,"") | AD57: =IFERROR(VLOOKUP(D57,'ASE Target (Spares), FY 21-22'!$C$40:$P$69,14,0),"") -> 112500 | AF57: =IFERROR(AE57/AD57,"") -> 0 | AG57: =IFERROR(VLOOKUP(D57,'ASE Target (Spares), FY 21-22'!$C$40:$Q$69,15,0),"") -> 225000 | AI57: =IFERROR(AH57/AG57,"") -> 0 | AJ57: =IFERROR(VLOOKUP(D57,'ASE Target (Spares), FY 21-22'!$C$40:$R$69,16,0),"") -> 225000 | AL57: =IFERROR(AK57/AJ57,"") -> 0 | AM57: =IFERROR(VLOOKUP(D57,'ASE Target (Spares), FY 21-22'!$C$40:$S$69,17,0),"") -> 225000 | AN57: 137220 | AO57: =IFERROR(AN57/AM57,"") -> 0.60986667 | AP57: =IFERROR(F57+I57+L57+O57+R57+U57+X57+AA57+AD57+AG57+AJ57+AM57,"") -> 1012500 | AQ57: =IFERROR(G57+J57+M57+P57+S57+V57+Y57+AB57+AE57+AH57+AK57+AN57,"") -> 137220 | AR57: =IFERROR(AQ57/AP57,"") -> 0.13552593
B58: =B23 -> 17 | C58: =IF(C23=0,"",C23) -> DSL-DHK | D58: =IF(D23=0,"",D23) -> Md. Jafor Ikbal | E58: =IF(E23=0,"",E23) -> 5929 | F58: =IFERROR(VLOOKUP(D58,'ASE Target (Spares), FY 21-22'!$C$40:$H$69,6,0),"") -> 0 | H58: =IFERROR(G58/F58,"") | I58: =IFERROR(VLOOKUP(D58,'ASE Target (Spares), FY 21-22'!$C$40:$I$69,7,0),"") -> 0 | K58: =IFERROR(J58/I58,"") | L58: =IFERROR(VLOOKUP(D58,'ASE Target (Spares), FY 21-22'!$C$40:$J$69,8,0),"") -> 0 | N58: =IFERROR(M58/L58,"") | O58: =IFERROR(VLOOKUP(D58,'ASE Target (Spares), FY 21-22'!$C$40:$K$69,9,0),"") -> 0 | Q58: =IFERROR(P58/O58,"") | R58: =IFERROR(VLOOKUP(D58,'ASE Target (Spares), FY 21-22'!$C$40:$L$69,10,0),"") -> 0 | T58: =IFERROR(S58/R58,"") | U58: =IFERROR(VLOOKUP(D58,'ASE Target (Spares), FY 21-22'!$C$40:$M$69,11,0),"") -> 0 | W58: =IFERROR(V58/U58,"") | X58: =IFERROR(VLOOKUP(D58,'ASE Target (Spares), FY 21-22'!$C$40:$N$69,12,0),"") -> 0 | Z58: =IFERROR(Y58/X58,"") | AA58: =IFERROR(VLOOKUP(D58,'ASE Target (Spares), FY 21-22'!$C$40:$O$69,13,0),"") -> 0 | AC58: =IFERROR(AB58/AA58,"") | AD58: =IFERROR(VLOOKUP(D58,'ASE Target (Spares), FY 21-22'!$C$40:$P$69,14,0),"") -> 0 | AF58: =IFERROR(AE58/AD58,"") | AG58: =IFERROR(VLOOKUP(D58,'ASE Target (Spares), FY 21-22'!$C$40:$Q$69,15,0),"") -> 0 | AI58: =IFERROR(AH58/AG58,"") | AJ58: =IFERROR(VLOOKUP(D58,'ASE Target (Spares), FY 21-22'!$C$40:$R$69,16,0),"") -> 0 | AL58: =IFERROR(AK58/AJ58,"") | AM58: =IFERROR(VLOOKUP(D58,'ASE Target (Spares), FY 21-22'!$C$40:$S$69,17,0),"") -> 0 | AO58: =IFERROR(AN58/AM58,"") | AP58: =IFERROR(F58+I58+L58+O58+R58+U58+X58+AA58+AD58+AG58+AJ58+AM58,"") -> 0 | AQ58: =IFERROR(G58+J58+M58+P58+S58+V58+Y58+AB58+AE58+AH58+AK58+AN58,"") -> 0 | AR58: =IFERROR(AQ58/AP58,"")
B59: =B24 -> 18 | C59: =IF(C24=0,"",C24) -> DSL-DHK | D59: =IF(D24=0,"",D24) -> Md. Habibur Rahman | E59: =IF(E24=0,"",E24) -> 6079 | F59: =IFERROR(VLOOKUP(D59,'ASE Target (Spares), FY 21-22'!$C$40:$H$69,6,0),"") -> 112500 | G59: 263694 | H59: =IFERROR(G59/F59,"") -> 2.3439467 | I59: =IFERROR(VLOOKUP(D59,'ASE Target (Spares), FY 21-22'!$C$40:$I$69,7,0),"") -> 112500 | K59: =IFERROR(J59/I59,"") -> 0 | L59: =IFERROR(VLOOKUP(D59,'ASE Target (Spares), FY 21-22'!$C$40:$J$69,8,0),"") -> 0 | N59: =IFERROR(M59/L59,"") | O59: =IFERROR(VLOOKUP(D59,'ASE Target (Spares), FY 21-22'!$C$40:$K$69,9,0),"") -> 0 | Q59: =IFERROR(P59/O59,"") | R59: =IFERROR(VLOOKUP(D59,'ASE Target (Spares), FY 21-22'!$C$40:$L$69,10,0),"") -> 0 | T59: =IFERROR(S59/R59,"") | U59: =IFERROR(VLOOKUP(D59,'ASE Target (Spares), FY 21-22'!$C$40:$M$69,11,0),"") -> 0 | W59: =IFERROR(V59/U59,"") | X59: =IFERROR(VLOOKUP(D59,'ASE Target (Spares), FY 21-22'!$C$40:$N$69,12,0),"") -> 0 | Z59: =IFERROR(Y59/X59,"") | AA59: =IFERROR(VLOOKUP(D59,'ASE Target (Spares), FY 21-22'!$C$40:$O$69,13,0),"") -> 0 | AC59: =IFERROR(AB59/AA59,"") | AD59: =IFERROR(VLOOKUP(D59,'ASE Target (Spares), FY 21-22'!$C$40:$P$69,14,0),"") -> 0 | AF59: =IFERROR(AE59/AD59,"") | AG59: =IFERROR(VLOOKUP(D59,'ASE Target (Spares), FY 21-22'!$C$40:$Q$69,15,0),"") -> 0 | AI59: =IFERROR(AH59/AG59,"") | AJ59: =IFERROR(VLOOKUP(D59,'ASE Target (Spares), FY 21-22'!$C$40:$R$69,16,0),"") -> 0 | AL59: =IFERROR(AK59/AJ59,"") | AM59: =IFERROR(VLOOKUP(D59,'ASE Target (Spares), FY 21-22'!$C$40:$S$69,17,0),"") -> 112500 | AN59: 272707 | AO59: =IFERROR(AN59/AM59,"") -> 2.4240622 | AP59: =IFERROR(F59+I59+L59+O59+R59+U59+X59+AA59+AD59+AG59+AJ59+AM59,"") -> 337500 | AQ59: =IFERROR(G59+J59+M59+P59+S59+V59+Y59+AB59+AE59+AH59+AK59+AN59,"") -> 536401 | AR59: =IFERROR(AQ59/AP59,"") -> 1.5893363
B60: =B25 -> 19 | C60: =IF(C25=0,"",C25) -> DSL-DHK | D60: =IF(D25=0,"",D25) -> Ashikur Rahman | E60: =IF(E25=0,"",E25) -> 6080 | F60: =IFERROR(VLOOKUP(D60,'ASE Target (Spares), FY 21-22'!$C$40:$H$69,6,0),"") -> 225000 | G60: 296744 | H60: =IFERROR(G60/F60,"") -> 1.3188622 | I60: =IFERROR(VLOOKUP(D60,'ASE Target (Spares), FY 21-22'!$C$40:$I$69,7,0),"") -> 225000 | K60: =IFERROR(J60/I60,"") -> 0 | L60: =IFERROR(VLOOKUP(D60,'ASE Target (Spares), FY 21-22'!$C$40:$J$69,8,0),"") -> 0 | N60: =IFERROR(M60/L60,"") | O60: =IFERROR(VLOOKUP(D60,'ASE Target (Spares), FY 21-22'!$C$40:$K$69,9,0),"") -> 0 | Q60: =IFERROR(P60/O60,"") | R60: =IFERROR(VLOOKUP(D60,'ASE Target (Spares), FY 21-22'!$C$40:$L$69,10,0),"") -> 0 | T60: =IFERROR(S60/R60,"") | U60: =IFERROR(VLOOKUP(D60,'ASE Target (Spares), FY 21-22'!$C$40:$M$69,11,0),"") -> 0 | W60: =IFERROR(V60/U60,"") | X60: =IFERROR(VLOOKUP(D60,'ASE Target (Spares), FY 21-22'!$C$40:$N$69,12,0),"") -> 0 | Z60: =IFERROR(Y60/X60,"") | AA60: =IFERROR(VLOOKUP(D60,'ASE Target (Spares), FY 21-22'!$C$40:$O$69,13,0),"") -> 0 | AC60: =IFERROR(AB60/AA60,"") | AD60: =IFERROR(VLOOKUP(D60,'ASE Target (Spares), FY 21-22'!$C$40:$P$69,14,0),"") -> 0 | AF60: =IFERROR(AE60/AD60,"") | AG60: =IFERROR(VLOOKUP(D60,'ASE Target (Spares), FY 21-22'!$C$40:$Q$69,15,0),"") -> 0 | AI60: =IFERROR(AH60/AG60,"") | AJ60: =IFERROR(VLOOKUP(D60,'ASE Target (Spares), FY 21-22'!$C$40:$R$69,16,0),"") -> 0 | AL60: =IFERROR(AK60/AJ60,"") | AM60: =IFERROR(VLOOKUP(D60,'ASE Target (Spares), FY 21-22'!$C$40:$S$69,17,0),"") -> 225000 | AN60: 342712 | AO60: =IFERROR(AN60/AM60,"") -> 1.5231644 | AP60: =IFERROR(F60+I60+L60+O60+R60+U60+X60+AA60+AD60+AG60+AJ60+AM60,"") -> 675000 | AQ60: =IFERROR(G60+J60+M60+P60+S60+V60+Y60+AB60+AE60+AH60+AK60+AN60,"") -> 639456 | AR60: =IFERROR(AQ60/AP60,"") -> 0.94734222
B61: =B26 -> 20 | C61: =IF(C26=0,"",C26) -> DSL-DHK | D61: =IF(D26=0,"",D26) -> Md. Sujon Hossain | E61: =IF(E26=0,"",E26) -> 6078 | F61: =IFERROR(VLOOKUP(D61,'ASE Target (Spares), FY 21-22'!$C$40:$H$69,6,0),"") -> 270000 | G61: 290128 | H61: =IFERROR(G61/F61,"") -> 1.0745481 | I61: =IFERROR(VLOOKUP(D61,'ASE Target (Spares), FY 21-22'!$C$40:$I$69,7,0),"") -> 270000 | K61: =IFERROR(J61/I61,"") -> 0 | L61: =IFERROR(VLOOKUP(D61,'ASE Target (Spares), FY 21-22'!$C$40:$J$69,8,0),"") -> 0 | N61: =IFERROR(M61/L61,"") | O61: =IFERROR(VLOOKUP(D61,'ASE Target (Spares), FY 21-22'!$C$40:$K$69,9,0),"") -> 0 | Q61: =IFERROR(P61/O61,"") | R61: =IFERROR(VLOOKUP(D61,'ASE Target (Spares), FY 21-22'!$C$40:$L$69,10,0),"") -> 0 | T61: =IFERROR(S61/R61,"") | U61: =IFERROR(VLOOKUP(D61,'ASE Target (Spares), FY 21-22'!$C$40:$M$69,11,0),"") -> 0 | W61: =IFERROR(V61/U61,"") | X61: =IFERROR(VLOOKUP(D61,'ASE Target (Spares), FY 21-22'!$C$40:$N$69,12,0),"") -> 0 | Z61: =IFERROR(Y61/X61,"") | AA61: =IFERROR(VLOOKUP(D61,'ASE Target (Spares), FY 21-22'!$C$40:$O$69,13,0),"") -> 0 | AC61: =IFERROR(AB61/AA61,"") | AD61: =IFERROR(VLOOKUP(D61,'ASE Target (Spares), FY 21-22'!$C$40:$P$69,14,0),"") -> 0 | AF61: =IFERROR(AE61/AD61,"") | AG61: =IFERROR(VLOOKUP(D61,'ASE Target (Spares), FY 21-22'!$C$40:$Q$69,15,0),"") -> 0 | AI61: =IFERROR(AH61/AG61,"") | AJ61: =IFERROR(VLOOKUP(D61,'ASE Target (Spares), FY 21-22'!$C$40:$R$69,16,0),"") -> 0 | AL61: =IFERROR(AK61/AJ61,"") | AM61: =IFERROR(VLOOKUP(D61,'ASE Target (Spares), FY 21-22'!$C$40:$S$69,17,0),"") -> 270000 | AN61: 413829 | AO61: =IFERROR(AN61/AM61,"") -> 1.5327 | AP61: =IFERROR(F61+I61+L61+O61+R61+U61+X61+AA61+AD61+AG61+AJ61+AM61,"") -> 810000 | AQ61: =IFERROR(G61+J61+M61+P61+S61+V61+Y61+AB61+AE61+AH61+AK61+AN61,"") -> 703957 | AR61: =IFERROR(AQ61/AP61,"") -> 0.86908272
B62: =B27 -> 21 | C62: =IF(C27=0,"",C27) -> DSL-DHK | D62: =IF(D27=0,"",D27) -> Md Jiaur Rahman | E62: =IF(E27=0,"",E27) -> 0522 | F62: =IFERROR(VLOOKUP(D62,'ASE Target (Spares), FY 21-22'!$C$40:$H$69,6,0),"") -> 405000 | H62: =IFERROR(G62/F62,"") -> 0 | I62: =IFERROR(VLOOKUP(D62,'ASE Target (Spares), FY 21-22'!$C$40:$I$69,7,0),"") -> 405000 | K62: =IFERROR(J62/I62,"") -> 0 | L62: =IFERROR(VLOOKUP(D62,'ASE Target (Spares), FY 21-22'!$C$40:$J$69,8,0),"") -> 0 | N62: =IFERROR(M62/L62,"") | O62: =IFERROR(VLOOKUP(D62,'ASE Target (Spares), FY 21-22'!$C$40:$K$69,9,0),"") -> 0 | Q62: =IFERROR(P62/O62,"") | R62: =IFERROR(VLOOKUP(D62,'ASE Target (Spares), FY 21-22'!$C$40:$L$69,10,0),"") -> 0 | T62: =IFERROR(S62/R62,"") | U62: =IFERROR(VLOOKUP(D62,'ASE Target (Spares), FY 21-22'!$C$40:$M$69,11,0),"") -> 0 | W62: =IFERROR(V62/U62,"") | X62: =IFERROR(VLOOKUP(D62,'ASE Target (Spares), FY 21-22'!$C$40:$N$69,12,0),"") -> 0 | Z62: =IFERROR(Y62/X62,"") | AA62: =IFERROR(VLOOKUP(D62,'ASE Target (Spares), FY 21-22'!$C$40:$O$69,13,0),"") -> 0 | AC62: =IFERROR(AB62/AA62,"") | AD62: =IFERROR(VLOOKUP(D62,'ASE Target (Spares), FY 21-22'!$C$40:$P$69,14,0),"") -> 382500 | AF62: =IFERROR(AE62/AD62,"") -> 0 | AG62: 255000 | AI62: =IFERROR(AH62/AG62,"") -> 0 | AJ62: =IFERROR(VLOOKUP(D62,'ASE Target (Spares), FY 21-22'!$C$40:$R$69,16,0),"") -> 765000 | AL62: =IFERROR(AK62/AJ62,"") -> 0 | AM62: =IFERROR(VLOOKUP(D62,'ASE Target (Spares), FY 21-22'!$C$40:$S$69,17,0),"") -> 787500 | AO62: =IFERROR(AN62/AM62,"") -> 0 | AP62: =IFERROR(F62+I62+L62+O62+R62+U62+X62+AA62+AD62+AG62+AJ62+AM62,"") -> 3000000 | AQ62: =IFERROR(G62+J62+M62+P62+S62+V62+Y62+AB62+AE62+AH62+AK62+AN62,"") -> 0 | AR62: =IFERROR(AQ62/AP62,"") -> 0
B63: =B28 -> 0 | C63: =IF(C28=0,"",C28) | D63: =IF(D28=0,"",D28) -> New-2 | E63: =IF(E28=0,"",E28) | F63: =IFERROR(VLOOKUP(D63,'ASE Target (Spares), FY 21-22'!$C$40:$H$69,6,0),"") -> 0 | H63: =IFERROR(G63/F63,"") | I63: =IFERROR(VLOOKUP(D63,'ASE Target (Spares), FY 21-22'!$C$40:$I$69,7,0),"") -> 0 | K63: =IFERROR(J63/I63,"") | L63: =IFERROR(VLOOKUP(D63,'ASE Target (Spares), FY 21-22'!$C$40:$J$69,8,0),"") -> 0 | N63: =IFERROR(M63/L63,"") | O63: =IFERROR(VLOOKUP(D63,'ASE Target (Spares), FY 21-22'!$C$40:$K$69,9,0),"") -> 0 | Q63: =IFERROR(P63/O63,"") | R63: =IFERROR(VLOOKUP(D63,'ASE Target (Spares), FY 21-22'!$C$40:$L$69,10,0),"") -> 0 | T63: =IFERROR(S63/R63,"") | U63: =IFERROR(VLOOKUP(D63,'ASE Target (Spares), FY 21-22'!$C$40:$M$69,11,0),"") -> 0 | W63: =IFERROR(V63/U63,"") | X63: =IFERROR(VLOOKUP(D63,'ASE Target (Spares), FY 21-22'!$C$40:$N$69,12,0),"") -> 0 | Z63: =IFERROR(Y63/X63,"") | AA63: =IFERROR(VLOOKUP(D63,'ASE Target (Spares), FY 21-22'!$C$40:$O$69,13,0),"") -> 0 | AC63: =IFERROR(AB63/AA63,"") | AD63: =IFERROR(VLOOKUP(D63,'ASE Target (Spares), FY 21-22'!$C$40:$P$69,14,0),"") -> 0 | AF63: =IFERROR(AE63/AD63,"") | AG63: =IFERROR(VLOOKUP(D63,'ASE Target (Spares), FY 21-22'!$C$40:$Q$69,15,0),"") -> 0 | AI63: =IFERROR(AH63/AG63,"") | AJ63: =IFERROR(VLOOKUP(D63,'ASE Target (Spares), FY 21-22'!$C$40:$R$69,16,0),"") -> 0 | AL63: =IFERROR(AK63/AJ63,"") | AM63: =IFERROR(VLOOKUP(D63,'ASE Target (Spares), FY 21-22'!$C$40:$S$69,17,0),"") -> 0 | AO63: =IFERROR(AN63/AM63,"") | AP63: =IFERROR(F63+I63+L63+O63+R63+U63+X63+AA63+AD63+AG63+AJ63+AM63,"") -> 0 | AQ63: =IFERROR(G63+J63+M63+P63+S63+V63+Y63+AB63+AE63+AH63+AK63+AN63,"") -> 0 | AR63: =IFERROR(AQ63/AP63,"")
C64: =IF(C29=0,"",C29) | D64: =IF(D29=0,"",D29) -> New-3 | E64: =IF(E29=0,"",E29) | F64: =IFERROR(VLOOKUP(D64,'ASE Target (Spares), FY 21-22'!$C$40:$H$69,6,0),"") -> 0 | H64: =IFERROR(G64/F64,"") | I64: =IFERROR(VLOOKUP(D64,'ASE Target (Spares), FY 21-22'!$C$40:$I$69,7,0),"") -> 0 | K64: =IFERROR(J64/I64,"") | L64: =IFERROR(VLOOKUP(D64,'ASE Target (Spares), FY 21-22'!$C$40:$J$69,8,0),"") -> 0 | N64: =IFERROR(M64/L64,"") | O64: =IFERROR(VLOOKUP(D64,'ASE Target (Spares), FY 21-22'!$C$40:$K$69,9,0),"") -> 0 | Q64: =IFERROR(P64/O64,"") | R64: =IFERROR(VLOOKUP(D64,'ASE Target (Spares), FY 21-22'!$C$40:$L$69,10,0),"") -> 0 | T64: =IFERROR(S64/R64,"") | U64: =IFERROR(VLOOKUP(D64,'ASE Target (Spares), FY 21-22'!$C$40:$M$69,11,0),"") -> 0 | W64: =IFERROR(V64/U64,"") | X64: =IFERROR(VLOOKUP(D64,'ASE Target (Spares), FY 21-22'!$C$40:$N$69,12,0),"") -> 0 | Z64: =IFERROR(Y64/X64,"") | AA64: =IFERROR(VLOOKUP(D64,'ASE Target (Spares), FY 21-22'!$C$40:$O$69,13,0),"") -> 0 | AC64: =IFERROR(AB64/AA64,"") | AD64: =IFERROR(VLOOKUP(D64,'ASE Target (Spares), FY 21-22'!$C$40:$P$69,14,0),"") -> 0 | AF64: =IFERROR(AE64/AD64,"") | AG64: =IFERROR(VLOOKUP(D64,'ASE Target (Spares), FY 21-22'!$C$40:$Q$69,15,0),"") -> 0 | AI64: =IFERROR(AH64/AG64,"") | AJ64: =IFERROR(VLOOKUP(D64,'ASE Target (Spares), FY 21-22'!$C$40:$R$69,16,0),"") -> 0 | AL64: =IFERROR(AK64/AJ64,"") | AM64: =IFERROR(VLOOKUP(D64,'ASE Target (Spares), FY 21-22'!$C$40:$S$69,17,0),"") -> 0 | AO64: =IFERROR(AN64/AM64,"") | AP64: =IFERROR(F64+I64+L64+O64+R64+U64+X64+AA64+AD64+AG64+AJ64+AM64,"") -> 0 | AQ64: =IFERROR(G64+J64+M64+P64+S64+V64+Y64+AB64+AE64+AH64+AK64+AN64,"") -> 0 | AR64: =IFERROR(AQ64/AP64,"")
C65: =IF(C30=0,"",C30) | D65: =IF(D30=0,"",D30) -> New-4 | E65: =IF(E30=0,"",E30) | F65: =IFERROR(VLOOKUP(D65,'ASE Target (Spares), FY 21-22'!$C$40:$H$69,6,0),"") -> 0 | H65: =IFERROR(G65/F65,"") | I65: =IFERROR(VLOOKUP(D65,'ASE Target (Spares), FY 21-22'!$C$40:$I$69,7,0),"") -> 0 | K65: =IFERROR(J65/I65,"") | L65: =IFERROR(VLOOKUP(D65,'ASE Target (Spares), FY 21-22'!$C$40:$J$69,8,0),"") -> 0 | N65: =IFERROR(M65/L65,"") | O65: =IFERROR(VLOOKUP(D65,'ASE Target (Spares), FY 21-22'!$C$40:$K$69,9,0),"") -> 0 | Q65: =IFERROR(P65/O65,"") | R65: =IFERROR(VLOOKUP(D65,'ASE Target (Spares), FY 21-22'!$C$40:$L$69,10,0),"") -> 0 | T65: =IFERROR(S65/R65,"") | U65: =IFERROR(VLOOKUP(D65,'ASE Target (Spares), FY 21-22'!$C$40:$M$69,11,0),"") -> 0 | W65: =IFERROR(V65/U65,"") | X65: =IFERROR(VLOOKUP(D65,'ASE Target (Spares), FY 21-22'!$C$40:$N$69,12,0),"") -> 0 | Z65: =IFERROR(Y65/X65,"") | AA65: =IFERROR(VLOOKUP(D65,'ASE Target (Spares), FY 21-22'!$C$40:$O$69,13,0),"") -> 0 | AC65: =IFERROR(AB65/AA65,"") | AD65: =IFERROR(VLOOKUP(D65,'ASE Target (Spares), FY 21-22'!$C$40:$P$69,14,0),"") -> 0 | AF65: =IFERROR(AE65/AD65,"") | AG65: =IFERROR(VLOOKUP(D65,'ASE Target (Spares), FY 21-22'!$C$40:$Q$69,15,0),"") -> 0 | AI65: =IFERROR(AH65/AG65,"") | AJ65: =IFERROR(VLOOKUP(D65,'ASE Target (Spares), FY 21-22'!$C$40:$R$69,16,0),"") -> 0 | AL65: =IFERROR(AK65/AJ65,"") | AM65: =IFERROR(VLOOKUP(D65,'ASE Target (Spares), FY 21-22'!$C$40:$S$69,17,0),"") -> 0 | AO65: =IFERROR(AN65/AM65,"") | AP65: =IFERROR(F65+I65+L65+O65+R65+U65+X65+AA65+AD65+AG65+AJ65+AM65,"") -> 0 | AQ65: =IFERROR(G65+J65+M65+P65+S65+V65+Y65+AB65+AE65+AH65+AK65+AN65,"") -> 0 | AR65: =IFERROR(AQ65/AP65,"")
C66: =IF(C31=0,"",C31) -> CTG | D66: =IF(D31=0,"",D31) -> Sumon Sen | E66: =IF(E31=0,"",E31) -> 8041 | F66: =IFERROR(VLOOKUP(D66,'ASE Target (Spares), FY 21-22'!$C$40:$H$69,6,0),"") -> 0 | H66: =IFERROR(G66/F66,"") | I66: =IFERROR(VLOOKUP(D66,'ASE Target (Spares), FY 21-22'!$C$40:$I$69,7,0),"") -> 0 | K66: =IFERROR(J66/I66,"") | L66: =IFERROR(VLOOKUP(D66,'ASE Target (Spares), FY 21-22'!$C$40:$J$69,8,0),"") -> 0 | N66: =IFERROR(M66/L66,"") | O66: =IFERROR(VLOOKUP(D66,'ASE Target (Spares), FY 21-22'!$C$40:$K$69,9,0),"") -> 0 | Q66: =IFERROR(P66/O66,"") | R66: =IFERROR(VLOOKUP(D66,'ASE Target (Spares), FY 21-22'!$C$40:$L$69,10,0),"") -> 0 | T66: =IFERROR(S66/R66,"") | U66: =IFERROR(VLOOKUP(D66,'ASE Target (Spares), FY 21-22'!$C$40:$M$69,11,0),"") -> 0 | W66: =IFERROR(V66/U66,"") | X66: =IFERROR(VLOOKUP(D66,'ASE Target (Spares), FY 21-22'!$C$40:$N$69,12,0),"") -> 0 | Z66: =IFERROR(Y66/X66,"") | AA66: =IFERROR(VLOOKUP(D66,'ASE Target (Spares), FY 21-22'!$C$40:$O$69,13,0),"") -> 202500 | AC66: =IFERROR(AB66/AA66,"") -> 0 | AD66: =IFERROR(VLOOKUP(D66,'ASE Target (Spares), FY 21-22'!$C$40:$P$69,14,0),"") -> 405000 | AF66: =IFERROR(AE66/AD66,"") -> 0 | AG66: =IFERROR(VLOOKUP(D66,'ASE Target (Spares), FY 21-22'!$C$40:$Q$69,15,0),"") -> 405000 | AI66: =IFERROR(AH66/AG66,"") -> 0 | AJ66: =IFERROR(VLOOKUP(D66,'ASE Target (Spares), FY 21-22'!$C$40:$R$69,16,0),"") -> 405000 | AL66: =IFERROR(AK66/AJ66,"") -> 0 | AM66: =IFERROR(VLOOKUP(D66,'ASE Target (Spares), FY 21-22'!$C$40:$S$69,17,0),"") -> 405000 | AO66: =IFERROR(AN66/AM66,"") -> 0 | AP66: =IFERROR(F66+I66+L66+O66+R66+U66+X66+AA66+AD66+AG66+AJ66+AM66,"") -> 1822500 | AQ66: =IFERROR(G66+J66+M66+P66+S66+V66+Y66+AB66+AE66+AH66+AK66+AN66,"") -> 0 | AR66: =IFERROR(AQ66/AP66,"") -> 0
C67: =IF(C32=0,"",C32) -> CTG | D67: =IF(D32=0,"",D32) -> Tapan Barua | E67: =IF(E32=0,"",E32) -> 1475 | F67: =IFERROR(VLOOKUP(D67,'ASE Target (Spares), FY 21-22'!$C$40:$H$69,6,0),"") -> 0 | H67: =IFERROR(G67/F67,"") | I67: =IFERROR(VLOOKUP(D67,'ASE Target (Spares), FY 21-22'!$C$40:$I$69,7,0),"") -> 0 | K67: =IFERROR(J67/I67,"") | L67: =IFERROR(VLOOKUP(D67,'ASE Target (Spares), FY 21-22'!$C$40:$J$69,8,0),"") -> 0 | N67: =IFERROR(M67/L67,"") | O67: =IFERROR(VLOOKUP(D67,'ASE Target (Spares), FY 21-22'!$C$40:$K$69,9,0),"") -> 0 | Q67: =IFERROR(P67/O67,"") | R67: =IFERROR(VLOOKUP(D67,'ASE Target (Spares), FY 21-22'!$C$40:$L$69,10,0),"") -> 0 | T67: =IFERROR(S67/R67,"") | U67: =IFERROR(VLOOKUP(D67,'ASE Target (Spares), FY 21-22'!$C$40:$M$69,11,0),"") -> 0 | W67: =IFERROR(V67/U67,"") | X67: =IFERROR(VLOOKUP(D67,'ASE Target (Spares), FY 21-22'!$C$40:$N$69,12,0),"") -> 0 | Z67: =IFERROR(Y67/X67,"") | AA67: =IFERROR(VLOOKUP(D67,'ASE Target (Spares), FY 21-22'!$C$40:$O$69,13,0),"") -> 202500 | AC67: =IFERROR(AB67/AA67,"") -> 0 | AD67: =IFERROR(VLOOKUP(D67,'ASE Target (Spares), FY 21-22'!$C$40:$P$69,14,0),"") -> 405000 | AF67: =IFERROR(AE67/AD67,"") -> 0 | AG67: =IFERROR(VLOOKUP(D67,'ASE Target (Spares), FY 21-22'!$C$40:$Q$69,15,0),"") -> 405000 | AI67: =IFERROR(AH67/AG67,"") -> 0 | AJ67: =IFERROR(VLOOKUP(D67,'ASE Target (Spares), FY 21-22'!$C$40:$R$69,16,0),"") -> 405000 | AL67: =IFERROR(AK67/AJ67,"") -> 0 | AM67: =IFERROR(VLOOKUP(D67,'ASE Target (Spares), FY 21-22'!$C$40:$S$69,17,0),"") -> 405000 | AO67: =IFERROR(AN67/AM67,"") -> 0 | AP67: =IFERROR(F67+I67+L67+O67+R67+U67+X67+AA67+AD67+AG67+AJ67+AM67,"") -> 1822500 | AQ67: =IFERROR(G67+J67+M67+P67+S67+V67+Y67+AB67+AE67+AH67+AK67+AN67,"") -> 0 | AR67: =IFERROR(AQ67/AP67,"") -> 0
C68: =IF(C33=0,"",C33) -> CTG | D68: =IF(D33=0,"",D33) -> Sozol prince | E68: =IF(E33=0,"",E33) -> 6076 | F68: =IFERROR(VLOOKUP(D68,'ASE Target (Spares), FY 21-22'!$C$40:$H$69,6,0),"") -> 0 | H68: =IFERROR(G68/F68,"") | I68: =IFERROR(VLOOKUP(D68,'ASE Target (Spares), FY 21-22'!$C$40:$I$69,7,0),"") -> 0 | K68: =IFERROR(J68/I68,"") | L68: =IFERROR(VLOOKUP(D68,'ASE Target (Spares), FY 21-22'!$C$40:$J$69,8,0),"") -> 0 | N68: =IFERROR(M68/L68,"") | O68: =IFERROR(VLOOKUP(D68,'ASE Target (Spares), FY 21-22'!$C$40:$K$69,9,0),"") -> 0 | Q68: =IFERROR(P68/O68,"") | R68: =IFERROR(VLOOKUP(D68,'ASE Target (Spares), FY 21-22'!$C$40:$L$69,10,0),"") -> 0 | T68: =IFERROR(S68/R68,"") | U68: =IFERROR(VLOOKUP(D68,'ASE Target (Spares), FY 21-22'!$C$40:$M$69,11,0),"") -> 0 | W68: =IFERROR(V68/U68,"") | X68: =IFERROR(VLOOKUP(D68,'ASE Target (Spares), FY 21-22'!$C$40:$N$69,12,0),"") -> 0 | Z68: =IFERROR(Y68/X68,"") | AA68: =IFERROR(VLOOKUP(D68,'ASE Target (Spares), FY 21-22'!$C$40:$O$69,13,0),"") -> 202500 | AC68: =IFERROR(AB68/AA68,"") -> 0 | AD68: =IFERROR(VLOOKUP(D68,'ASE Target (Spares), FY 21-22'!$C$40:$P$69,14,0),"") -> 405000 | AF68: =IFERROR(AE68/AD68,"") -> 0 | AG68: =IFERROR(VLOOKUP(D68,'ASE Target (Spares), FY 21-22'!$C$40:$Q$69,15,0),"") -> 405000 | AI68: =IFERROR(AH68/AG68,"") -> 0 | AJ68: =IFERROR(VLOOKUP(D68,'ASE Target (Spares), FY 21-22'!$C$40:$R$69,16,0),"") -> 405000 | AL68: =IFERROR(AK68/AJ68,"") -> 0 | AM68: =IFERROR(VLOOKUP(D68,'ASE Target (Spares), FY 21-22'!$C$40:$S$69,17,0),"") -> 405000 | AO68: =IFERROR(AN68/AM68,"") -> 0 | AP68: =IFERROR(F68+I68+L68+O68+R68+U68+X68+AA68+AD68+AG68+AJ68+AM68,"") -> 1822500 | AQ68: =IFERROR(G68+J68+M68+P68+S68+V68+Y68+AB68+AE68+AH68+AK68+AN68,"") -> 0 | AR68: =IFERROR(AQ68/AP68,"") -> 0
C69: =IF(C34=0,"",C34) | D69: =IF(D34=0,"",D34) -> New-5 | E69: =IF(E34=0,"",E34) | F69: =IFERROR(VLOOKUP(D69,'ASE Target (Spares), FY 21-22'!$C$40:$H$69,6,0),"") -> 0 | H69: =IFERROR(G69/F69,"") | I69: =IFERROR(VLOOKUP(D69,'ASE Target (Spares), FY 21-22'!$C$40:$I$69,7,0),"") -> 0 | K69: =IFERROR(J69/I69,"") | L69: =IFERROR(VLOOKUP(D69,'ASE Target (Spares), FY 21-22'!$C$40:$J$69,8,0),"") -> 0 | N69: =IFERROR(M69/L69,"") | O69: =IFERROR(VLOOKUP(D69,'ASE Target (Spares), FY 21-22'!$C$40:$K$69,9,0),"") -> 0 | Q69: =IFERROR(P69/O69,"") | R69: =IFERROR(VLOOKUP(D69,'ASE Target (Spares), FY 21-22'!$C$40:$L$69,10,0),"") -> 0 | T69: =IFERROR(S69/R69,"") | U69: =IFERROR(VLOOKUP(D69,'ASE Target (Spares), FY 21-22'!$C$40:$M$69,11,0),"") -> 0 | W69: =IFERROR(V69/U69,"") | X69: =IFERROR(VLOOKUP(D69,'ASE Target (Spares), FY 21-22'!$C$40:$N$69,12,0),"") -> 0 | Z69: =IFERROR(Y69/X69,"") | AA69: =IFERROR(VLOOKUP(D69,'ASE Target (Spares), FY 21-22'!$C$40:$O$69,13,0),"") -> 0 | AC69: =IFERROR(AB69/AA69,"") | AD69: =IFERROR(VLOOKUP(D69,'ASE Target (Spares), FY 21-22'!$C$40:$P$69,14,0),"") -> 0 | AF69: =IFERROR(AE69/AD69,"") | AG69: =IFERROR(VLOOKUP(D69,'ASE Target (Spares), FY 21-22'!$C$40:$Q$69,15,0),"") -> 0 | AI69: =IFERROR(AH69/AG69,"") | AJ69: =IFERROR(VLOOKUP(D69,'ASE Target (Spares), FY 21-22'!$C$40:$R$69,16,0),"") -> 0 | AL69: =IFERROR(AK69/AJ69,"") | AM69: =IFERROR(VLOOKUP(D69,'ASE Target (Spares), FY 21-22'!$C$40:$S$69,17,0),"") -> 0 | AO69: =IFERROR(AN69/AM69,"") | AP69: =IFERROR(F69+I69+L69+O69+R69+U69+X69+AA69+AD69+AG69+AJ69+AM69,"") -> 0 | AQ69: =IFERROR(G69+J69+M69+P69+S69+V69+Y69+AB69+AE69+AH69+AK69+AN69,"") -> 0 | AR69: =IFERROR(AQ69/AP69,"")
C70: =IF(C35=0,"",C35) | D70: =IF(D35=0,"",D35) -> New-6 | E70: =IF(E35=0,"",E35) | F70: =IFERROR(VLOOKUP(D70,'ASE Target (Spares), FY 21-22'!$C$40:$H$69,6,0),"") -> 0 | H70: =IFERROR(G70/F70,"") | I70: =IFERROR(VLOOKUP(D70,'ASE Target (Spares), FY 21-22'!$C$40:$I$69,7,0),"") -> 0 | K70: =IFERROR(J70/I70,"") | L70: =IFERROR(VLOOKUP(D70,'ASE Target (Spares), FY 21-22'!$C$40:$J$69,8,0),"") -> 0 | N70: =IFERROR(M70/L70,"") | O70: =IFERROR(VLOOKUP(D70,'ASE Target (Spares), FY 21-22'!$C$40:$K$69,9,0),"") -> 0 | Q70: =IFERROR(P70/O70,"") | R70: =IFERROR(VLOOKUP(D70,'ASE Target (Spares), FY 21-22'!$C$40:$L$69,10,0),"") -> 0 | T70: =IFERROR(S70/R70,"") | U70: =IFERROR(VLOOKUP(D70,'ASE Target (Spares), FY 21-22'!$C$40:$M$69,11,0),"") -> 0 | W70: =IFERROR(V70/U70,"") | X70: =IFERROR(VLOOKUP(D70,'ASE Target (Spares), FY 21-22'!$C$40:$N$69,12,0),"") -> 0 | Z70: =IFERROR(Y70/X70,"") | AA70: =IFERROR(VLOOKUP(D70,'ASE Target (Spares), FY 21-22'!$C$40:$O$69,13,0),"") -> 0 | AC70: =IFERROR(AB70/AA70,"") | AD70: =IFERROR(VLOOKUP(D70,'ASE Target (Spares), FY 21-22'!$C$40:$P$69,14,0),"") -> 0 | AF70: =IFERROR(AE70/AD70,"") | AG70: =IFERROR(VLOOKUP(D70,'ASE Target (Spares), FY 21-22'!$C$40:$Q$69,15,0),"") -> 0 | AI70: =IFERROR(AH70/AG70,"") | AJ70: =IFERROR(VLOOKUP(D70,'ASE Target (Spares), FY 21-22'!$C$40:$R$69,16,0),"") -> 0 | AL70: =IFERROR(AK70/AJ70,"") | AM70: =IFERROR(VLOOKUP(D70,'ASE Target (Spares), FY 21-22'!$C$40:$S$69,17,0),"") -> 0 | AO70: =IFERROR(AN70/AM70,"") | AP70: =IFERROR(F70+I70+L70+O70+R70+U70+X70+AA70+AD70+AG70+AJ70+AM70,"") -> 0 | AQ70: =IFERROR(G70+J70+M70+P70+S70+V70+Y70+AB70+AE70+AH70+AK70+AN70,"") -> 0 | AR70: =IFERROR(AQ70/AP70,"")
C71: =IF(C36=0,"",C36) | D71: =IF(D36=0,"",D36) | E71: =IF(E36=0,"",E36) | F71: =IFERROR(VLOOKUP(D71,'ASE Target (Spares), FY 21-22'!$C$40:$H$69,6,0),"") | H71: =IFERROR(G71/F71,"") | I71: =IFERROR(VLOOKUP(D71,'ASE Target (Spares), FY 21-22'!$C$40:$I$69,7,0),"") | K71: =IFERROR(J71/I71,"") | L71: =IFERROR(VLOOKUP(D71,'ASE Target (Spares), FY 21-22'!$C$40:$J$69,8,0),"") | N71: =IFERROR(M71/L71,"") | O71: =IFERROR(VLOOKUP(D71,'ASE Target (Spares), FY 21-22'!$C$40:$K$69,9,0),"") | Q71: =IFERROR(P71/O71,"") | R71: =IFERROR(VLOOKUP(D71,'ASE Target (Spares), FY 21-22'!$C$40:$L$69,10,0),"") | T71: =IFERROR(S71/R71,"") | U71: =IFERROR(VLOOKUP(D71,'ASE Target (Spares), FY 21-22'!$C$40:$M$69,11,0),"") | W71: =IFERROR(V71/U71,"") | X71: =IFERROR(VLOOKUP(D71,'ASE Target (Spares), FY 21-22'!$C$40:$N$69,12,0),"") | Z71: =IFERROR(Y71/X71,"") | AA71: =IFERROR(VLOOKUP(D71,'ASE Target (Spares), FY 21-22'!$C$40:$O$69,13,0),"") | AC71: =IFERROR(AB71/AA71,"") | AD71: =IFERROR(VLOOKUP(D71,'ASE Target (Spares), FY 21-22'!$C$40:$P$69,14,0),"") | AF71: =IFERROR(AE71/AD71,"") | AG71: =IFERROR(VLOOKUP(D71,'ASE Target (Spares), FY 21-22'!$C$40:$Q$69,15,0),"") | AI71: =IFERROR(AH71/AG71,"") | AJ71: =IFERROR(VLOOKUP(D71,'ASE Target (Spares), FY 21-22'!$C$40:$R$69,16,0),"") | AL71: =IFERROR(AK71/AJ71,"") | AM71: =IFERROR(VLOOKUP(D71,'ASE Target (Spares), FY 21-22'!$C$40:$S$69,17,0),"") | AO71: =IFERROR(AN71/AM71,"") | AP71: =IFERROR(F71+I71+L71+O71+R71+U71+X71+AA71+AD71+AG71+AJ71+AM71,"") | AQ71: =IFERROR(G71+J71+M71+P71+S71+V71+Y71+AB71+AE71+AH71+AK71+AN71,"") -> 0 | AR71: =IFERROR(AQ71/AP71,"")

Sheet ASE Ach(Lube Oil Sales)
B2: ='Monthly Summary (No Input)'!B2 -> Month | C2: ='Monthly Summary (No Input)'!C2 -> Jul | D2: <<< No input
B4: Sales (Lubeoil) | F4: Input ▼
B5: ='ASE Target (Spares), FY 21-22'!A5 -> Sl. | C5: ='ASE Target (Spares), FY 21-22'!B5 -> Wing | D5: ='ASE Target (Spares), FY 21-22'!C5 -> Name | E5: ='ASE Target (Spares), FY 21-22'!D5 -> ID | F5: Total Lubeoil Sales
F6: QTY; L
B7: ='ASE Target (Spares), FY 21-22'!A6 -> 1 | C7: =IF('ASE Target (Spares), FY 21-22'!B6=0,"",'ASE Target (Spares), FY 21-22'!B6) -> DSL-DHK | D7: =IF('ASE Target (Spares), FY 21-22'!C6=0,"",'ASE Target (Spares), FY 21-22'!C6) -> Md. Shohidul | E7: =IF('ASE Target (Spares), FY 21-22'!D6=0,"",'ASE Target (Spares), FY 21-22'!D6) -> 1418 | F7: 120
B8: ='ASE Target (Spares), FY 21-22'!A7 -> 2 | C8: =IF('ASE Target (Spares), FY 21-22'!B7=0,"",'ASE Target (Spares), FY 21-22'!B7) -> DSL-DHK | D8: =IF('ASE Target (Spares), FY 21-22'!C7=0,"",'ASE Target (Spares), FY 21-22'!C7) -> Sagar Chakrobarti | E8: =IF('ASE Target (Spares), FY 21-22'!D7=0,"",'ASE Target (Spares), FY 21-22'!D7) -> 2701
B9: ='ASE Target (Spares), FY 21-22'!A8 -> 3 | C9: =IF('ASE Target (Spares), FY 21-22'!B8=0,"",'ASE Target (Spares), FY 21-22'!B8) -> DSL-DHK | D9: =IF('ASE Target (Spares), FY 21-22'!C8=0,"",'ASE Target (Spares), FY 21-22'!C8) -> Md. Minhazul Islam | E9: =IF('ASE Target (Spares), FY 21-22'!D8=0,"",'ASE Target (Spares), FY 21-22'!D8) -> 2330
B10: ='ASE Target (Spares), FY 21-22'!A9 -> 4 | C10: =IF('ASE Target (Spares), FY 21-22'!B9=0,"",'ASE Target (Spares), FY 21-22'!B9) -> DSL-DHK | D10: =IF('ASE Target (Spares), FY 21-22'!C9=0,"",'ASE Target (Spares), FY 21-22'!C9) -> Md. Nazmul Hasan Titu | E10: =IF('ASE Target (Spares), FY 21-22'!D9=0,"",'ASE Target (Spares), FY 21-22'!D9) -> 2913 | F10: 429
B11: ='ASE Target (Spares), FY 21-22'!A10 -> 5 | C11: =IF('ASE Target (Spares), FY 21-22'!B10=0,"",'ASE Target (Spares), FY 21-22'!B10) -> DSL-DHK | D11: =IF('ASE Target (Spares), FY 21-22'!C10=0,"",'ASE Target (Spares), FY 21-22'!C10) -> Md. Zahirul Islam | E11: =IF('ASE Target (Spares), FY 21-22'!D10=0,"",'ASE Target (Spares), FY 21-22'!D10) -> 2914 | F11: 300
B12: ='ASE Target (Spares), FY 21-22'!A11 -> 6 | C12: =IF('ASE Target (Spares), FY 21-22'!B11=0,"",'ASE Target (Spares), FY 21-22'!B11) -> DSL-DHK | D12: =IF('ASE Target (Spares), FY 21-22'!C11=0,"",'ASE Target (Spares), FY 21-22'!C11) -> Md. Rakibul Hasan | E12: =IF('ASE Target (Spares), FY 21-22'!D11=0,"",'ASE Target (Spares), FY 21-22'!D11) -> 2927 | F12: 110
B13: ='ASE Target (Spares), FY 21-22'!A12 -> 7 | C13: =IF('ASE Target (Spares), FY 21-22'!B12=0,"",'ASE Target (Spares), FY 21-22'!B12) -> DSL-DHK | D13: =IF('ASE Target (Spares), FY 21-22'!C12=0,"",'ASE Target (Spares), FY 21-22'!C12) -> Md Ariful Islam | E13: =IF('ASE Target (Spares), FY 21-22'!D12=0,"",'ASE Target (Spares), FY 21-22'!D12) -> 2699
B14: ='ASE Target (Spares), FY 21-22'!A13 -> 8 | C14: =IF('ASE Target (Spares), FY 21-22'!B13=0,"",'ASE Target (Spares), FY 21-22'!B13) -> DSL-DHK | D14: =IF('ASE Target (Spares), FY 21-22'!C13=0,"",'ASE Target (Spares), FY 21-22'!C13) -> Mohammad Jewel Rana | E14: =IF('ASE Target (Spares), FY 21-22'!D13=0,"",'ASE Target (Spares), FY 21-22'!D13) -> 3002 | F14: 120
B15: ='ASE Target (Spares), FY 21-22'!A14 -> 9 | C15: =IF('ASE Target (Spares), FY 21-22'!B14=0,"",'ASE Target (Spares), FY 21-22'!B14) -> DSL-DHK | D15: =IF('ASE Target (Spares), FY 21-22'!C14=0,"",'ASE Target (Spares), FY 21-22'!C14) -> Faysal Ahmed | E15: =IF('ASE Target (Spares), FY 21-22'!D14=0,"",'ASE Target (Spares), FY 21-22'!D14) -> 3004 | F15: 100
B16: ='ASE Target (Spares), FY 21-22'!A15 -> 10 | C16: =IF('ASE Target (Spares), FY 21-22'!B15=0,"",'ASE Target (Spares), FY 21-22'!B15) -> DSL-DHK | D16: =IF('ASE Target (Spares), FY 21-22'!C15=0,"",'ASE Target (Spares), FY 21-22'!C15) -> Rakibul Islam Razib | E16: =IF('ASE Target (Spares), FY 21-22'!D15=0,"",'ASE Target (Spares), FY 21-22'!D15) -> 3006 | F16: 200
B17: ='ASE Target (Spares), FY 21-22'!A16 -> 11 | C17: =IF('ASE Target (Spares), FY 21-22'!B16=0,"",'ASE Target (Spares), FY 21-22'!B16) -> DSL-DHK | D17: =IF('ASE Target (Spares), FY 21-22'!C16=0,"",'ASE Target (Spares), FY 21-22'!C16) -> Ashraful Islam | E17: =IF('ASE Target (Spares), FY 21-22'!D16=0,"",'ASE Target (Spares), FY 21-22'!D16) -> 3003 | F17: 350
B18: ='ASE Target (Spares), FY 21-22'!A17 -> 12 | C18: =IF('ASE Target (Spares), FY 21-22'!B17=0,"",'ASE Target (Spares), FY 21-22'!B17) -> DSL-DHK | D18: =IF('ASE Target (Spares), FY 21-22'!C17=0,"",'ASE Target (Spares), FY 21-22'!C17) -> Md. Rakibul Islam | E18: =IF('ASE Target (Spares), FY 21-22'!D17=0,"",'ASE Target (Spares), FY 21-22'!D17) -> 5690 | F18: 60
B19: ='ASE Target (Spares), FY 21-22'!A18 -> 13 | C19: =IF('ASE Target (Spares), FY 21-22'!B18=0,"",'ASE Target (Spares), FY 21-22'!B18) -> DSL-DHK | D19: =IF('ASE Target (Spares), FY 21-22'!C18=0,"",'ASE Target (Spares), FY 21-22'!C18) -> Ohid Hasan Saikat | E19: =IF('ASE Target (Spares), FY 21-22'!D18=0,"",'ASE Target (Spares), FY 21-22'!D18) -> 5691
B20: ='ASE Target (Spares), FY 21-22'!A19 -> 14 | C20: =IF('ASE Target (Spares), FY 21-22'!B19=0,"",'ASE Target (Spares), FY 21-22'!B19) -> DSL-DHK | D20: =IF('ASE Target (Spares), FY 21-22'!C19=0,"",'ASE Target (Spares), FY 21-22'!C19) -> Abdullah Al Mahmud | E20: =IF('ASE Target (Spares), FY 21-22'!D19=0,"",'ASE Target (Spares), FY 21-22'!D19) -> 5692
B21: ='ASE Target (Spares), FY 21-22'!A20 -> 15 | C21: =IF('ASE Target (Spares), FY 21-22'!B20=0,"",'ASE Target (Spares), FY 21-22'!B20) -> DSL-DHK | D21: =IF('ASE Target (Spares), FY 21-22'!C20=0,"",'ASE Target (Spares), FY 21-22'!C20) -> Apurba Kumar Gain | E21: =IF('ASE Target (Spares), FY 21-22'!D20=0,"",'ASE Target (Spares), FY 21-22'!D20) -> 5927 | F21: 80
B22: ='ASE Target (Spares), FY 21-22'!A21 -> 16 | C22: =IF('ASE Target (Spares), FY 21-22'!B21=0,"",'ASE Target (Spares), FY 21-22'!B21) -> DSL-DHK | D22: =IF('ASE Target (Spares), FY 21-22'!C21=0,"",'ASE Target (Spares), FY 21-22'!C21) -> Amirul Islam | E22: =IF('ASE Target (Spares), FY 21-22'!D21=0,"",'ASE Target (Spares), FY 21-22'!D21) -> 5928
B23: ='ASE Target (Spares), FY 21-22'!A22 -> 17 | C23: =IF('ASE Target (Spares), FY 21-22'!B22=0,"",'ASE Target (Spares), FY 21-22'!B22) -> DSL-DHK | D23: =IF('ASE Target (Spares), FY 21-22'!C22=0,"",'ASE Target (Spares), FY 21-22'!C22) -> Md. Jafor Ikbal | E23: =IF('ASE Target (Spares), FY 21-22'!D22=0,"",'ASE Target (Spares), FY 21-22'!D22) -> 5929
B24: ='ASE Target (Spares), FY 21-22'!A23 -> 14 | C24: =IF('ASE Target (Spares), FY 21-22'!B23=0,"",'ASE Target (Spares), FY 21-22'!B23) -> DSL-DHK | D24: =IF('ASE Target (Spares), FY 21-22'!C23=0,"",'ASE Target (Spares), FY 21-22'!C23) -> Md. Habibur Rahman | E24: =IF('ASE Target (Spares), FY 21-22'!D23=0,"",'ASE Target (Spares), FY 21-22'!D23) -> 6079 | F24: 80
B25: ='ASE Target (Spares), FY 21-22'!A24 -> 15 | C25: =IF('ASE Target (Spares), FY 21-22'!B24=0,"",'ASE Target (Spares), FY 21-22'!B24) -> DSL-DHK | D25: =IF('ASE Target (Spares), FY 21-22'!C24=0,"",'ASE Target (Spares), FY 21-22'!C24) -> Ashikur Rahman | E25: =IF('ASE Target (Spares), FY 21-22'!D24=0,"",'ASE Target (Spares), FY 21-22'!D24) -> 6080
B26: ='ASE Target (Spares), FY 21-22'!A25 -> 16 | C26: =IF('ASE Target (Spares), FY 21-22'!B25=0,"",'ASE Target (Spares), FY 21-22'!B25) -> DSL-DHK | D26: =IF('ASE Target (Spares), FY 21-22'!C25=0,"",'ASE Target (Spares), FY 21-22'!C25) -> Md. Sujon Hossain | E26: =IF('ASE Target (Spares), FY 21-22'!D25=0,"",'ASE Target (Spares), FY 21-22'!D25) -> 6078
B27: ='ASE Target (Spares), FY 21-22'!A26 -> 15 | C27: =IF('ASE Target (Spares), FY 21-22'!B26=0,"",'ASE Target (Spares), FY 21-22'!B26) -> DSL-DHK | D27: =IF('ASE Target (Spares), FY 21-22'!C26=0,"",'ASE Target (Spares), FY 21-22'!C26) -> Md Jiaur Rahman | E27: =IF('ASE Target (Spares), FY 21-22'!D26=0,"",'ASE Target (Spares), FY 21-22'!D26) -> 0522
B28: ='ASE Target (Spares), FY 21-22'!A27 -> 16 | C28: =IF('ASE Target (Spares), FY 21-22'!B27=0,"",'ASE Target (Spares), FY 21-22'!B27) | D28: =IF('ASE Target (Spares), FY 21-22'!C27=0,"",'ASE Target (Spares), FY 21-22'!C27) -> New-2 | E28: =IF('ASE Target (Spares), FY 21-22'!D27=0,"",'ASE Target (Spares), FY 21-22'!D27)
B29: ='ASE Target (Spares), FY 21-22'!A28 -> 17 | C29: =IF('ASE Target (Spares), FY 21-22'!B28=0,"",'ASE Target (Spares), FY 21-22'!B28) | D29: =IF('ASE Target (Spares), FY 21-22'!C28=0,"",'ASE Target (Spares), FY 21-22'!C28) -> New-3 | E29: =IF('ASE Target (Spares), FY 21-22'!D28=0,"",'ASE Target (Spares), FY 21-22'!D28)
B30: ='ASE Target (Spares), FY 21-22'!A29 -> 18 | C30: =IF('ASE Target (Spares), FY 21-22'!B29=0,"",'ASE Target (Spares), FY 21-22'!B29) | D30: =IF('ASE Target (Spares), FY 21-22'!C29=0,"",'ASE Target (Spares), FY 21-22'!C29) -> New-4 | E30: =IF('ASE Target (Spares), FY 21-22'!D29=0,"",'ASE Target (Spares), FY 21-22'!D29)
B31: ='ASE Target (Spares), FY 21-22'!A30 -> 19 | C31: =IF('ASE Target (Spares), FY 21-22'!B30=0,"",'ASE Target (Spares), FY 21-22'!B30) -> CTG | D31: =IF('ASE Target (Spares), FY 21-22'!C30=0,"",'ASE Target (Spares), FY 21-22'!C30) -> Sumon Sen | E31: =IF('ASE Target (Spares), FY 21-22'!D30=0,"",'ASE Target (Spares), FY 21-22'!D30) -> 8041
B32: ='ASE Target (Spares), FY 21-22'!A31 -> 20 | C32: =IF('ASE Target (Spares), FY 21-22'!B31=0,"",'ASE Target (Spares), FY 21-22'!B31) -> CTG | D32: =IF('ASE Target (Spares), FY 21-22'!C31=0,"",'ASE Target (Spares), FY 21-22'!C31) -> Tapan Barua | E32: =IF('ASE Target (Spares), FY 21-22'!D31=0,"",'ASE Target (Spares), FY 21-22'!D31) -> 1475
B33: ='ASE Target (Spares), FY 21-22'!A32 -> 21 | C33: =IF('ASE Target (Spares), FY 21-22'!B32=0,"",'ASE Target (Spares), FY 21-22'!B32) -> CTG | D33: =IF('ASE Target (Spares), FY 21-22'!C32=0,"",'ASE Target (Spares), FY 21-22'!C32) -> Sozol prince | E33: =IF('ASE Target (Spares), FY 21-22'!D32=0,"",'ASE Target (Spares), FY 21-22'!D32) -> 6076
B34: ='ASE Target (Spares), FY 21-22'!A33 -> 16 | C34: =IF('ASE Target (Spares), FY 21-22'!B33=0,"",'ASE Target (Spares), FY 21-22'!B33) | D34: =IF('ASE Target (Spares), FY 21-22'!C33=0,"",'ASE Target (Spares), FY 21-22'!C33) -> New-5 | E34: =IF('ASE Target (Spares), FY 21-22'!D33=0,"",'ASE Target (Spares), FY 21-22'!D33)
B35: ='ASE Target (Spares), FY 21-22'!A34 -> 17 | C35: =IF('ASE Target (Spares), FY 21-22'!B34=0,"",'ASE Target (Spares), FY 21-22'!B34) | D35: =IF('ASE Target (Spares), FY 21-22'!C34=0,"",'ASE Target (Spares), FY 21-22'!C34) -> New-6 | E35: =IF('ASE Target (Spares), FY 21-22'!D34=0,"",'ASE Target (Spares), FY 21-22'!D34)
B36: ='ASE Target (Spares), FY 21-22'!A35 -> 0 | C36: =IF('ASE Target (Spares), FY 21-22'!B35=0,"",'ASE Target (Spares), FY 21-22'!B35) | D36: =IF('ASE Target (Spares), FY 21-22'!C35=0,"",'ASE Target (Spares), FY 21-22'!C35) | E36: =IF('ASE Target (Spares), FY 21-22'!D35=0,"",'ASE Target (Spares), FY 21-22'!D35)
B37: ='ASE Target (Spares), FY 21-22'!A35 -> 0 | C37: =IF('ASE Target (Spares), FY 21-22'!B35=0,"",'ASE Target (Spares), FY 21-22'!B35) | D37: =IF('ASE Target (Spares), FY 21-22'!C35=0,"",'ASE Target (Spares), FY 21-22'!C35) | E37: =IF('ASE Target (Spares), FY 21-22'!D35=0,"",'ASE Target (Spares), FY 21-22'!D35)
B38: ='ASE Target (Spares), FY 21-22'!A36 -> 0 | C38: =IF('ASE Target (Spares), FY 21-22'!B36=0,"",'ASE Target (Spares), FY 21-22'!B36) | D38: =IF('ASE Target (Spares), FY 21-22'!C36=0,"",'ASE Target (Spares), FY 21-22'!C36) | E38: =IF('ASE Target (Spares), FY 21-22'!D36=0,"",'ASE Target (Spares), FY 21-22'!D36)
B39: ='ASE Target (Spares), FY 21-22'!A37 -> 0 | C39: =IF('ASE Target (Spares), FY 21-22'!B37=0,"",'ASE Target (Spares), FY 21-22'!B37) | D39: =IF('ASE Target (Spares), FY 21-22'!C37=0,"",'ASE Target (Spares), FY 21-22'!C37) | E39: =IF('ASE Target (Spares), FY 21-22'!D37=0,"",'ASE Target (Spares), FY 21-22'!D37)
B40: ='ASE Target (Spares), FY 21-22'!A38 -> 0 | C40: =IF('ASE Target (Spares), FY 21-22'!B38=0,"",'ASE Target (Spares), FY 21-22'!B38) | D40: =IF('ASE Target (Spares), FY 21-22'!C38=0,"",'ASE Target (Spares), FY 21-22'!C38) | E40: =IF('ASE Target (Spares), FY 21-22'!D38=0,"",'ASE Target (Spares), FY 21-22'!D38)

Sheet ASE Ach (Service)(Input)
B2: ='Monthly Summary (No Input)'!B2 -> Month | C2: ='Monthly Summary (No Input)'!C2 -> Jul | D2: <<< No input
B4: Service Payment & TDS/VDS Collection | F4: No input▼ | G4: No input▼ | H4: input▼ | I4: input▼ | J4: input▼ | K4: input▼ | L4: input▼ | M4: input▼ | N4: input▼ | O4: input▼ | P4: input▼ | Q4: input▼ | R4: input▼ | S4: input▼ | T4: input▼ | U4: input▼ | V4: input▼ | W4: input▼ | X4: input▼ | Y4: input▼ | Z4: input▼ | AA4: input▼ | AB4: input▼ | AC4: input▼ | AD4: input▼ | AE4: input▼ | AF4: input▼ | AG4: input▼ | AH4: input▼ | AI4: input▼ | AJ4: input▼ | AK4: input▼ | AL4: input▼ | AM4: input▼ | AN4: input▼ | AO4: input▼ | AP4: input▼ | AQ4: input▼ | AR4: input▼ | AS4: input▼ | AT4: input▼ | AU4: input▼ | AV4: input▼ | AW4: input▼ | AX4: input▼ | AY4: input▼ | AZ4: input▼ | BA4: input▼ | BB4: input▼ | BC4: input▼ | BD4: input▼ | BE4: input▼ | BF4: input▼ | BG4: input▼ | BH4: input▼ | BI4: input▼ | BJ4: input▼ | BK4: input▼ | BL4: input▼ | BM4: input▼ | BN4: input▼ | BO4: input▼ | BP4: input▼ | BQ4: input▼ | BR4: input▼ | BS4: input▼ | BT4: input▼ | BU4: input▼ | BV4: input▼ | BW4: input▼ | BX4: input▼ | BY4: input▼ | BZ4: input▼ | CA4: input▼ | CB4: input▼ | CC4: input▼ | CD4: input▼ | CE4: input▼ | CF4: input▼ | CG4: input▼ | CH4: input▼ | CI4: input▼ | CJ4: input▼ | CK4: input▼ | CL4: input▼ | CM4: input▼ | CN4: input▼ | CO4: input▼ | CP4: input▼ | CQ4: input▼ | CR4: input▼ | CS4: input▼ | CT4: input▼ | CU4: input▼ | CV4: input▼ | CW4: input▼ | CX4: input▼ | CY4: input▼ | CZ4: input▼ | DA4: input▼ | DB4: input▼ | DC4: input▼ | DD4: input▼ | DE4: input▼ | DF4: input▼ | DG4: input▼ | DH4: input▼ | DI4: input▼ | DJ4: input▼ | DK4: input▼ | DL4: input▼ | DM4: input▼ | DN4: input▼ | DO4: input▼ | DP4: input▼ | DQ4: input▼ | DR4: input▼ | DS4: input▼ | DT4: input▼ | DU4: input▼ | DV4: input▼ | DW4: input▼ | DX4: input▼ | DY4: input▼ | DZ4: input▼ | EA4: input▼ | EB4: input▼ | EC4: input▼ | ED4: input▼ | EE4: input▼ | EF4: input▼ | EG4: input▼ | EH4: input▼ | EI4: input▼ | EJ4: input▼ | EK4: input▼ | EL4: input▼ | EM4: input▼ | EN4: input▼ | EO4: input▼ | EP4: input▼ | EQ4: input▼ | ER4: input▼ | ES4: input▼ | ET4: input▼ | EU4: input▼ | EV4: input▼ | EW4: input▼ | EX4: input▼ | EY4: input▼ | EZ4: input▼ | FA4: input▼ | FB4: input▼ | FC4: input▼ | FD4: input▼ | FE4: input▼ | FF4: input▼ | FG4: input▼ | FH4: input▼ | FI4: input▼ | FJ4: input▼ | FK4: input▼ | FL4: input▼ | FM4: input▼ | FN4: input▼ | FO4: input▼ | FP4: input▼ | FQ4: input▼ | FR4: input▼ | FS4: input▼ | FT4: input▼ | FU4: input▼ | FV4: input▼ | FW4: input▼ | FX4: input▼ | FY4: input▼ | FZ4: input▼ | GA4: input▼ | GB4: input▼ | GC4: input▼ | GD4: input▼ | GE4: input▼ | GF4: input▼ | GG4: input▼ | GH4: input▼ | GI4: input▼ | GJ4: input▼ | GK4: input▼ | GL4: input▼ | GM4: input▼ | GN4: input▼ | GO4: input▼ | GP4: input▼ | GQ4: input▼ | GR4: input▼ | GS4: input▼ | GT4: input▼ | GU4: input▼ | GV4: input▼ | GW4: input▼ | GX4: input▼ | GY4: input▼ | GZ4: input▼ | HA4: input▼ | HB4: input▼ | HC4: input▼ | HD4: input▼ | HE4: input▼ | HF4: input▼ | HG4: input▼ | HH4: input▼ | HI4: input▼ | HJ4: input▼ | HK4: input▼ | HL4: input▼ | HM4: input▼ | HN4: input▼ | HO4: input▼ | HP4: input▼ | HQ4: input▼ | HR4: input▼ | HS4: input▼ | HT4: input▼ | HU4: input▼ | HV4: input▼ | HW4: input▼ | HX4: input▼ | HY4: input▼ | HZ4: input▼ | IA4: input▼ | IB4: input▼ | IC4: input▼ | ID4: input▼ | IE4: input▼ | IF4: input▼ | IG4: input▼ | IH4: input▼ | II4: input▼ | IJ4: input▼ | IK4: input▼ | IL4: input▼ | IM4: input▼ | IN4: input▼ | IO4: input▼ | IP4: input▼ | IQ4: input▼ | IR4: input▼ | IS4: input▼ | IT4: input▼ | IU4: input▼ | IV4: input▼ | IW4: input▼ | IX4: input▼ | IY4: input▼ | IZ4: input▼ | JA4: input▼ | JB4: input▼ | JC4: input▼ | JD4: input▼ | JE4: input▼ | JF4: input▼ | JG4: input▼ | JH4: input▼ | JI4: input▼ | JJ4: input▼ | JK4: input▼ | JL4: input▼ | JM4: input▼ | JN4: input▼ | JO4: input▼ | JP4: input▼ | JQ4: input▼ | JR4: input▼ | JS4: input▼ | JT4: input▼ | JU4: input▼ | JV4: input▼ | JW4: input▼ | JX4: input▼ | JY4: input▼ | JZ4: input▼ | KA4: input▼ | KB4: input▼ | KC4: input▼ | KD4: input▼ | KE4: input▼ | KF4: input▼ | KG4: input▼ | KH4: input▼ | KI4: input▼
B5: ='ASE Target (Spares), FY 21-22'!A5 -> Sl. | C5: ='ASE Target (Spares), FY 21-22'!B5 -> Wing | D5: ='ASE Target (Spares), FY 21-22'!C5 -> Name | E5: ='ASE Target (Spares), FY 21-22'!D5 -> ID | F5: Total Service Amount | G5: Total TDS/VDS Collection | H5: Per Service Amount | I5: Per TDS/VDS Collection | J5: Per Service Amount | K5: Per TDS/VDS Collection | L5: Per Service Amount | M5: Per TDS/VDS Collection | N5: Per Service Amount | O5: Per TDS/VDS Collection | P5: Per Service Amount | Q5: Per TDS/VDS Collection | R5: Per Service Amount | S5: Per TDS/VDS Collection | T5: Per Service Amount | U5: Per TDS/VDS Collection | V5: Per Service Amount | W5: Per TDS/VDS Collection | X5: Per Service Amount | Y5: Per TDS/VDS Collection | Z5: Per Service Amount | AA5: Per TDS/VDS Collection | AB5: Per Service Amount | AC5: Per TDS/VDS Collection | AD5: Per Service Amount | AE5: Per TDS/VDS Collection | AF5: Per Service Amount | AG5: Per TDS/VDS Collection | AH5: Per Service Amount | AI5: Per TDS/VDS Collection | AJ5: Per Service Amount | AK5: Per TDS/VDS Collection | AL5: Per Service Amount | AM5: Per TDS/VDS Collection | AN5: Per Service Amount | AO5: Per TDS/VDS Collection | AP5: Per Service Amount | AQ5: Per TDS/VDS Collection | AR5: Per Service Amount | AS5: Per TDS/VDS Collection | AT5: Per Service Amount | AU5: Per TDS/VDS Collection | AV5: Per Service Amount | AW5: Per TDS/VDS Collection | AX5: Per Service Amount | AY5: Per TDS/VDS Collection | AZ5: Per Service Amount | BA5: Per TDS/VDS Collection | BB5: Per Service Amount | BC5: Per TDS/VDS Collection | BD5: Per Service Amount | BE5: Per TDS/VDS Collection | BF5: Per Service Amount | BG5: Per TDS/VDS Collection | BH5: Per Service Amount | BI5: Per TDS/VDS Collection | BJ5: Per Service Amount | BK5: Per TDS/VDS Collection | BL5: Per Service Amount | BM5: Per TDS/VDS Collection | BN5: Per Service Amount | BO5: Per TDS/VDS Collection | BP5: Per Service Amount | BQ5: Per TDS/VDS Collection | BR5: Per Service Amount | BS5: Per TDS/VDS Collection | BT5: Per Service Amount | BU5: Per TDS/VDS Collection | BV5: Per Service Amount | BW5: Per TDS/VDS Collection | BX5: Per Service Amount | BY5: Per TDS/VDS Collection | BZ5: Per Service Amount | CA5: Per TDS/VDS Collection | CB5: Per Service Amount | CC5: Per TDS/VDS Collection | CD5: Per Service Amount | CE5: Per TDS/VDS Collection | CF5: Per Service Amount | CG5: Per TDS/VDS Collection | CH5: Per Service Amount | CI5: Per TDS/VDS Collection | CJ5: Per Service Amount | CK5: Per TDS/VDS Collection | CL5: Per Service Amount | CM5: Per TDS/VDS Collection | CN5: Per Service Amount | CO5: Per TDS/VDS Collection | CP5: Per Service Amount | CQ5: Per TDS/VDS Collection | CR5: Per Service Amount | CS5: Per TDS/VDS Collection | CT5: Per Service Amount | CU5: Per TDS/VDS Collection | CV5: Per Service Amount | CW5: Per TDS/VDS Collection | CX5: Per Service Amount | CY5: Per TDS/VDS Collection | CZ5: Per Service Amount | DA5: Per TDS/VDS Collection | DB5: Per Service Amount | DC5: Per TDS/VDS Collection | DD5: Per Service Amount | DE5: Per TDS/VDS Collection | DF5: Per Service Amount | DG5: Per TDS/VDS Collection | DH5: Per Service Amount | DI5: Per TDS/VDS Collection | DJ5: Per Service Amount | DK5: Per TDS/VDS Collection | DL5: Per Service Amount | DM5: Per TDS/VDS Collection | DN5: Per Service Amount | DO5: Per TDS/VDS Collection | DP5: Per Service Amount | DQ5: Per TDS/VDS Collection | DR5: Per Service Amount | DS5: Per TDS/VDS Collection | DT5: Per Service Amount | DU5: Per TDS/VDS Collection | DV5: Per Service Amount | DW5: Per TDS/VDS Collection | DX5: Per Service Amount | DY5: Per TDS/VDS Collection | DZ5: Per Service Amount | EA5: Per TDS/VDS Collection | EB5: Per Service Amount | EC5: Per TDS/VDS Collection | ED5: Per Service Amount | EE5: Per TDS/VDS Collection | EF5: Per Service Amount | EG5: Per TDS/VDS Collection | EH5: Per Service Amount | EI5: Per TDS/VDS Collection | EJ5: Per Service Amount | EK5: Per TDS/VDS Collection | EL5: Per Service Amount | EM5: Per TDS/VDS Collection | EN5: Per Service Amount | EO5: Per TDS/VDS Collection | EP5: Per Service Amount | EQ5: Per TDS/VDS Collection | ER5: Per Service Amount | ES5: Per TDS/VDS Collection | ET5: Per Service Amount | EU5: Per TDS/VDS Collection | EV5: Per Service Amount | EW5: Per TDS/VDS Collection | EX5: Per Service Amount | EY5: Per TDS/VDS Collection | EZ5: Per Service Amount | FA5: Per TDS/VDS Collection | FB5: Per Service Amount | FC5: Per TDS/VDS Collection | FD5: Per Service Amount | FE5: Per TDS/VDS Collection | FF5: Per Service Amount | FG5: Per TDS/VDS Collection | FH5: Per Service Amount | FI5: Per TDS/VDS Collection | FJ5: Per Service Amount | FK5: Per TDS/VDS Collection | FL5: Per Service Amount | FM5: Per TDS/VDS Collection | FN5: Per Service Amount | FO5: Per TDS/VDS Collection | FP5: Per Service Amount | FQ5: Per TDS/VDS Collection | FR5: Per Service Amount | FS5: Per TDS/VDS Collection | FT5: Per Service Amount | FU5: Per TDS/VDS Collection | FV5: Per Service Amount | FW5: Per TDS/VDS Collection | FX5: Per Service Amount | FY5: Per TDS/VDS Collection | FZ5: Per Service Amount | GA5: Per TDS/VDS Collection | GB5: Per Service Amount | GC5: Per TDS/VDS Collection | GD5: Per Service Amount | GE5: Per TDS/VDS Collection | GF5: Per Service Amount | GG5: Per TDS/VDS Collection | GH5: Per Service Amount | GI5: Per TDS/VDS Collection | GJ5: Per Service Amount | GK5: Per TDS/VDS Collection | GL5: Per Service Amount | GM5: Per TDS/VDS Collection | GN5: Per Service Amount | GO5: Per TDS/VDS Collection | GP5: Per Service Amount | GQ5: Per TDS/VDS Collection | GR5: Per Service Amount | GS5: Per TDS/VDS Collection | GT5: Per Service Amount | GU5: Per TDS/VDS Collection | GV5: Per Service Amount | GW5: Per TDS/VDS Collection | GX5: Per Service Amount | GY5: Per TDS/VDS Collection | GZ5: Per Service Amount | HA5: Per TDS/VDS Collection | HB5: Per Service Amount | HC5: Per TDS/VDS Collection | HD5: Per Service Amount | HE5: Per TDS/VDS Collection | HF5: Per Service Amount | HG5: Per TDS/VDS Collection | HH5: Per Service Amount | HI5: Per TDS/VDS Collection | HJ5: Per Service Amount | HK5: Per TDS/VDS Collection | HL5: Per Service Amount | HM5: Per TDS/VDS Collection | HN5: Per Service Amount | HO5: Per TDS/VDS Collection | HP5: Per Service Amount | HQ5: Per TDS/VDS Collection | HR5: Per Service Amount | HS5: Per TDS/VDS Collection | HT5: Per Service Amount | HU5: Per TDS/VDS Collection | HV5: Per Service Amount | HW5: Per TDS/VDS Collection | HX5: Per Service Amount | HY5: Per TDS/VDS Collection | HZ5: Per Service Amount | IA5: Per TDS/VDS Collection | IB5: Per Service Amount | IC5: Per TDS/VDS Collection | ID5: Per Service Amount | IE5: Per TDS/VDS Collection | IF5: Per Service Amount | IG5: Per TDS/VDS Collection | IH5: Per Service Amount | II5: Per TDS/VDS Collection | IJ5: Per Service Amount | IK5: Per TDS/VDS Collection | IL5: Per Service Amount | IM5: Per TDS/VDS Collection | IN5: Per Service Amount | IO5: Per TDS/VDS Collection | IP5: Per Service Amount | IQ5: Per TDS/VDS Collection | IR5: Per Service Amount | IS5: Per TDS/VDS Collection | IT5: Per Service Amount | IU5: Per TDS/VDS Collection | IV5: Per Service Amount | IW5: Per TDS/VDS Collection | IX5: Per Service Amount | IY5: Per TDS/VDS Collection | IZ5: Per Service Amount | JA5: Per TDS/VDS Collection | JB5: Per Service Amount | JC5: Per TDS/VDS Collection | JD5: Per Service Amount | JE5: Per TDS/VDS Collection | JF5: Per Service Amount | JG5: Per TDS/VDS Collection | JH5: Per Service Amount | JI5: Per TDS/VDS Collection | JJ5: Per Service Amount | JK5: Per TDS/VDS Collection | JL5: Per Service Amount | JM5: Per TDS/VDS Collection | JN5: Per Service Amount | JO5: Per TDS/VDS Collection | JP5: Per Service Amount | JQ5: Per TDS/VDS Collection | JR5: Per Service Amount | JS5: Per TDS/VDS Collection | JT5: Per Service Amount | JU5: Per TDS/VDS Collection | JV5: Per Service Amount | JW5: Per TDS/VDS Collection | JX5: Per Service Amount | JY5: Per TDS/VDS Collection | JZ5: Per Service Amount | KA5: Per TDS/VDS Collection | KB5: Per Service Amount | KC5: Per TDS/VDS Collection | KD5: Per Service Amount | KE5: Per TDS/VDS Collection | KF5: Per Service Amount | KG5: Per TDS/VDS Collection | KH5: Per Service Amount | KI5: Per TDS/VDS Collection
B6: ='ASE Target (Spares), FY 21-22'!A6 -> 1 | C6: ='ASE Target vs Ach(Spares)(Inpt)'!C7 -> DSL-DHK | D6: ='ASE Target vs Ach(Spares)(Inpt)'!D7 -> Md. Shohidul | E6: ='ASE Target vs Ach(Spares)(Inpt)'!E7 -> 1418 | F6: =H6+J6+L6+N6+P6+R6+T6+V6+X6+Z6+AB6+AD6+AF6+AH6+AJ6+AL6+AN6+AP6+AR6+AT6+AV6+AX6+AZ6+BB6+BD6+BF6+BH6+BJ6+BL6+BN6+BP6+BR6+BT6+BV6+BX6+BZ6+CB6+CD6+CF6+CH6+CJ6+CL6+CM6+CO6+CQ6+CS6+CU6+CW6+CY6+DB6+DD6+DF6+DH6+DJ6+DL6+DN6+DP6+DR6+DT6+DV6+DX6+DZ6+EB6+ED6+EF6+EH6+EJ6+EL6+EN6+EP6+ER6+ET6+EV6+EX6+EZ6+FB6+FD6+FF6+FH6+FJ6+FL6+FN6+FP6+FR6+FT6+FV6+FX6+FZ6+GB6+GD6+GF6+GH6+GJ6+GL6+GN6+GP6+GR6+GT6+GV6+GX6+GZ6+HB6+HD6+HF6+HH6+HJ6+HL6+HN6+HP6+HR6+HT6+HV6+HX6+HZ6+IB6+ID6+IF6+IH6+IJ6+IL6+IN6+IP6+IR6+IT6+IV6+IX6+IZ6+JB6+JD6+JF6+JH6+JJ6+JL6+JN6+JP6+JR6+JT6+JV6+JX6+JZ6+KB6+KD6+KF6+KH6 -> 202901 | G6: =I6+K6+M6+O6+Q6+S6+U6+W6+Y6+AA6+AC6+AE6+AG6+AI6+AK6+AM6+AO6+AQ6+AS6+AU6+AW6+AY6+BA6+BC6+BE6+BG6+BI6+BK6+BM6+BO6+BQ6+BS6+BU6+BW6+BY6+CA6+CC6+CE6+CG6+CI6+CK6+CM6+CN6+CP6+CR6+CT6+CV6+CX6+CZ6+DC6+DE6+DG6+DI6+DK6+DM6+DO6+DQ6+DS6+DU6+DW6+DY6+EA6+EC6+EE6+EG6+EI6+EK6+EM6+EO6+EQ6+ES6+EU6+EW6+EY6+FA6+FC6+FE6+FG6+FI6+FK6+FM6+FO6+FQ6+FS6+FU6+FW6+FY6+GA6+GC6+GE6+GG6+GI6+GK6+GM6+GO6+GQ6+GS6+GU6+GW6+GY6+HA6+HC6+HE6+HG6+HI6+HK6+HM6+HO6+HQ6+HS6+HU6+HW6+HY6+IA6+IC6+IE6+IG6+II6+IK6+IM6+IO6+IQ6+IS6+IU6+IW6+IY6+JA6+JC6+JE6+JG6+JI6+JK6+JM6+JO6+JQ6+JS6+JU6+JW6+JY6+KA6+KC6+KE6+KG6+KI6 -> 0 | H6: 2000 | J6: 2000 | L6: 4000 | N6: 4000 | P6: 3863 | R6: 3000 | T6: 3000 | V6: 12000 | X6: 8000 | Z6: 13000 | AB6: 32175 | AD6: 10691 | AF6: 10691 | AH6: 3000 | AJ6: 3000 | AL6: 15000 | AN6: 12500 | AP6: 2000 | AR6: 3564 | AT6: 8749 | AV6: 3340 | AX6: 1000 | AZ6: 35273 | BB6: 7055
B7: ='ASE Target (Spares), FY 21-22'!A7 -> 2 | C7: ='ASE Target vs Ach(Spares)(Inpt)'!C8 -> DSL-DHK | D7: ='ASE Target vs Ach(Spares)(Inpt)'!D8 -> Sagar Chakrobarti | E7: ='ASE Target vs Ach(Spares)(Inpt)'!E8 -> 2701 | F7: =H7+J7+L7+N7+P7+R7+T7+V7+X7+Z7+AB7+AD7+AF7+AH7+AJ7+AL7+AN7+AP7+AR7+AT7+AV7+AX7+AZ7+BB7+BD7+BF7+BH7+BJ7+BL7+BN7+BP7+BR7+BT7+BV7+BX7+BZ7+CB7+CD7+CF7+CH7+CJ7+CL7+CM7+CO7+CQ7+CS7+CU7+CW7+CY7+DB7+DD7+DF7+DH7+DJ7+DL7+DN7+DP7+DR7+DT7+DV7+DX7+DZ7+EB7+ED7+EF7+EH7+EJ7+EL7+EN7+EP7+ER7+ET7+EV7+EX7+EZ7+FB7+FD7+FF7+FH7+FJ7+FL7+FN7+FP7+FR7+FT7+FV7+FX7+FZ7+GB7+GD7+GF7+GH7+GJ7+GL7+GN7+GP7+GR7+GT7+GV7+GX7+GZ7+HB7+HD7+HF7+HH7+HJ7+HL7+HN7+HP7+HR7+HT7+HV7+HX7+HZ7+IB7+ID7+IF7+IH7+IJ7+IL7+IN7+IP7+IR7+IT7+IV7+IX7+IZ7+JB7+JD7+JF7+JH7+JJ7+JL7+JN7+JP7+JR7+JT7+JV7+JX7+JZ7+KB7+KD7+KF7+KH7 -> 0 | G7: =I7+K7+M7+O7+Q7+S7+U7+W7+Y7+AA7+AC7+AE7+AG7+AI7+AK7+AM7+AO7+AQ7+AS7+AU7+AW7+AY7+BA7+BC7+BE7+BG7+BI7+BK7+BM7+BO7+BQ7+BS7+BU7+BW7+BY7+CA7+CC7+CE7+CG7+CI7+CK7+CM7+CN7+CP7+CR7+CT7+CV7+CX7+CZ7+DC7+DE7+DG7+DI7+DK7+DM7+DO7+DQ7+DS7+DU7+DW7+DY7+EA7+EC7+EE7+EG7+EI7+EK7+EM7+EO7+EQ7+ES7+EU7+EW7+EY7+FA7+FC7+FE7+FG7+FI7+FK7+FM7+FO7+FQ7+FS7+FU7+FW7+FY7+GA7+GC7+GE7+GG7+GI7+GK7+GM7+GO7+GQ7+GS7+GU7+GW7+GY7+HA7+HC7+HE7+HG7+HI7+HK7+HM7+HO7+HQ7+HS7+HU7+HW7+HY7+IA7+IC7+IE7+IG7+II7+IK7+IM7+IO7+IQ7+IS7+IU7+IW7+IY7+JA7+JC7+JE7+JG7+JI7+JK7+JM7+JO7+JQ7+JS7+JU7+JW7+JY7+KA7+KC7+KE7+KG7+KI7 -> 0
B8: ='ASE Target (Spares), FY 21-22'!A8 -> 3 | C8: ='ASE Target vs Ach(Spares)(Inpt)'!C9 -> DSL-DHK | D8: ='ASE Target vs Ach(Spares)(Inpt)'!D9 -> Md. Minhazul Islam | E8: ='ASE Target vs Ach(Spares)(Inpt)'!E9 -> 2330 | F8: =H8+J8+L8+N8+P8+R8+T8+V8+X8+Z8+AB8+AD8+AF8+AH8+AJ8+AL8+AN8+AP8+AR8+AT8+AV8+AX8+AZ8+BB8+BD8+BF8+BH8+BJ8+BL8+BN8+BP8+BR8+BT8+BV8+BX8+BZ8+CB8+CD8+CF8+CH8+CJ8+CL8+CM8+CO8+CQ8+CS8+CU8+CW8+CY8+DB8+DD8+DF8+DH8+DJ8+DL8+DN8+DP8+DR8+DT8+DV8+DX8+DZ8+EB8+ED8+EF8+EH8+EJ8+EL8+EN8+EP8+ER8+ET8+EV8+EX8+EZ8+FB8+FD8+FF8+FH8+FJ8+FL8+FN8+FP8+FR8+FT8+FV8+FX8+FZ8+GB8+GD8+GF8+GH8+GJ8+GL8+GN8+GP8+GR8+GT8+GV8+GX8+GZ8+HB8+HD8+HF8+HH8+HJ8+HL8+HN8+HP8+HR8+HT8+HV8+HX8+HZ8+IB8+ID8+IF8+IH8+IJ8+IL8+IN8+IP8+IR8+IT8+IV8+IX8+IZ8+JB8+JD8+JF8+JH8+JJ8+JL8+JN8+JP8+JR8+JT8+JV8+JX8+JZ8+KB8+KD8+KF8+KH8 -> 0 | G8: =I8+K8+M8+O8+Q8+S8+U8+W8+Y8+AA8+AC8+AE8+AG8+AI8+AK8+AM8+AO8+AQ8+AS8+AU8+AW8+AY8+BA8+BC8+BE8+BG8+BI8+BK8+BM8+BO8+BQ8+BS8+BU8+BW8+BY8+CA8+CC8+CE8+CG8+CI8+CK8+CM8+CN8+CP8+CR8+CT8+CV8+CX8+CZ8+DC8+DE8+DG8+DI8+DK8+DM8+DO8+DQ8+DS8+DU8+DW8+DY8+EA8+EC8+EE8+EG8+EI8+EK8+EM8+EO8+EQ8+ES8+EU8+EW8+EY8+FA8+FC8+FE8+FG8+FI8+FK8+FM8+FO8+FQ8+FS8+FU8+FW8+FY8+GA8+GC8+GE8+GG8+GI8+GK8+GM8+GO8+GQ8+GS8+GU8+GW8+GY8+HA8+HC8+HE8+HG8+HI8+HK8+HM8+HO8+HQ8+HS8+HU8+HW8+HY8+IA8+IC8+IE8+IG8+II8+IK8+IM8+IO8+IQ8+IS8+IU8+IW8+IY8+JA8+JC8+JE8+JG8+JI8+JK8+JM8+JO8+JQ8+JS8+JU8+JW8+JY8+KA8+KC8+KE8+KG8+KI8 -> 0
B9: ='ASE Target (Spares), FY 21-22'!A9 -> 4 | C9: ='ASE Target vs Ach(Spares)(Inpt)'!C10 -> DSL-DHK | D9: ='ASE Target vs Ach(Spares)(Inpt)'!D10 -> Md. Nazmul Hasan Titu | E9: ='ASE Target vs Ach(Spares)(Inpt)'!E10 -> 2913 | F9: =H9+J9+L9+N9+P9+R9+T9+V9+X9+Z9+AB9+AD9+AF9+AH9+AJ9+AL9+AN9+AP9+AR9+AT9+AV9+AX9+AZ9+BB9+BD9+BF9+BH9+BJ9+BL9+BN9+BP9+BR9+BT9+BV9+BX9+BZ9+CB9+CD9+CF9+CH9+CJ9+CL9+CM9+CO9+CQ9+CS9+CU9+CW9+CY9+DB9+DD9+DF9+DH9+DJ9+DL9+DN9+DP9+DR9+DT9+DV9+DX9+DZ9+EB9+ED9+EF9+EH9+EJ9+EL9+EN9+EP9+ER9+ET9+EV9+EX9+EZ9+FB9+FD9+FF9+FH9+FJ9+FL9+FN9+FP9+FR9+FT9+FV9+FX9+FZ9+GB9+GD9+GF9+GH9+GJ9+GL9+GN9+GP9+GR9+GT9+GV9+GX9+GZ9+HB9+HD9+HF9+HH9+HJ9+HL9+HN9+HP9+HR9+HT9+HV9+HX9+HZ9+IB9+ID9+IF9+IH9+IJ9+IL9+IN9+IP9+IR9+IT9+IV9+IX9+IZ9+JB9+JD9+JF9+JH9+JJ9+JL9+JN9+JP9+JR9+JT9+JV9+JX9+JZ9+KB9+KD9+KF9+KH9 -> 131824 | G9: =I9+K9+M9+O9+Q9+S9+U9+W9+Y9+AA9+AC9+AE9+AG9+AI9+AK9+AM9+AO9+AQ9+AS9+AU9+AW9+AY9+BA9+BC9+BE9+BG9+BI9+BK9+BM9+BO9+BQ9+BS9+BU9+BW9+BY9+CA9+CC9+CE9+CG9+CI9+CK9+CM9+CN9+CP9+CR9+CT9+CV9+CX9+CZ9+DC9+DE9+DG9+DI9+DK9+DM9+DO9+DQ9+DS9+DU9+DW9+DY9+EA9+EC9+EE9+EG9+EI9+EK9+EM9+EO9+EQ9+ES9+EU9+EW9+EY9+FA9+FC9+FE9+FG9+FI9+FK9+FM9+FO9+FQ9+FS9+FU9+FW9+FY9+GA9+GC9+GE9+GG9+GI9+GK9+GM9+GO9+GQ9+GS9+GU9+GW9+GY9+HA9+HC9+HE9+HG9+HI9+HK9+HM9+HO9+HQ9+HS9+HU9+HW9+HY9+IA9+IC9+IE9+IG9+II9+IK9+IM9+IO9+IQ9+IS9+IU9+IW9+IY9+JA9+JC9+JE9+JG9+JI9+JK9+JM9+JO9+JQ9+JS9+JU9+JW9+JY9+KA9+KC9+KE9+KG9+KI9 -> 0 | H9: 3000 | J9: 3990 | L9: 3000 | N9: 3500 | P9: 8182 | R9: 12000 | T9: 18000 | V9: 40000 | X9: 6716 | Z9: 6136 | AB9: 4500 | AD9: 3900 | AF9: 3900 | AH9: 5000 | AJ9: 5000 | AL9: 5000
B10: ='ASE Target (Spares), FY 21-22'!A10 -> 5 | C10: ='ASE Target vs Ach(Spares)(Inpt)'!C11 -> DSL-DHK | D10: ='ASE Target vs Ach(Spares)(Inpt)'!D11 -> Md. Zahirul Islam | E10: ='ASE Target vs Ach(Spares)(Inpt)'!E11 -> 2914 | F10: =H10+J10+L10+N10+P10+R10+T10+V10+X10+Z10+AB10+AD10+AF10+AH10+AJ10+AL10+AN10+AP10+AR10+AT10+AV10+AX10+AZ10+BB10+BD10+BF10+BH10+BJ10+BL10+BN10+BP10+BR10+BT10+BV10+BX10+BZ10+CB10+CD10+CF10+CH10+CJ10+CL10+CM10+CO10+CQ10+CS10+CU10+CW10+CY10+DB10+DD10+DF10+DH10+DJ10+DL10+DN10+DP10+DR10+DT10+DV10+DX10+DZ10+EB10+ED10+EF10+EH10+EJ10+EL10+EN10+EP10+ER10+ET10+EV10+EX10+EZ10+FB10+FD10+FF10+FH10+FJ10+FL10+FN10+FP10+FR10+FT10+FV10+FX10+FZ10+GB10+GD10+GF10+GH10+GJ10+GL10+GN10+GP10+GR10+GT10+GV10+GX10+GZ10+HB10+HD10+HF10+HH10+HJ10+HL10+HN10+HP10+HR10+HT10+HV10+HX10+HZ10+IB10+ID10+IF10+IH10+IJ10+IL10+IN10+IP10+IR10+IT10+IV10+IX10+IZ10+JB10+JD10+JF10+JH10+JJ10+JL10+JN10+JP10+JR10+JT10+JV10+JX10+JZ10+KB10+KD10+KF10+KH10 -> 186389 | G10: =I10+K10+M10+O10+Q10+S10+U10+W10+Y10+AA10+AC10+AE10+AG10+AI10+AK10+AM10+AO10+AQ10+AS10+AU10+AW10+AY10+BA10+BC10+BE10+BG10+BI10+BK10+BM10+BO10+BQ10+BS10+BU10+BW10+BY10+CA10+CC10+CE10+CG10+CI10+CK10+CM10+CN10+CP10+CR10+CT10+CV10+CX10+CZ10+DC10+DE10+DG10+DI10+DK10+DM10+DO10+DQ10+DS10+DU10+DW10+DY10+EA10+EC10+EE10+EG10+EI10+EK10+EM10+EO10+EQ10+ES10+EU10+EW10+EY10+FA10+FC10+FE10+FG10+FI10+FK10+FM10+FO10+FQ10+FS10+FU10+FW10+FY10+GA10+GC10+GE10+GG10+GI10+GK10+GM10+GO10+GQ10+GS10+GU10+GW10+GY10+HA10+HC10+HE10+HG10+HI10+HK10+HM10+HO10+HQ10+HS10+HU10+HW10+HY10+IA10+IC10+IE10+IG10+II10+IK10+IM10+IO10+IQ10+IS10+IU10+IW10+IY10+JA10+JC10+JE10+JG10+JI10+JK10+JM10+JO10+JQ10+JS10+JU10+JW10+JY10+KA10+KC10+KE10+KG10+KI10 -> 0 | H10: 4000 | J10: 4000 | L10: 4000 | N10: 4000 | P10: 6000 | R10: 11345 | T10: 25637 | V10: 10254 | X10: 4000 | Z10: 6000 | AB10: 6000 | AD10: 6000 | AF10: 6000 | AH10: 6000 | AJ10: 5000 | AL10: 9000 | AN10: 10000 | AP10: 20000 | AR10: 10000 | AT10: 6000 | AV10: 15000 | AX10: 6000 | AZ10: 2153
B11: ='ASE Target (Spares), FY 21-22'!A11 -> 6 | C11: ='ASE Target vs Ach(Spares)(Inpt)'!C12 -> DSL-DHK | D11: ='ASE Target vs Ach(Spares)(Inpt)'!D12 -> Md. Rakibul Hasan | E11: ='ASE Target vs Ach(Spares)(Inpt)'!E12 -> 2927 | F11: =H11+J11+L11+N11+P11+R11+T11+V11+X11+Z11+AB11+AD11+AF11+AH11+AJ11+AL11+AN11+AP11+AR11+AT11+AV11+AX11+AZ11+BB11+BD11+BF11+BH11+BJ11+BL11+BN11+BP11+BR11+BT11+BV11+BX11+BZ11+CB11+CD11+CF11+CH11+CJ11+CL11+CM11+CO11+CQ11+CS11+CU11+CW11+CY11+DB11+DD11+DF11+DH11+DJ11+DL11+DN11+DP11+DR11+DT11+DV11+DX11+DZ11+EB11+ED11+EF11+EH11+EJ11+EL11+EN11+EP11+ER11+ET11+EV11+EX11+EZ11+FB11+FD11+FF11+FH11+FJ11+FL11+FN11+FP11+FR11+FT11+FV11+FX11+FZ11+GB11+GD11+GF11+GH11+GJ11+GL11+GN11+GP11+GR11+GT11+GV11+GX11+GZ11+HB11+HD11+HF11+HH11+HJ11+HL11+HN11+HP11+HR11+HT11+HV11+HX11+HZ11+IB11+ID11+IF11+IH11+IJ11+IL11+IN11+IP11+IR11+IT11+IV11+IX11+IZ11+JB11+JD11+JF11+JH11+JJ11+JL11+JN11+JP11+JR11+JT11+JV11+JX11+JZ11+KB11+KD11+KF11+KH11 -> 184700 | G11: =I11+K11+M11+O11+Q11+S11+U11+W11+Y11+AA11+AC11+AE11+AG11+AI11+AK11+AM11+AO11+AQ11+AS11+AU11+AW11+AY11+BA11+BC11+BE11+BG11+BI11+BK11+BM11+BO11+BQ11+BS11+BU11+BW11+BY11+CA11+CC11+CE11+CG11+CI11+CK11+CM11+CN11+CP11+CR11+CT11+CV11+CX11+CZ11+DC11+DE11+DG11+DI11+DK11+DM11+DO11+DQ11+DS11+DU11+DW11+DY11+EA11+EC11+EE11+EG11+EI11+EK11+EM11+EO11+EQ11+ES11+EU11+EW11+EY11+FA11+FC11+FE11+FG11+FI11+FK11+FM11+FO11+FQ11+FS11+FU11+FW11+FY11+GA11+GC11+GE11+GG11+GI11+GK11+GM11+GO11+GQ11+GS11+GU11+GW11+GY11+HA11+HC11+HE11+HG11+HI11+HK11+HM11+HO11+HQ11+HS11+HU11+HW11+HY11+IA11+IC11+IE11+IG11+II11+IK11+IM11+IO11+IQ11+IS11+IU11+IW11+IY11+JA11+JC11+JE11+JG11+JI11+JK11+JM11+JO11+JQ11+JS11+JU11+JW11+JY11+KA11+KC11+KE11+KG11+KI11 -> 9554 | H11: 3000 | J11: 10000 | L11: 110000 | N11: 31700 | P11: 15000 | R11: 7500 | T11: 7500 | U11: 6600 | W11: 1181 | Y11: 1773
B12: ='ASE Target (Spares), FY 21-22'!A12 -> 7 | C12: ='ASE Target vs Ach(Spares)(Inpt)'!C13 -> DSL-DHK | D12: ='ASE Target vs Ach(Spares)(Inpt)'!D13 -> Md Ariful Islam | E12: ='ASE Target vs Ach(Spares)(Inpt)'!E13 -> 2699 | F12: =H12+J12+L12+N12+P12+R12+T12+V12+X12+Z12+AB12+AD12+AF12+AH12+AJ12+AL12+AN12+AP12+AR12+AT12+AV12+AX12+AZ12+BB12+BD12+BF12+BH12+BJ12+BL12+BN12+BP12+BR12+BT12+BV12+BX12+BZ12+CB12+CD12+CF12+CH12+CJ12+CL12+CM12+CO12+CQ12+CS12+CU12+CW12+CY12+DB12+DD12+DF12+DH12+DJ12+DL12+DN12+DP12+DR12+DT12+DV12+DX12+DZ12+EB12+ED12+EF12+EH12+EJ12+EL12+EN12+EP12+ER12+ET12+EV12+EX12+EZ12+FB12+FD12+FF12+FH12+FJ12+FL12+FN12+FP12+FR12+FT12+FV12+FX12+FZ12+GB12+GD12+GF12+GH12+GJ12+GL12+GN12+GP12+GR12+GT12+GV12+GX12+GZ12+HB12+HD12+HF12+HH12+HJ12+HL12+HN12+HP12+HR12+HT12+HV12+HX12+HZ12+IB12+ID12+IF12+IH12+IJ12+IL12+IN12+IP12+IR12+IT12+IV12+IX12+IZ12+JB12+JD12+JF12+JH12+JJ12+JL12+JN12+JP12+JR12+JT12+JV12+JX12+JZ12+KB12+KD12+KF12+KH12 -> 0 | G12: =I12+K12+M12+O12+Q12+S12+U12+W12+Y12+AA12+AC12+AE12+AG12+AI12+AK12+AM12+AO12+AQ12+AS12+AU12+AW12+AY12+BA12+BC12+BE12+BG12+BI12+BK12+BM12+BO12+BQ12+BS12+BU12+BW12+BY12+CA12+CC12+CE12+CG12+CI12+CK12+CM12+CN12+CP12+CR12+CT12+CV12+CX12+CZ12+DC12+DE12+DG12+DI12+DK12+DM12+DO12+DQ12+DS12+DU12+DW12+DY12+EA12+EC12+EE12+EG12+EI12+EK12+EM12+EO12+EQ12+ES12+EU12+EW12+EY12+FA12+FC12+FE12+FG12+FI12+FK12+FM12+FO12+FQ12+FS12+FU12+FW12+FY12+GA12+GC12+GE12+GG12+GI12+GK12+GM12+GO12+GQ12+GS12+GU12+GW12+GY12+HA12+HC12+HE12+HG12+HI12+HK12+HM12+HO12+HQ12+HS12+HU12+HW12+HY12+IA12+IC12+IE12+IG12+II12+IK12+IM12+IO12+IQ12+IS12+IU12+IW12+IY12+JA12+JC12+JE12+JG12+JI12+JK12+JM12+JO12+JQ12+JS12+JU12+JW12+JY12+KA12+KC12+KE12+KG12+KI12 -> 0
B13: ='ASE Target (Spares), FY 21-22'!A13 -> 8 | C13: ='ASE Target vs Ach(Spares)(Inpt)'!C14 -> DSL-DHK | D13: ='ASE Target vs Ach(Spares)(Inpt)'!D14 -> Mohammad Jewel Rana | E13: ='ASE Target vs Ach(Spares)(Inpt)'!E14 -> 3002 | F13: =H13+J13+L13+N13+P13+R13+T13+V13+X13+Z13+AB13+AD13+AF13+AH13+AJ13+AL13+AN13+AP13+AR13+AT13+AV13+AX13+AZ13+BB13+BD13+BF13+BH13+BJ13+BL13+BN13+BP13+BR13+BT13+BV13+BX13+BZ13+CB13+CD13+CF13+CH13+CJ13+CL13+CM13+CO13+CQ13+CS13+CU13+CW13+CY13+DB13+DD13+DF13+DH13+DJ13+DL13+DN13+DP13+DR13+DT13+DV13+DX13+DZ13+EB13+ED13+EF13+EH13+EJ13+EL13+EN13+EP13+ER13+ET13+EV13+EX13+EZ13+FB13+FD13+FF13+FH13+FJ13+FL13+FN13+FP13+FR13+FT13+FV13+FX13+FZ13+GB13+GD13+GF13+GH13+GJ13+GL13+GN13+GP13+GR13+GT13+GV13+GX13+GZ13+HB13+HD13+HF13+HH13+HJ13+HL13+HN13+HP13+HR13+HT13+HV13+HX13+HZ13+IB13+ID13+IF13+IH13+IJ13+IL13+IN13+IP13+IR13+IT13+IV13+IX13+IZ13+JB13+JD13+JF13+JH13+JJ13+JL13+JN13+JP13+JR13+JT13+JV13+JX13+JZ13+KB13+KD13+KF13+KH13 -> 77596 | G13: =I13+K13+M13+O13+Q13+S13+U13+W13+Y13+AA13+AC13+AE13+AG13+AI13+AK13+AM13+AO13+AQ13+AS13+AU13+AW13+AY13+BA13+BC13+BE13+BG13+BI13+BK13+BM13+BO13+BQ13+BS13+BU13+BW13+BY13+CA13+CC13+CE13+CG13+CI13+CK13+CM13+CN13+CP13+CR13+CT13+CV13+CX13+CZ13+DC13+DE13+DG13+DI13+DK13+DM13+DO13+DQ13+DS13+DU13+DW13+DY13+EA13+EC13+EE13+EG13+EI13+EK13+EM13+EO13+EQ13+ES13+EU13+EW13+EY13+FA13+FC13+FE13+FG13+FI13+FK13+FM13+FO13+FQ13+FS13+FU13+FW13+FY13+GA13+GC13+GE13+GG13+GI13+GK13+GM13+GO13+GQ13+GS13+GU13+GW13+GY13+HA13+HC13+HE13+HG13+HI13+HK13+HM13+HO13+HQ13+HS13+HU13+HW13+HY13+IA13+IC13+IE13+IG13+II13+IK13+IM13+IO13+IQ13+IS13+IU13+IW13+IY13+JA13+JC13+JE13+JG13+JI13+JK13+JM13+JO13+JQ13+JS13+JU13+JW13+JY13+KA13+KC13+KE13+KG13+KI13 -> 0 | H13: 27273 | J13: 15000 | L13: 9000 | N13: 8791 | P13: 4000 | R13: 9000 | T13: 4532
B14: ='ASE Target (Spares), FY 21-22'!A14 -> 9 | C14: ='ASE Target vs Ach(Spares)(Inpt)'!C15 -> DSL-DHK | D14: ='ASE Target vs Ach(Spares)(Inpt)'!D15 -> Faysal Ahmed | E14: ='ASE Target vs Ach(Spares)(Inpt)'!E15 -> 3004 | F14: =H14+J14+L14+N14+P14+R14+T14+V14+X14+Z14+AB14+AD14+AF14+AH14+AJ14+AL14+AN14+AP14+AR14+AT14+AV14+AX14+AZ14+BB14+BD14+BF14+BH14+BJ14+BL14+BN14+BP14+BR14+BT14+BV14+BX14+BZ14+CB14+CD14+CF14+CH14+CJ14+CL14+CM14+CO14+CQ14+CS14+CU14+CW14+CY14+DB14+DD14+DF14+DH14+DJ14+DL14+DN14+DP14+DR14+DT14+DV14+DX14+DZ14+EB14+ED14+EF14+EH14+EJ14+EL14+EN14+EP14+ER14+ET14+EV14+EX14+EZ14+FB14+FD14+FF14+FH14+FJ14+FL14+FN14+FP14+FR14+FT14+FV14+FX14+FZ14+GB14+GD14+GF14+GH14+GJ14+GL14+GN14+GP14+GR14+GT14+GV14+GX14+GZ14+HB14+HD14+HF14+HH14+HJ14+HL14+HN14+HP14+HR14+HT14+HV14+HX14+HZ14+IB14+ID14+IF14+IH14+IJ14+IL14+IN14+IP14+IR14+IT14+IV14+IX14+IZ14+JB14+JD14+JF14+JH14+JJ14+JL14+JN14+JP14+JR14+JT14+JV14+JX14+JZ14+KB14+KD14+KF14+KH14 -> 194107 | G14: =I14+K14+M14+O14+Q14+S14+U14+W14+Y14+AA14+AC14+AE14+AG14+AI14+AK14+AM14+AO14+AQ14+AS14+AU14+AW14+AY14+BA14+BC14+BE14+BG14+BI14+BK14+BM14+BO14+BQ14+BS14+BU14+BW14+BY14+CA14+CC14+CE14+CG14+CI14+CK14+CM14+CN14+CP14+CR14+CT14+CV14+CX14+CZ14+DC14+DE14+DG14+DI14+DK14+DM14+DO14+DQ14+DS14+DU14+DW14+DY14+EA14+EC14+EE14+EG14+EI14+EK14+EM14+EO14+EQ14+ES14+EU14+EW14+EY14+FA14+FC14+FE14+FG14+FI14+FK14+FM14+FO14+FQ14+FS14+FU14+FW14+FY14+GA14+GC14+GE14+GG14+GI14+GK14+GM14+GO14+GQ14+GS14+GU14+GW14+GY14+HA14+HC14+HE14+HG14+HI14+HK14+HM14+HO14+HQ14+HS14+HU14+HW14+HY14+IA14+IC14+IE14+IG14+II14+IK14+IM14+IO14+IQ14+IS14+IU14+IW14+IY14+JA14+JC14+JE14+JG14+JI14+JK14+JM14+JO14+JQ14+JS14+JU14+JW14+JY14+KA14+KC14+KE14+KG14+KI14 -> 223322 | H14: 10000 | J14: 15100 | L14: 83334 | N14: 47455 | P14: 15100 | R14: 18118 | T14: 5000 | U14: 117014 | W14: 88075 | Y14: 15250 | AA14: 1644 | AC14: 1339
B15: ='ASE Target (Spares), FY 21-22'!A15 -> 10 | C15: ='ASE Target vs Ach(Spares)(Inpt)'!C16 -> DSL-DHK | D15: ='ASE Target vs Ach(Spares)(Inpt)'!D16 -> Rakibul Islam Razib | E15: ='ASE Target vs Ach(Spares)(Inpt)'!E16 -> 3006 | F15: =H15+J15+L15+N15+P15+R15+T15+V15+X15+Z15+AB15+AD15+AF15+AH15+AJ15+AL15+AN15+AP15+AR15+AT15+AV15+AX15+AZ15+BB15+BD15+BF15+BH15+BJ15+BL15+BN15+BP15+BR15+BT15+BV15+BX15+BZ15+CB15+CD15+CF15+CH15+CJ15+CL15+CM15+CO15+CQ15+CS15+CU15+CW15+CY15+DB15+DD15+DF15+DH15+DJ15+DL15+DN15+DP15+DR15+DT15+DV15+DX15+DZ15+EB15+ED15+EF15+EH15+EJ15+EL15+EN15+EP15+ER15+ET15+EV15+EX15+EZ15+FB15+FD15+FF15+FH15+FJ15+FL15+FN15+FP15+FR15+FT15+FV15+FX15+FZ15+GB15+GD15+GF15+GH15+GJ15+GL15+GN15+GP15+GR15+GT15+GV15+GX15+GZ15+HB15+HD15+HF15+HH15+HJ15+HL15+HN15+HP15+HR15+HT15+HV15+HX15+HZ15+IB15+ID15+IF15+IH15+IJ15+IL15+IN15+IP15+IR15+IT15+IV15+IX15+IZ15+JB15+JD15+JF15+JH15+JJ15+JL15+JN15+JP15+JR15+JT15+JV15+JX15+JZ15+KB15+KD15+KF15+KH15 -> 112059 | G15: =I15+K15+M15+O15+Q15+S15+U15+W15+Y15+AA15+AC15+AE15+AG15+AI15+AK15+AM15+AO15+AQ15+AS15+AU15+AW15+AY15+BA15+BC15+BE15+BG15+BI15+BK15+BM15+BO15+BQ15+BS15+BU15+BW15+BY15+CA15+CC15+CE15+CG15+CI15+CK15+CM15+CN15+CP15+CR15+CT15+CV15+CX15+CZ15+DC15+DE15+DG15+DI15+DK15+DM15+DO15+DQ15+DS15+DU15+DW15+DY15+EA15+EC15+EE15+EG15+EI15+EK15+EM15+EO15+EQ15+ES15+EU15+EW15+EY15+FA15+FC15+FE15+FG15+FI15+FK15+FM15+FO15+FQ15+FS15+FU15+FW15+FY15+GA15+GC15+GE15+GG15+GI15+GK15+GM15+GO15+GQ15+GS15+GU15+GW15+GY15+HA15+HC15+HE15+HG15+HI15+HK15+HM15+HO15+HQ15+HS15+HU15+HW15+HY15+IA15+IC15+IE15+IG15+II15+IK15+IM15+IO15+IQ15+IS15+IU15+IW15+IY15+JA15+JC15+JE15+JG15+JI15+JK15+JM15+JO15+JQ15+JS15+JU15+JW15+JY15+KA15+KC15+KE15+KG15+KI15 -> 0 | H15: 4000 | J15: 3341 | L15: 3500 | N15: 1500 | P15: 1500 | R15: 1500 | T15: 2000 | V15: 2000 | X15: 2500 | Z15: 2500 | AB15: 2500 | AD15: 2500 | AF15: 6600 | AH15: 6600 | AJ15: 1500 | AL15: 1500 | AN15: 1500 | AP15: 1500 | AR15: 2000 | AT15: 2000 | AV15: 2000 | AX15: 2000 | AZ15: 2000 | BB15: 2000 | BD15: 2000 | BF15: 2000 | BH15: 2000 | BJ15: 2000 | BL15: 18518 | BN15: 12500 | BP15: 12500
B16: ='ASE Target (Spares), FY 21-22'!A9 -> 4 | C16: ='ASE Target vs Ach(Spares)(Inpt)'!C17 -> DSL-DHK | D16: ='ASE Target vs Ach(Spares)(Inpt)'!D17 -> Ashraful Islam | E16: ='ASE Target vs Ach(Spares)(Inpt)'!E17 -> 3003 | F16: =H16+J16+L16+N16+P16+R16+T16+V16+X16+Z16+AB16+AD16+AF16+AH16+AJ16+AL16+AN16+AP16+AR16+AT16+AV16+AX16+AZ16+BB16+BD16+BF16+BH16+BJ16+BL16+BN16+BP16+BR16+BT16+BV16+BX16+BZ16+CB16+CD16+CF16+CH16+CJ16+CL16+CM16+CO16+CQ16+CS16+CU16+CW16+CY16+DB16+DD16+DF16+DH16+DJ16+DL16+DN16+DP16+DR16+DT16+DV16+DX16+DZ16+EB16+ED16+EF16+EH16+EJ16+EL16+EN16+EP16+ER16+ET16+EV16+EX16+EZ16+FB16+FD16+FF16+FH16+FJ16+FL16+FN16+FP16+FR16+FT16+FV16+FX16+FZ16+GB16+GD16+GF16+GH16+GJ16+GL16+GN16+GP16+GR16+GT16+GV16+GX16+GZ16+HB16+HD16+HF16+HH16+HJ16+HL16+HN16+HP16+HR16+HT16+HV16+HX16+HZ16+IB16+ID16+IF16+IH16+IJ16+IL16+IN16+IP16+IR16+IT16+IV16+IX16+IZ16+JB16+JD16+JF16+JH16+JJ16+JL16+JN16+JP16+JR16+JT16+JV16+JX16+JZ16+KB16+KD16+KF16+KH16 -> 259519 | G16: =I16+K16+M16+O16+Q16+S16+U16+W16+Y16+AA16+AC16+AE16+AG16+AI16+AK16+AM16+AO16+AQ16+AS16+AU16+AW16+AY16+BA16+BC16+BE16+BG16+BI16+BK16+BM16+BO16+BQ16+BS16+BU16+BW16+BY16+CA16+CC16+CE16+CG16+CI16+CK16+CM16+CN16+CP16+CR16+CT16+CV16+CX16+CZ16+DC16+DE16+DG16+DI16+DK16+DM16+DO16+DQ16+DS16+DU16+DW16+DY16+EA16+EC16+EE16+EG16+EI16+EK16+EM16+EO16+EQ16+ES16+EU16+EW16+EY16+FA16+FC16+FE16+FG16+FI16+FK16+FM16+FO16+FQ16+FS16+FU16+FW16+FY16+GA16+GC16+GE16+GG16+GI16+GK16+GM16+GO16+GQ16+GS16+GU16+GW16+GY16+HA16+HC16+HE16+HG16+HI16+HK16+HM16+HO16+HQ16+HS16+HU16+HW16+HY16+IA16+IC16+IE16+IG16+II16+IK16+IM16+IO16+IQ16+IS16+IU16+IW16+IY16+JA16+JC16+JE16+JG16+JI16+JK16+JM16+JO16+JQ16+JS16+JU16+JW16+JY16+KA16+KC16+KE16+KG16+KI16 -> 0 | H16: 15000 | J16: 100000 | L16: 18684 | N16: 10000 | P16: 58407 | R16: 15520 | T16: 7652 | V16: 2604 | X16: 3907 | Z16: 5972 | AB16: 2389 | AD16: 1182 | AF16: 5046 | AH16: 5046 | AJ16: 8110
B17: ='ASE Target (Spares), FY 21-22'!A10 -> 5 | C17: ='ASE Target vs Ach(Spares)(Inpt)'!C18 -> DSL-DHK | D17: ='ASE Target vs Ach(Spares)(Inpt)'!D18 -> Md. Rakibul Islam | E17: ='ASE Target vs Ach(Spares)(Inpt)'!E18 -> 5690 | F17: =H17+J17+L17+N17+P17+R17+T17+V17+X17+Z17+AB17+AD17+AF17+AH17+AJ17+AL17+AN17+AP17+AR17+AT17+AV17+AX17+AZ17+BB17+BD17+BF17+BH17+BJ17+BL17+BN17+BP17+BR17+BT17+BV17+BX17+BZ17+CB17+CD17+CF17+CH17+CJ17+CL17+CM17+CO17+CQ17+CS17+CU17+CW17+CY17+DB17+DD17+DF17+DH17+DJ17+DL17+DN17+DP17+DR17+DT17+DV17+DX17+DZ17+EB17+ED17+EF17+EH17+EJ17+EL17+EN17+EP17+ER17+ET17+EV17+EX17+EZ17+FB17+FD17+FF17+FH17+FJ17+FL17+FN17+FP17+FR17+FT17+FV17+FX17+FZ17+GB17+GD17+GF17+GH17+GJ17+GL17+GN17+GP17+GR17+GT17+GV17+GX17+GZ17+HB17+HD17+HF17+HH17+HJ17+HL17+HN17+HP17+HR17+HT17+HV17+HX17+HZ17+IB17+ID17+IF17+IH17+IJ17+IL17+IN17+IP17+IR17+IT17+IV17+IX17+IZ17+JB17+JD17+JF17+JH17+JJ17+JL17+JN17+JP17+JR17+JT17+JV17+JX17+JZ17+KB17+KD17+KF17+KH17 -> 0 | G17: =I17+K17+M17+O17+Q17+S17+U17+W17+Y17+AA17+AC17+AE17+AG17+AI17+AK17+AM17+AO17+AQ17+AS17+AU17+AW17+AY17+BA17+BC17+BE17+BG17+BI17+BK17+BM17+BO17+BQ17+BS17+BU17+BW17+BY17+CA17+CC17+CE17+CG17+CI17+CK17+CM17+CN17+CP17+CR17+CT17+CV17+CX17+CZ17+DC17+DE17+DG17+DI17+DK17+DM17+DO17+DQ17+DS17+DU17+DW17+DY17+EA17+EC17+EE17+EG17+EI17+EK17+EM17+EO17+EQ17+ES17+EU17+EW17+EY17+FA17+FC17+FE17+FG17+FI17+FK17+FM17+FO17+FQ17+FS17+FU17+FW17+FY17+GA17+GC17+GE17+GG17+GI17+GK17+GM17+GO17+GQ17+GS17+GU17+GW17+GY17+HA17+HC17+HE17+HG17+HI17+HK17+HM17+HO17+HQ17+HS17+HU17+HW17+HY17+IA17+IC17+IE17+IG17+II17+IK17+IM17+IO17+IQ17+IS17+IU17+IW17+IY17+JA17+JC17+JE17+JG17+JI17+JK17+JM17+JO17+JQ17+JS17+JU17+JW17+JY17+KA17+KC17+KE17+KG17+KI17 -> 0
B18: ='ASE Target (Spares), FY 21-22'!A11 -> 6 | C18: ='ASE Target vs Ach(Spares)(Inpt)'!C19 -> DSL-DHK | D18: ='ASE Target vs Ach(Spares)(Inpt)'!D19 -> Ohid Hasan Saikat | E18: ='ASE Target vs Ach(Spares)(Inpt)'!E19 -> 5691 | F18: =H18+J18+L18+N18+P18+R18+T18+V18+X18+Z18+AB18+AD18+AF18+AH18+AJ18+AL18+AN18+AP18+AR18+AT18+AV18+AX18+AZ18+BB18+BD18+BF18+BH18+BJ18+BL18+BN18+BP18+BR18+BT18+BV18+BX18+BZ18+CB18+CD18+CF18+CH18+CJ18+CL18+CM18+CO18+CQ18+CS18+CU18+CW18+CY18+DB18+DD18+DF18+DH18+DJ18+DL18+DN18+DP18+DR18+DT18+DV18+DX18+DZ18+EB18+ED18+EF18+EH18+EJ18+EL18+EN18+EP18+ER18+ET18+EV18+EX18+EZ18+FB18+FD18+FF18+FH18+FJ18+FL18+FN18+FP18+FR18+FT18+FV18+FX18+FZ18+GB18+GD18+GF18+GH18+GJ18+GL18+GN18+GP18+GR18+GT18+GV18+GX18+GZ18+HB18+HD18+HF18+HH18+HJ18+HL18+HN18+HP18+HR18+HT18+HV18+HX18+HZ18+IB18+ID18+IF18+IH18+IJ18+IL18+IN18+IP18+IR18+IT18+IV18+IX18+IZ18+JB18+JD18+JF18+JH18+JJ18+JL18+JN18+JP18+JR18+JT18+JV18+JX18+JZ18+KB18+KD18+KF18+KH18 -> 293913 | G18: =I18+K18+M18+O18+Q18+S18+U18+W18+Y18+AA18+AC18+AE18+AG18+AI18+AK18+AM18+AO18+AQ18+AS18+AU18+AW18+AY18+BA18+BC18+BE18+BG18+BI18+BK18+BM18+BO18+BQ18+BS18+BU18+BW18+BY18+CA18+CC18+CE18+CG18+CI18+CK18+CM18+CN18+CP18+CR18+CT18+CV18+CX18+CZ18+DC18+DE18+DG18+DI18+DK18+DM18+DO18+DQ18+DS18+DU18+DW18+DY18+EA18+EC18+EE18+EG18+EI18+EK18+EM18+EO18+EQ18+ES18+EU18+EW18+EY18+FA18+FC18+FE18+FG18+FI18+FK18+FM18+FO18+FQ18+FS18+FU18+FW18+FY18+GA18+GC18+GE18+GG18+GI18+GK18+GM18+GO18+GQ18+GS18+GU18+GW18+GY18+HA18+HC18+HE18+HG18+HI18+HK18+HM18+HO18+HQ18+HS18+HU18+HW18+HY18+IA18+IC18+IE18+IG18+II18+IK18+IM18+IO18+IQ18+IS18+IU18+IW18+IY18+JA18+JC18+JE18+JG18+JI18+JK18+JM18+JO18+JQ18+JS18+JU18+JW18+JY18+KA18+KC18+KE18+KG18+KI18 -> 12830 | H18: 6000 | J18: 2000 | L18: 1500 | N18: 1250 | P18: 2500 | R18: 2500 | T18: 3750 | V18: 1636 | X18: 1636 | Z18: 1636 | AB18: 3626 | AD18: 3300 | AF18: 97209 | AH18: 100000 | AJ18: 9000 | AL18: 2500 | AN18: 2273 | AP18: 2273 | AR18: 2273 | AT18: 4545 | AV18: 5550 | AX18: 6000 | AZ18: 6000 | BB18: 11748 | BD18: 4308 | BF18: 4900 | BH18: 4000 | BI18: 1716 | BK18: 9750 | BM18: 1364
B19: ='ASE Target (Spares), FY 21-22'!A12 -> 7 | C19: ='ASE Target vs Ach(Spares)(Inpt)'!C20 -> DSL-DHK | D19: ='ASE Target vs Ach(Spares)(Inpt)'!D20 -> Abdullah Al Mahmud | E19: ='ASE Target vs Ach(Spares)(Inpt)'!E20 -> 5692 | F19: =H19+J19+L19+N19+P19+R19+T19+V19+X19+Z19+AB19+AD19+AF19+AH19+AJ19+AL19+AN19+AP19+AR19+AT19+AV19+AX19+AZ19+BB19+BD19+BF19+BH19+BJ19+BL19+BN19+BP19+BR19+BT19+BV19+BX19+BZ19+CB19+CD19+CF19+CH19+CJ19+CL19+CM19+CO19+CQ19+CS19+CU19+CW19+CY19+DB19+DD19+DF19+DH19+DJ19+DL19+DN19+DP19+DR19+DT19+DV19+DX19+DZ19+EB19+ED19+EF19+EH19+EJ19+EL19+EN19+EP19+ER19+ET19+EV19+EX19+EZ19+FB19+FD19+FF19+FH19+FJ19+FL19+FN19+FP19+FR19+FT19+FV19+FX19+FZ19+GB19+GD19+GF19+GH19+GJ19+GL19+GN19+GP19+GR19+GT19+GV19+GX19+GZ19+HB19+HD19+HF19+HH19+HJ19+HL19+HN19+HP19+HR19+HT19+HV19+HX19+HZ19+IB19+ID19+IF19+IH19+IJ19+IL19+IN19+IP19+IR19+IT19+IV19+IX19+IZ19+JB19+JD19+JF19+JH19+JJ19+JL19+JN19+JP19+JR19+JT19+JV19+JX19+JZ19+KB19+KD19+KF19+KH19 -> 74600 | G19: =I19+K19+M19+O19+Q19+S19+U19+W19+Y19+AA19+AC19+AE19+AG19+AI19+AK19+AM19+AO19+AQ19+AS19+AU19+AW19+AY19+BA19+BC19+BE19+BG19+BI19+BK19+BM19+BO19+BQ19+BS19+BU19+BW19+BY19+CA19+CC19+CE19+CG19+CI19+CK19+CM19+CN19+CP19+CR19+CT19+CV19+CX19+CZ19+DC19+DE19+DG19+DI19+DK19+DM19+DO19+DQ19+DS19+DU19+DW19+DY19+EA19+EC19+EE19+EG19+EI19+EK19+EM19+EO19+EQ19+ES19+EU19+EW19+EY19+FA19+FC19+FE19+FG19+FI19+FK19+FM19+FO19+FQ19+FS19+FU19+FW19+FY19+GA19+GC19+GE19+GG19+GI19+GK19+GM19+GO19+GQ19+GS19+GU19+GW19+GY19+HA19+HC19+HE19+HG19+HI19+HK19+HM19+HO19+HQ19+HS19+HU19+HW19+HY19+IA19+IC19+IE19+IG19+II19+IK19+IM19+IO19+IQ19+IS19+IU19+IW19+IY19+JA19+JC19+JE19+JG19+JI19+JK19+JM19+JO19+JQ19+JS19+JU19+JW19+JY19+KA19+KC19+KE19+KG19+KI19 -> 0 | H19: 1500 | J19: 4800 | L19: 1600 | N19: 1600 | P19: 1600 | R19: 3500 | T19: 7500 | V19: 7500 | X19: 9000 | Z19: 3000 | AB19: 3000 | AD19: 3000 | AF19: 3000 | AH19: 3000 | AJ19: 3000 | AL19: 3000 | AN19: 3000 | AP19: 3000 | AR19: 6000 | AT19: 3000
B20: ='ASE Target (Spares), FY 21-22'!A13 -> 8 | C20: ='ASE Target vs Ach(Spares)(Inpt)'!C21 -> DSL-DHK | D20: ='ASE Target vs Ach(Spares)(Inpt)'!D21 -> Apurba Kumar Gain | E20: ='ASE Target vs Ach(Spares)(Inpt)'!E21 -> 5927 | F20: =H20+J20+L20+N20+P20+R20+T20+V20+X20+Z20+AB20+AD20+AF20+AH20+AJ20+AL20+AN20+AP20+AR20+AT20+AV20+AX20+AZ20+BB20+BD20+BF20+BH20+BJ20+BL20+BN20+BP20+BR20+BT20+BV20+BX20+BZ20+CB20+CD20+CF20+CH20+CJ20+CL20+CM20+CO20+CQ20+CS20+CU20+CW20+CY20+DB20+DD20+DF20+DH20+DJ20+DL20+DN20+DP20+DR20+DT20+DV20+DX20+DZ20+EB20+ED20+EF20+EH20+EJ20+EL20+EN20+EP20+ER20+ET20+EV20+EX20+EZ20+FB20+FD20+FF20+FH20+FJ20+FL20+FN20+FP20+FR20+FT20+FV20+FX20+FZ20+GB20+GD20+GF20+GH20+GJ20+GL20+GN20+GP20+GR20+GT20+GV20+GX20+GZ20+HB20+HD20+HF20+HH20+HJ20+HL20+HN20+HP20+HR20+HT20+HV20+HX20+HZ20+IB20+ID20+IF20+IH20+IJ20+IL20+IN20+IP20+IR20+IT20+IV20+IX20+IZ20+JB20+JD20+JF20+JH20+JJ20+JL20+JN20+JP20+JR20+JT20+JV20+JX20+JZ20+KB20+KD20+KF20+KH20 -> 64300 | G20: =I20+K20+M20+O20+Q20+S20+U20+W20+Y20+AA20+AC20+AE20+AG20+AI20+AK20+AM20+AO20+AQ20+AS20+AU20+AW20+AY20+BA20+BC20+BE20+BG20+BI20+BK20+BM20+BO20+BQ20+BS20+BU20+BW20+BY20+CA20+CC20+CE20+CG20+CI20+CK20+CM20+CN20+CP20+CR20+CT20+CV20+CX20+CZ20+DC20+DE20+DG20+DI20+DK20+DM20+DO20+DQ20+DS20+DU20+DW20+DY20+EA20+EC20+EE20+EG20+EI20+EK20+EM20+EO20+EQ20+ES20+EU20+EW20+EY20+FA20+FC20+FE20+FG20+FI20+FK20+FM20+FO20+FQ20+FS20+FU20+FW20+FY20+GA20+GC20+GE20+GG20+GI20+GK20+GM20+GO20+GQ20+GS20+GU20+GW20+GY20+HA20+HC20+HE20+HG20+HI20+HK20+HM20+HO20+HQ20+HS20+HU20+HW20+HY20+IA20+IC20+IE20+IG20+II20+IK20+IM20+IO20+IQ20+IS20+IU20+IW20+IY20+JA20+JC20+JE20+JG20+JI20+JK20+JM20+JO20+JQ20+JS20+JU20+JW20+JY20+KA20+KC20+KE20+KG20+KI20 -> 0 | H20: 6000 | J20: 4000 | L20: 2500 | N20: 15000 | P20: 5000 | R20: 2000 | T20: 2000 | V20: 3000 | X20: 6000 | Z20: 1800 | AB20: 1500 | AD20: 1500 | AF20: 5000 | AH20: 9000
B21: ='ASE Target (Spares), FY 21-22'!A14 -> 9 | C21: ='ASE Target vs Ach(Spares)(Inpt)'!C22 -> DSL-DHK | D21: ='ASE Target vs Ach(Spares)(Inpt)'!D22 -> Amirul Islam | E21: ='ASE Target vs Ach(Spares)(Inpt)'!E22 -> 5928 | F21: =H21+J21+L21+N21+P21+R21+T21+V21+X21+Z21+AB21+AD21+AF21+AH21+AJ21+AL21+AN21+AP21+AR21+AT21+AV21+AX21+AZ21+BB21+BD21+BF21+BH21+BJ21+BL21+BN21+BP21+BR21+BT21+BV21+BX21+BZ21+CB21+CD21+CF21+CH21+CJ21+CL21+CM21+CO21+CQ21+CS21+CU21+CW21+CY21+DB21+DD21+DF21+DH21+DJ21+DL21+DN21+DP21+DR21+DT21+DV21+DX21+DZ21+EB21+ED21+EF21+EH21+EJ21+EL21+EN21+EP21+ER21+ET21+EV21+EX21+EZ21+FB21+FD21+FF21+FH21+FJ21+FL21+FN21+FP21+FR21+FT21+FV21+FX21+FZ21+GB21+GD21+GF21+GH21+GJ21+GL21+GN21+GP21+GR21+GT21+GV21+GX21+GZ21+HB21+HD21+HF21+HH21+HJ21+HL21+HN21+HP21+HR21+HT21+HV21+HX21+HZ21+IB21+ID21+IF21+IH21+IJ21+IL21+IN21+IP21+IR21+IT21+IV21+IX21+IZ21+JB21+JD21+JF21+JH21+JJ21+JL21+JN21+JP21+JR21+JT21+JV21+JX21+JZ21+KB21+KD21+KF21+KH21 -> 58900 | G21: =I21+K21+M21+O21+Q21+S21+U21+W21+Y21+AA21+AC21+AE21+AG21+AI21+AK21+AM21+AO21+AQ21+AS21+AU21+AW21+AY21+BA21+BC21+BE21+BG21+BI21+BK21+BM21+BO21+BQ21+BS21+BU21+BW21+BY21+CA21+CC21+CE21+CG21+CI21+CK21+CM21+CN21+CP21+CR21+CT21+CV21+CX21+CZ21+DC21+DE21+DG21+DI21+DK21+DM21+DO21+DQ21+DS21+DU21+DW21+DY21+EA21+EC21+EE21+EG21+EI21+EK21+EM21+EO21+EQ21+ES21+EU21+EW21+EY21+FA21+FC21+FE21+FG21+FI21+FK21+FM21+FO21+FQ21+FS21+FU21+FW21+FY21+GA21+GC21+GE21+GG21+GI21+GK21+GM21+GO21+GQ21+GS21+GU21+GW21+GY21+HA21+HC21+HE21+HG21+HI21+HK21+HM21+HO21+HQ21+HS21+HU21+HW21+HY21+IA21+IC21+IE21+IG21+II21+IK21+IM21+IO21+IQ21+IS21+IU21+IW21+IY21+JA21+JC21+JE21+JG21+JI21+JK21+JM21+JO21+JQ21+JS21+JU21+JW21+JY21+KA21+KC21+KE21+KG21+KI21 -> 0 | H21: 6000 | J21: 3000 | L21: 3000 | N21: 2000 | P21: 1500 | R21: 1500 | T21: 5000 | V21: 5400 | X21: 2000 | Z21: 1500 | AB21: 3000 | AD21: 5000 | AF21: 500 | AH21: 3000 | AJ21: 1500 | AL21: 1500 | AN21: 1500 | AP21: 1500 | AR21: 1500 | AT21: 4500 | AV21: 4500
B22: ='ASE Target (Spares), FY 21-22'!A21 -> 16 | C22: ='ASE Target vs Ach(Spares)(Inpt)'!C23 -> DSL-DHK | D22: ='ASE Target vs Ach(Spares)(Inpt)'!D23 -> Md. Jafor Ikbal | E22: ='ASE Target vs Ach(Spares)(Inpt)'!E23 -> 5929 | F22: =H22+J22+L22+N22+P22+R22+T22+V22+X22+Z22+AB22+AD22+AF22+AH22+AJ22+AL22+AN22+AP22+AR22+AT22+AV22+AX22+AZ22+BB22+BD22+BF22+BH22+BJ22+BL22+BN22+BP22+BR22+BT22+BV22+BX22+BZ22+CB22+CD22+CF22+CH22+CJ22+CL22+CM22+CO22+CQ22+CS22+CU22+CW22+CY22+DB22+DD22+DF22+DH22+DJ22+DL22+DN22+DP22+DR22+DT22+DV22+DX22+DZ22+EB22+ED22+EF22+EH22+EJ22+EL22+EN22+EP22+ER22+ET22+EV22+EX22+EZ22+FB22+FD22+FF22+FH22+FJ22+FL22+FN22+FP22+FR22+FT22+FV22+FX22+FZ22+GB22+GD22+GF22+GH22+GJ22+GL22+GN22+GP22+GR22+GT22+GV22+GX22+GZ22+HB22+HD22+HF22+HH22+HJ22+HL22+HN22+HP22+HR22+HT22+HV22+HX22+HZ22+IB22+ID22+IF22+IH22+IJ22+IL22+IN22+IP22+IR22+IT22+IV22+IX22+IZ22+JB22+JD22+JF22+JH22+JJ22+JL22+JN22+JP22+JR22+JT22+JV22+JX22+JZ22+KB22+KD22+KF22+KH22 -> 324166 | G22: =I22+K22+M22+O22+Q22+S22+U22+W22+Y22+AA22+AC22+AE22+AG22+AI22+AK22+AM22+AO22+AQ22+AS22+AU22+AW22+AY22+BA22+BC22+BE22+BG22+BI22+BK22+BM22+BO22+BQ22+BS22+BU22+BW22+BY22+CA22+CC22+CE22+CG22+CI22+CK22+CM22+CN22+CP22+CR22+CT22+CV22+CX22+CZ22+DC22+DE22+DG22+DI22+DK22+DM22+DO22+DQ22+DS22+DU22+DW22+DY22+EA22+EC22+EE22+EG22+EI22+EK22+EM22+EO22+EQ22+ES22+EU22+EW22+EY22+FA22+FC22+FE22+FG22+FI22+FK22+FM22+FO22+FQ22+FS22+FU22+FW22+FY22+GA22+GC22+GE22+GG22+GI22+GK22+GM22+GO22+GQ22+GS22+GU22+GW22+GY22+HA22+HC22+HE22+HG22+HI22+HK22+HM22+HO22+HQ22+HS22+HU22+HW22+HY22+IA22+IC22+IE22+IG22+II22+IK22+IM22+IO22+IQ22+IS22+IU22+IW22+IY22+JA22+JC22+JE22+JG22+JI22+JK22+JM22+JO22+JQ22+JS22+JU22+JW22+JY22+KA22+KC22+KE22+KG22+KI22 -> 360094 | H22: 6000 | J22: 8000 | K22: 3140 | L22: 24348 | M22: 36363 | N22: 16000 | P22: 8000 | Q22: 34546 | S22: 33333 | T22: 26000 | V22: 8000 | W22: 16947 | Y22: 31818 | Z22: 149591 | AB22: 4000 | AD22: 4000 | AF22: 4000 | AG22: 5455 | AH22: 43000 | AI22: 2400 | AK22: 31818 | AM22: 638 | AN22: 9000 | AP22: 9818 | AR22: 4409 | AS22: 163636
B23: ='ASE Target (Spares), FY 21-22'!A16 -> 11 | C23: ='ASE Target vs Ach(Spares)(Inpt)'!C24 -> DSL-DHK | D23: ='ASE Target vs Ach(Spares)(Inpt)'!D24 -> Md. Habibur Rahman | E23: ='ASE Target vs Ach(Spares)(Inpt)'!E24 -> 6079 | F23: =H23+J23+L23+N23+P23+R23+T23+V23+X23+Z23+AB23+AD23+AF23+AH23+AJ23+AL23+AN23+AP23+AR23+AT23+AV23+AX23+AZ23+BB23+BD23+BF23+BH23+BJ23+BL23+BN23+BP23+BR23+BT23+BV23+BX23+BZ23+CB23+CD23+CF23+CH23+CJ23+CL23+CM23+CO23+CQ23+CS23+CU23+CW23+CY23+DB23+DD23+DF23+DH23+DJ23+DL23+DN23+DP23+DR23+DT23+DV23+DX23+DZ23+EB23+ED23+EF23+EH23+EJ23+EL23+EN23+EP23+ER23+ET23+EV23+EX23+EZ23+FB23+FD23+FF23+FH23+FJ23+FL23+FN23+FP23+FR23+FT23+FV23+FX23+FZ23+GB23+GD23+GF23+GH23+GJ23+GL23+GN23+GP23+GR23+GT23+GV23+GX23+GZ23+HB23+HD23+HF23+HH23+HJ23+HL23+HN23+HP23+HR23+HT23+HV23+HX23+HZ23+IB23+ID23+IF23+IH23+IJ23+IL23+IN23+IP23+IR23+IT23+IV23+IX23+IZ23+JB23+JD23+JF23+JH23+JJ23+JL23+JN23+JP23+JR23+JT23+JV23+JX23+JZ23+KB23+KD23+KF23+KH23 -> 0 | G23: =I23+K23+M23+O23+Q23+S23+U23+W23+Y23+AA23+AC23+AE23+AG23+AI23+AK23+AM23+AO23+AQ23+AS23+AU23+AW23+AY23+BA23+BC23+BE23+BG23+BI23+BK23+BM23+BO23+BQ23+BS23+BU23+BW23+BY23+CA23+CC23+CE23+CG23+CI23+CK23+CM23+CN23+CP23+CR23+CT23+CV23+CX23+CZ23+DC23+DE23+DG23+DI23+DK23+DM23+DO23+DQ23+DS23+DU23+DW23+DY23+EA23+EC23+EE23+EG23+EI23+EK23+EM23+EO23+EQ23+ES23+EU23+EW23+EY23+FA23+FC23+FE23+FG23+FI23+FK23+FM23+FO23+FQ23+FS23+FU23+FW23+FY23+GA23+GC23+GE23+GG23+GI23+GK23+GM23+GO23+GQ23+GS23+GU23+GW23+GY23+HA23+HC23+HE23+HG23+HI23+HK23+HM23+HO23+HQ23+HS23+HU23+HW23+HY23+IA23+IC23+IE23+IG23+II23+IK23+IM23+IO23+IQ23+IS23+IU23+IW23+IY23+JA23+JC23+JE23+JG23+JI23+JK23+JM23+JO23+JQ23+JS23+JU23+JW23+JY23+KA23+KC23+KE23+KG23+KI23 -> 8110 | I23: 8110
B24: ='ASE Target (Spares), FY 21-22'!A17 -> 12 | C24: ='ASE Target vs Ach(Spares)(Inpt)'!C25 -> DSL-DHK | D24: ='ASE Target vs Ach(Spares)(Inpt)'!D25 -> Ashikur Rahman | E24: ='ASE Target vs Ach(Spares)(Inpt)'!E25 -> 6080 | F24: =H24+J24+L24+N24+P24+R24+T24+V24+X24+Z24+AB24+AD24+AF24+AH24+AJ24+AL24+AN24+AP24+AR24+AT24+AV24+AX24+AZ24+BB24+BD24+BF24+BH24+BJ24+BL24+BN24+BP24+BR24+BT24+BV24+BX24+BZ24+CB24+CD24+CF24+CH24+CJ24+CL24+CM24+CO24+CQ24+CS24+CU24+CW24+CY24+DB24+DD24+DF24+DH24+DJ24+DL24+DN24+DP24+DR24+DT24+DV24+DX24+DZ24+EB24+ED24+EF24+EH24+EJ24+EL24+EN24+EP24+ER24+ET24+EV24+EX24+EZ24+FB24+FD24+FF24+FH24+FJ24+FL24+FN24+FP24+FR24+FT24+FV24+FX24+FZ24+GB24+GD24+GF24+GH24+GJ24+GL24+GN24+GP24+GR24+GT24+GV24+GX24+GZ24+HB24+HD24+HF24+HH24+HJ24+HL24+HN24+HP24+HR24+HT24+HV24+HX24+HZ24+IB24+ID24+IF24+IH24+IJ24+IL24+IN24+IP24+IR24+IT24+IV24+IX24+IZ24+JB24+JD24+JF24+JH24+JJ24+JL24+JN24+JP24+JR24+JT24+JV24+JX24+JZ24+KB24+KD24+KF24+KH24 -> 250830 | G24: =I24+K24+M24+O24+Q24+S24+U24+W24+Y24+AA24+AC24+AE24+AG24+AI24+AK24+AM24+AO24+AQ24+AS24+AU24+AW24+AY24+BA24+BC24+BE24+BG24+BI24+BK24+BM24+BO24+BQ24+BS24+BU24+BW24+BY24+CA24+CC24+CE24+CG24+CI24+CK24+CM24+CN24+CP24+CR24+CT24+CV24+CX24+CZ24+DC24+DE24+DG24+DI24+DK24+DM24+DO24+DQ24+DS24+DU24+DW24+DY24+EA24+EC24+EE24+EG24+EI24+EK24+EM24+EO24+EQ24+ES24+EU24+EW24+EY24+FA24+FC24+FE24+FG24+FI24+FK24+FM24+FO24+FQ24+FS24+FU24+FW24+FY24+GA24+GC24+GE24+GG24+GI24+GK24+GM24+GO24+GQ24+GS24+GU24+GW24+GY24+HA24+HC24+HE24+HG24+HI24+HK24+HM24+HO24+HQ24+HS24+HU24+HW24+HY24+IA24+IC24+IE24+IG24+II24+IK24+IM24+IO24+IQ24+IS24+IU24+IW24+IY24+JA24+JC24+JE24+JG24+JI24+JK24+JM24+JO24+JQ24+JS24+JU24+JW24+JY24+KA24+KC24+KE24+KG24+KI24 -> 0 | H24: 10000 | J24: 11000 | L24: 9408 | N24: 9410 | P24: 10800 | R24: 8859 | T24: 66441 | V24: 62013 | X24: 13288 | Z24: 8859 | AB24: 8859 | AD24: 10631 | AF24: 10631 | AH24: 10631
B25: ='ASE Target (Spares), FY 21-22'!A18 -> 13 | C25: ='ASE Target vs Ach(Spares)(Inpt)'!C26 -> DSL-DHK | D25: ='ASE Target vs Ach(Spares)(Inpt)'!D26 -> Md. Sujon Hossain | E25: ='ASE Target vs Ach(Spares)(Inpt)'!E26 -> 6078 | F25: =H25+J25+L25+N25+P25+R25+T25+V25+X25+Z25+AB25+AD25+AF25+AH25+AJ25+AL25+AN25+AP25+AR25+AT25+AV25+AX25+AZ25+BB25+BD25+BF25+BH25+BJ25+BL25+BN25+BP25+BR25+BT25+BV25+BX25+BZ25+CB25+CD25+CF25+CH25+CJ25+CL25+CM25+CO25+CQ25+CS25+CU25+CW25+CY25+DB25+DD25+DF25+DH25+DJ25+DL25+DN25+DP25+DR25+DT25+DV25+DX25+DZ25+EB25+ED25+EF25+EH25+EJ25+EL25+EN25+EP25+ER25+ET25+EV25+EX25+EZ25+FB25+FD25+FF25+FH25+FJ25+FL25+FN25+FP25+FR25+FT25+FV25+FX25+FZ25+GB25+GD25+GF25+GH25+GJ25+GL25+GN25+GP25+GR25+GT25+GV25+GX25+GZ25+HB25+HD25+HF25+HH25+HJ25+HL25+HN25+HP25+HR25+HT25+HV25+HX25+HZ25+IB25+ID25+IF25+IH25+IJ25+IL25+IN25+IP25+IR25+IT25+IV25+IX25+IZ25+JB25+JD25+JF25+JH25+JJ25+JL25+JN25+JP25+JR25+JT25+JV25+JX25+JZ25+KB25+KD25+KF25+KH25 -> 274343 | G25: =I25+K25+M25+O25+Q25+S25+U25+W25+Y25+AA25+AC25+AE25+AG25+AI25+AK25+AM25+AO25+AQ25+AS25+AU25+AW25+AY25+BA25+BC25+BE25+BG25+BI25+BK25+BM25+BO25+BQ25+BS25+BU25+BW25+BY25+CA25+CC25+CE25+CG25+CI25+CK25+CM25+CN25+CP25+CR25+CT25+CV25+CX25+CZ25+DC25+DE25+DG25+DI25+DK25+DM25+DO25+DQ25+DS25+DU25+DW25+DY25+EA25+EC25+EE25+EG25+EI25+EK25+EM25+EO25+EQ25+ES25+EU25+EW25+EY25+FA25+FC25+FE25+FG25+FI25+FK25+FM25+FO25+FQ25+FS25+FU25+FW25+FY25+GA25+GC25+GE25+GG25+GI25+GK25+GM25+GO25+GQ25+GS25+GU25+GW25+GY25+HA25+HC25+HE25+HG25+HI25+HK25+HM25+HO25+HQ25+HS25+HU25+HW25+HY25+IA25+IC25+IE25+IG25+II25+IK25+IM25+IO25+IQ25+IS25+IU25+IW25+IY25+JA25+JC25+JE25+JG25+JI25+JK25+JM25+JO25+JQ25+JS25+JU25+JW25+JY25+KA25+KC25+KE25+KG25+KI25 -> 0 | H25: 12818 | J25: 10800 | L25: 10800 | N25: 10800 | P25: 10800 | R25: 10800 | T25: 10800 | V25: 10000 | X25: 10000 | Z25: 10000 | AB25: 13000 | AD25: 13000 | AF25: 12818 | AH25: 12818 | AJ25: 12818 | AL25: 12818 | AN25: 12818 | AP25: 12818 | AR25: 12818 | AT25: 13000 | AV25: 12818 | AX25: 8181 | AZ25: 8500 | BB25: 8500
B26: ='ASE Target (Spares), FY 21-22'!A19 -> 14 | C26: ='ASE Target vs Ach(Spares)(Inpt)'!C27 -> DSL-DHK | D26: ='ASE Target vs Ach(Spares)(Inpt)'!D27 -> Md Jiaur Rahman | E26: ='ASE Target vs Ach(Spares)(Inpt)'!E27 -> 0522 | F26: =H26+J26+L26+N26+P26+R26+T26+V26+X26+Z26+AB26+AD26+AF26+AH26+AJ26+AL26+AN26+AP26+AR26+AT26+AV26+AX26+AZ26+BB26+BD26+BF26+BH26+BJ26+BL26+BN26+BP26+BR26+BT26+BV26+BX26+BZ26+CB26+CD26+CF26+CH26+CJ26+CL26+CM26+CO26+CQ26+CS26+CU26+CW26+CY26+DB26+DD26+DF26+DH26+DJ26+DL26+DN26+DP26+DR26+DT26+DV26+DX26+DZ26+EB26+ED26+EF26+EH26+EJ26+EL26+EN26+EP26+ER26+ET26+EV26+EX26+EZ26+FB26+FD26+FF26+FH26+FJ26+FL26+FN26+FP26+FR26+FT26+FV26+FX26+FZ26+GB26+GD26+GF26+GH26+GJ26+GL26+GN26+GP26+GR26+GT26+GV26+GX26+GZ26+HB26+HD26+HF26+HH26+HJ26+HL26+HN26+HP26+HR26+HT26+HV26+HX26+HZ26+IB26+ID26+IF26+IH26+IJ26+IL26+IN26+IP26+IR26+IT26+IV26+IX26+IZ26+JB26+JD26+JF26+JH26+JJ26+JL26+JN26+JP26+JR26+JT26+JV26+JX26+JZ26+KB26+KD26+KF26+KH26 -> 0 | G26: =I26+K26+M26+O26+Q26+S26+U26+W26+Y26+AA26+AC26+AE26+AG26+AI26+AK26+AM26+AO26+AQ26+AS26+AU26+AW26+AY26+BA26+BC26+BE26+BG26+BI26+BK26+BM26+BO26+BQ26+BS26+BU26+BW26+BY26+CA26+CC26+CE26+CG26+CI26+CK26+CM26+CN26+CP26+CR26+CT26+CV26+CX26+CZ26+DC26+DE26+DG26+DI26+DK26+DM26+DO26+DQ26+DS26+DU26+DW26+DY26+EA26+EC26+EE26+EG26+EI26+EK26+EM26+EO26+EQ26+ES26+EU26+EW26+EY26+FA26+FC26+FE26+FG26+FI26+FK26+FM26+FO26+FQ26+FS26+FU26+FW26+FY26+GA26+GC26+GE26+GG26+GI26+GK26+GM26+GO26+GQ26+GS26+GU26+GW26+GY26+HA26+HC26+HE26+HG26+HI26+HK26+HM26+HO26+HQ26+HS26+HU26+HW26+HY26+IA26+IC26+IE26+IG26+II26+IK26+IM26+IO26+IQ26+IS26+IU26+IW26+IY26+JA26+JC26+JE26+JG26+JI26+JK26+JM26+JO26+JQ26+JS26+JU26+JW26+JY26+KA26+KC26+KE26+KG26+KI26 -> 0
B27: ='ASE Target (Spares), FY 21-22'!A20 -> 15 | C27: ='ASE Target vs Ach(Spares)(Inpt)'!C28 | D27: ='ASE Target vs Ach(Spares)(Inpt)'!D28 -> New-2 | E27: ='ASE Target vs Ach(Spares)(Inpt)'!E28 | F27: =H27+J27+L27+N27+P27+R27+T27+V27+X27+Z27+AB27+AD27+AF27+AH27+AJ27+AL27+AN27+AP27+AR27+AT27+AV27+AX27+AZ27+BB27+BD27+BF27+BH27+BJ27+BL27+BN27+BP27+BR27+BT27+BV27+BX27+BZ27+CB27+CD27+CF27+CH27+CJ27+CL27+CM27+CO27+CQ27+CS27+CU27+CW27+CY27+DB27+DD27+DF27+DH27+DJ27+DL27+DN27+DP27+DR27+DT27+DV27+DX27+DZ27+EB27+ED27+EF27+EH27+EJ27+EL27+EN27+EP27+ER27+ET27+EV27+EX27+EZ27+FB27+FD27+FF27+FH27+FJ27+FL27+FN27+FP27+FR27+FT27+FV27+FX27+FZ27+GB27+GD27+GF27+GH27+GJ27+GL27+GN27+GP27+GR27+GT27+GV27+GX27+GZ27+HB27+HD27+HF27+HH27+HJ27+HL27+HN27+HP27+HR27+HT27+HV27+HX27+HZ27+IB27+ID27+IF27+IH27+IJ27+IL27+IN27+IP27+IR27+IT27+IV27+IX27+IZ27+JB27+JD27+JF27+JH27+JJ27+JL27+JN27+JP27+JR27+JT27+JV27+JX27+JZ27+KB27+KD27+KF27+KH27 -> 0 | G27: =I27+K27+M27+O27+Q27+S27+U27+W27+Y27+AA27+AC27+AE27+AG27+AI27+AK27+AM27+AO27+AQ27+AS27+AU27+AW27+AY27+BA27+BC27+BE27+BG27+BI27+BK27+BM27+BO27+BQ27+BS27+BU27+BW27+BY27+CA27+CC27+CE27+CG27+CI27+CK27+CM27+CN27+CP27+CR27+CT27+CV27+CX27+CZ27+DC27+DE27+DG27+DI27+DK27+DM27+DO27+DQ27+DS27+DU27+DW27+DY27+EA27+EC27+EE27+EG27+EI27+EK27+EM27+EO27+EQ27+ES27+EU27+EW27+EY27+FA27+FC27+FE27+FG27+FI27+FK27+FM27+FO27+FQ27+FS27+FU27+FW27+FY27+GA27+GC27+GE27+GG27+GI27+GK27+GM27+GO27+GQ27+GS27+GU27+GW27+GY27+HA27+HC27+HE27+HG27+HI27+HK27+HM27+HO27+HQ27+HS27+HU27+HW27+HY27+IA27+IC27+IE27+IG27+II27+IK27+IM27+IO27+IQ27+IS27+IU27+IW27+IY27+JA27+JC27+JE27+JG27+JI27+JK27+JM27+JO27+JQ27+JS27+JU27+JW27+JY27+KA27+KC27+KE27+KG27+KI27 -> 0
B28: ='ASE Target (Spares), FY 21-22'!A21 -> 16 | C28: ='ASE Target vs Ach(Spares)(Inpt)'!C29 | D28: ='ASE Target vs Ach(Spares)(Inpt)'!D29 -> New-3 | E28: ='ASE Target vs Ach(Spares)(Inpt)'!E29 | F28: =H28+J28+L28+N28+P28+R28+T28+V28+X28+Z28+AB28+AD28+AF28+AH28+AJ28+AL28+AN28+AP28+AR28+AT28+AV28+AX28+AZ28+BB28+BD28+BF28+BH28+BJ28+BL28+BN28+BP28+BR28+BT28+BV28+BX28+BZ28+CB28+CD28+CF28+CH28+CJ28+CL28+CM28+CO28+CQ28+CS28+CU28+CW28+CY28+DB28+DD28+DF28+DH28+DJ28+DL28+DN28+DP28+DR28+DT28+DV28+DX28+DZ28+EB28+ED28+EF28+EH28+EJ28+EL28+EN28+EP28+ER28+ET28+EV28+EX28+EZ28+FB28+FD28+FF28+FH28+FJ28+FL28+FN28+FP28+FR28+FT28+FV28+FX28+FZ28+GB28+GD28+GF28+GH28+GJ28+GL28+GN28+GP28+GR28+GT28+GV28+GX28+GZ28+HB28+HD28+HF28+HH28+HJ28+HL28+HN28+HP28+HR28+HT28+HV28+HX28+HZ28+IB28+ID28+IF28+IH28+IJ28+IL28+IN28+IP28+IR28+IT28+IV28+IX28+IZ28+JB28+JD28+JF28+JH28+JJ28+JL28+JN28+JP28+JR28+JT28+JV28+JX28+JZ28+KB28+KD28+KF28+KH28 -> 0 | G28: =I28+K28+M28+O28+Q28+S28+U28+W28+Y28+AA28+AC28+AE28+AG28+AI28+AK28+AM28+AO28+AQ28+AS28+AU28+AW28+AY28+BA28+BC28+BE28+BG28+BI28+BK28+BM28+BO28+BQ28+BS28+BU28+BW28+BY28+CA28+CC28+CE28+CG28+CI28+CK28+CM28+CN28+CP28+CR28+CT28+CV28+CX28+CZ28+DC28+DE28+DG28+DI28+DK28+DM28+DO28+DQ28+DS28+DU28+DW28+DY28+EA28+EC28+EE28+EG28+EI28+EK28+EM28+EO28+EQ28+ES28+EU28+EW28+EY28+FA28+FC28+FE28+FG28+FI28+FK28+FM28+FO28+FQ28+FS28+FU28+FW28+FY28+GA28+GC28+GE28+GG28+GI28+GK28+GM28+GO28+GQ28+GS28+GU28+GW28+GY28+HA28+HC28+HE28+HG28+HI28+HK28+HM28+HO28+HQ28+HS28+HU28+HW28+HY28+IA28+IC28+IE28+IG28+II28+IK28+IM28+IO28+IQ28+IS28+IU28+IW28+IY28+JA28+JC28+JE28+JG28+JI28+JK28+JM28+JO28+JQ28+JS28+JU28+JW28+JY28+KA28+KC28+KE28+KG28+KI28 -> 0
B29: ='ASE Target (Spares), FY 21-22'!A22 -> 17 | C29: ='ASE Target vs Ach(Spares)(Inpt)'!C30 | D29: ='ASE Target vs Ach(Spares)(Inpt)'!D30 -> New-4 | E29: ='ASE Target vs Ach(Spares)(Inpt)'!E30 | F29: =H29+J29+L29+N29+P29+R29+T29+V29+X29+Z29+AB29+AD29+AF29+AH29+AJ29+AL29+AN29+AP29+AR29+AT29+AV29+AX29+AZ29+BB29+BD29+BF29+BH29+BJ29+BL29+BN29+BP29+BR29+BT29+BV29+BX29+BZ29+CB29+CD29+CF29+CH29+CJ29+CL29+CM29+CO29+CQ29+CS29+CU29+CW29+CY29+DB29+DD29+DF29+DH29+DJ29+DL29+DN29+DP29+DR29+DT29+DV29+DX29+DZ29+EB29+ED29+EF29+EH29+EJ29+EL29+EN29+EP29+ER29+ET29+EV29+EX29+EZ29+FB29+FD29+FF29+FH29+FJ29+FL29+FN29+FP29+FR29+FT29+FV29+FX29+FZ29+GB29+GD29+GF29+GH29+GJ29+GL29+GN29+GP29+GR29+GT29+GV29+GX29+GZ29+HB29+HD29+HF29+HH29+HJ29+HL29+HN29+HP29+HR29+HT29+HV29+HX29+HZ29+IB29+ID29+IF29+IH29+IJ29+IL29+IN29+IP29+IR29+IT29+IV29+IX29+IZ29+JB29+JD29+JF29+JH29+JJ29+JL29+JN29+JP29+JR29+JT29+JV29+JX29+JZ29+KB29+KD29+KF29+KH29 -> 0 | G29: =I29+K29+M29+O29+Q29+S29+U29+W29+Y29+AA29+AC29+AE29+AG29+AI29+AK29+AM29+AO29+AQ29+AS29+AU29+AW29+AY29+BA29+BC29+BE29+BG29+BI29+BK29+BM29+BO29+BQ29+BS29+BU29+BW29+BY29+CA29+CC29+CE29+CG29+CI29+CK29+CM29+CN29+CP29+CR29+CT29+CV29+CX29+CZ29+DC29+DE29+DG29+DI29+DK29+DM29+DO29+DQ29+DS29+DU29+DW29+DY29+EA29+EC29+EE29+EG29+EI29+EK29+EM29+EO29+EQ29+ES29+EU29+EW29+EY29+FA29+FC29+FE29+FG29+FI29+FK29+FM29+FO29+FQ29+FS29+FU29+FW29+FY29+GA29+GC29+GE29+GG29+GI29+GK29+GM29+GO29+GQ29+GS29+GU29+GW29+GY29+HA29+HC29+HE29+HG29+HI29+HK29+HM29+HO29+HQ29+HS29+HU29+HW29+HY29+IA29+IC29+IE29+IG29+II29+IK29+IM29+IO29+IQ29+IS29+IU29+IW29+IY29+JA29+JC29+JE29+JG29+JI29+JK29+JM29+JO29+JQ29+JS29+JU29+JW29+JY29+KA29+KC29+KE29+KG29+KI29 -> 0
